Workbook

Sheet Read me
A2: Worksheets Guide
A4: Search Strings | B4: Search strings used in the systematic review
A5: Relevance Ratings | B5: Relevance ratings definitions
A6: References | B6: The list of source documents
A7: Inflation | B7: Inflation indices used to convert to 2017 values
A8: Currency | B8: Exchange rates used to convert to €
A9: Res, Cap, Agg, Pro Costs | B9: The normalised data used in Figures 2-5
A10: Capacity Credit | B10: The data used in Figure 6
A11: Curtailment | B11: The data used in Supplementary Figures 1 and 2 (in Supplementary Information)

Sheet Search Strings
A1: Wind AND (intermittent OR intermittency OR variable generation)
A2: Solar AND (intermittent OR intermittency OR variable generation)
A3: Storage AND (intermittent OR intermittency OR variable generation)
A4: Renewable AND (intermittent OR intermittency OR variable generation)
A5: Network AND (wind OR solar OR storage)
A6: Grid AND (wind OR solar OR storage)
A7: Transmission AND (wind OR solar OR storage)
A8: Capacity credit AND (wind OR solar OR storage)
A9: Capacity margin AND (wind OR solar OR storage)
A10: System reserve AND (wind OR solar OR storage)
A11: System balancing AND (wind OR solar OR storage)
A12: Load factor AND (wind OR solar OR storage)
... A19: Profile cost AND variable renewables

Sheet Relevance Ratings
A1: Relevance rating | B1: Definition
A2: 1 | B2: Article shows clear data on at least one of the terms above
A3: 2 | B3: Article shows clear data on at least one of the terms above, however, misses some data or uses an uncommon metric
A4: 3 | B4: Article mentions at least one of the terms above, however, does not include relevant data
A5: 4 | B5: Irrelevant article or duplicate

Sheet References
A1: Reference ID | B1: Search term | C1: Source | D1: Searched by | E1: Total number of returned documents | F1: Relevant literature | G1: Year | H1: Title | I1: Journal | J1: Leading author | K1: Link | L1: Ann.:
A3: 1 | B3: wind intermittency OR intermittent OR "variable generation" | C3: google scholar | D3: FS | E3: 91700 | F3: 2 | G3: 2007 | H3: The costs of wind’s intermittency in Germany: application of a stochastic electricity market model | I3: Euro. Trans. Electr. Power | J3: DJ Swider | K3: http://onlinelibrary.wiley.com/doi/10.1002/etep.125/pdf
A4: 2 | B4: wind intermittency OR intermittent OR "variable generation" | C4: google scholar | D4: FS | E4: 91700 | F4: 3 | G4: 2009 | H4: Intermittent wind generation in optimal power flow dispatching | I4: Generation, Transmission & Distribution | J4: RA Jabr | K4: http://ieeexplore.ieee.org/xpls/abs_all.jsp?arnumber=4721662&tag=1
A5: 3 | B5: wind intermittency OR intermittent OR "variable generation" | C5: google scholar | D5: FS | E5: 91700 | F5: 3 | G5: 2007 | H5: Controllable and affordable utility-scale electricity from intermittent wind resources and compressed air energy storage (CAES) | I5: Energy | J5: A Cavallo | K5: http://www.sciencedirect.com/science/article/pii/S0360544206000776
A6: 4 | B6: wind intermittency OR intermittent OR "variable generation" | C6: google scholar | D6: FS | E6: 91700 | F6: 2 | G6: 2006 | H6: A Stochastic Unit-commitment Model for the Evaluation of the Impacts of Integration of Large Amounts of Intermittent Wind Power | I6: Probabilistic Methods Applied to Power Systems | J6: R Barth | K6: http://ieeexplore.ieee.org/xpls/abs_all.jsp?arnumber=4202207&tag=1
A7: 5 | B7: wind intermittency OR intermittent OR "variable generation" | C7: google scholar | D7: FS | E7: 91700 | F7: 1 | G7: 2010 | H7: Overview of wind power intermittency impacts on power systems | I7: Electronic Power Systems Research | J7: MH Albadi | K7: http://www.sciencedirect.com/science/article/pii/S0378779609002764
A8: 6 | B8: wind intermittency OR intermittent OR "variable generation" | C8: google scholar | D8: FS | E8: 91700 | F8: 1 | G8: 2006 | H8: The economics of large-scale wind power in a carbon constrained world | I8: Energy Policy | J8: JF DeCarolis | K8: http://www.sciencedirect.com/science/article/pii/S0301421504001740
A9: 7 | B9: wind intermittency OR intermittent OR "variable generation" | C9: google scholar | D9: FS | E9: 91700 | F9: 3 | G9: 2009 | H9: The intermittency of wind, solar, and renewable electricity generators: Technical barrier or rhetorical excuse? | I9: Utilities Policy | J9: BK Sovacool | K9: http://www.sciencedirect.com/science/article/pii/S0957178708000611
A10: 8 | B10: wind intermittency OR intermittent OR "variable generation" | C10: google scholar | D10: FS | E10: 91700 | F10: 3 | G10: 2010 | H10: A review of wind power and wind speed forecasting methods with different time horizons | I10: North American Power Symposium | J10: SS Soman | K10: http://ieeexplore.ieee.org/xpls/abs_all.jsp?arnumber=5619586
A11: 9 | B11: wind intermittency OR intermittent OR "variable generation" | C11: google scholar | D11: FS | E11: 91700 | F11: 2 | G11: 2007 | H11: Supplying Baseload Power and Reducing Transmission Requirements by Interconnecting Wind Farms | I11: J. Appl. Meteor. Climatol. | J11: CL Archer | K11: http://journals.ametsoc.org/doi/abs/10.1175/2007JAMC1538.1
A12: 10 | B12: wind intermittency OR intermittent OR "variable generation" | C12: google scholar | D12: FS | E12: 91700 | F12: 3 | G12: 2010 | H12: Wind Power | I12: Cambridge University Press (Book) | J12: P Musgrove | K12: http://www.langtoninfo.com/web_content/9780521762380_frontmatter.pdf
A13: 11 | B13: wind intermittency OR intermittent OR "variable generation" | C13: google scholar | D13: FS | E13: 91700 | F13: 2 | G13: 2007 | H13: Exploring the impact on cost and electricity production of high penetration levels of intermittent electricity in OECD Europe and the USA, results for wind energy | I13: Energy | J13: M Hoogwijk | K13: http://www.sciencedirect.com/science/article/pii/S0360544206002544
A14: 12 | B14: wind intermittency OR intermittent OR "variable generation" | C14: google scholar | D14: FS | E14: 91700 | F14: 3 | G14: 2008 | H14: Security-Constrained Unit Commitment With Volatile Wind Power Generation | I14: Power Systems | J14: J Wang | K14: http://ieeexplore.ieee.org/xpls/abs_all.jsp?arnumber=4556639
... A192: 190 | B192: Network wind OR solar OR storage | C192: google scholar | D192: FS | E192: 1430000 | F192: 4 | G192: 2012 | H192: A Novel Distributed Direct-Voltage Control Strategy for Grid Integration of Offshore Wind Energy Systems Through MTDC Network | I192: Industrial Electronics | J192: RT Pinto | K192: http://ieeexplore.ieee.org/xpls/abs_all.jsp?arnumber=6290374
A193: 191 | B193: Network wind OR solar OR storage | C193: google scholar | D193: FS | E193: 1430000 | F193: 3 | G193: 2011 | H193: Modal Analysis of a DFIG-Based Wind Farm Interfaced With a Series Compensated Network | I193: Energy Conversion | J193: L Fan | K193: http://ieeexplore.ieee.org/stamp/stamp.jsp?tp=&arnumber=5982088 | L193: intertia - tech
A194: 192 | B194: Network wind OR solar OR storage | C194: google scholar | D194: FS | E194: 1430000 | F194: 4 | G194: 2009 | H194: A review on the forecasting of wind speed and generated power | I194: Renewable and Sustainable Energy Reviews | J194: M Lei | K194: http://www.sciencedirect.com/science/article/pii/S1364032108000282
A195: 193 | B195: Network wind OR solar OR storage | C195: google scholar | D195: FS | E195: 1430000 | F195: 4 | G195: 2011 | H195: Short-term wind power forecasting using ridgelet neural network | I195: Electric Power Systems Research | J195: N Amjady | K195: http://www.sciencedirect.com/science/article/pii/S0378779611001945
A196: 194 | B196: Network wind OR solar OR storage | C196: google scholar | D196: FS | E196: 1430000 | F196: 4 | G196: 2007 | H196: Real-Time and Off-Line Simulation of a Detailed Wind Farm Model Connected to a Multi-Bus Network | I196: Electrical Power Conference | J196: JN Paquin | K196: http://ieeexplore.ieee.org/xpls/abs_all.jsp?arnumber=4520321
A197: 195 | B197: Network wind OR solar OR storage | C197: google scholar | D197: FS | E197: 1430000 | F197: 4 | G197: 2006 | H197: Output power leveling of wind farm using pitch angle control with fuzzy neural network | I197: Power Engineering Society General Meeting | J197: T Senjyu | K197: http://ieeexplore.ieee.org/xpls/abs_all.jsp?arnumber=1709377
A198: 196 | B198: Grid wind OR solar OR storage | C198: google scholar | D198: FS | E198: 1170000 | F198: 3 | G198: 2010 | H198: The economics of using plug-in hybrid electric vehicle battery packs for grid storage | I198: Journal of Power Sources | J198: SB Peterson | K198: http://www.sciencedirect.com/science/article/pii/S0378775309017303
A199: 197 | B199: Grid wind OR solar OR storage | C199: google scholar | D199: FS | E199: 1170000 | F199: 3 | G199: 2011 | H199: Electrical Energy Storage for the Grid: A Battery of Choices | I199: Science | J199: B Dunn | K199: http://www.sciencemag.org/content/334/6058/928.short
A200: 198 | B200: Grid wind OR solar OR storage | C200: google scholar | D200: FS | E200: 1170000 | F200: 4 | G200: 2012 | H200: Battery energy storage and wind energy integrated into the Smart Grid | I200: Innovative Smart Grid Technologies | J200: MC Such | K200: http://ieeexplore.ieee.org/xpl/articleDetails.jsp?arnumber=6175772&tag=1
A201: 199 | B201: Grid wind OR solar OR storage | C201: google scholar | D201: FS | E201: 1170000 | F201: 4 | G201: 2007 | H201: Kriegers flak 640 MW off-shore wind power grid connection—A real project case study | I201: Energy Conversion | J201: D Andersson | K201: http://ieeexplore.ieee.org/xpls/abs_all.jsp?arnumber=4105992
A202: 200 | B202: Grid wind OR solar OR storage | C202: google scholar | D202: FS | E202: 1170000 | F202: 4 | G202: 2010 | H202: A new conversion and control system for a small off-grid wind turbine | I202: Optimization of Electrical and Electronic Equipment (OPTIM) | J202: N Muntean | K202: http://ieeexplore.ieee.org/xpls/abs_all.jsp?arnumber=5510367
A203: 201 | B203: Grid wind OR solar OR storage | C203: google scholar | D203: FS | E203: 1170000 | F203: 4 | G203: 2006 | H203: Control of permanent-magnet generators applied to variable-speed wind-energy systems connected to the grid | I203: Energy Conversion | J203: M Chinchilla | K203: http://ieeexplore.ieee.org/xpls/abs_all.jsp?arnumber=1597329
A204: 202 | B204: Grid wind OR solar OR storage | C204: google scholar | D204: FS | E204: 1170000 | F204: 4 | G204: 2011 | H204: Grid Converters for Photovoltaic and Wind Power Systems | I204: Book | J204: R Teodorescu | K204: https://books.google.co.uk/books?hl=en&lr=&id=5k4tmcVIaM0C&oi=fnd&pg=PP10&dq=Grid++wind+OR+solar+OR+storage&ots=vbPYeH9jws&sig=J0KunCLPuEEUoCzCdfhf8Hj9BAY#v=onepage&q=Grid%20%20wind%20OR%20solar%20OR%20storage&f=false
A205: 203 | B205: Grid wind OR solar OR storage | C205: google scholar | D205: FS | E205: 1170000 | F205: 4 | G205: 2011 | H205: Electrochemical Energy Storage for Green Grid | I205: Chemical Reviews | J205: Z Yang | K205: http://pubs.acs.org/doi/full/10.1021/cr100290v | L205: data from different source but relevant
A206: 204 | B206: Grid wind OR solar OR storage | C206: google scholar | D206: FS | E206: 1170000 | F206: 3 | G206: 2006 | H206: Advanced grid requirements for the integration of wind turbines into the German transmission system | I206: Power Engineering Society General Meeting | J206: I Erlich | K206: http://ieeexplore.ieee.org/xpls/abs_all.jsp?arnumber=1709340
A207: 205 | B207: Grid wind OR solar OR storage | C207: google scholar | D207: FS | E207: 1170000 | F207: 4 | G207: 2010 | H207: Energy Storage Systems for Transport and Grid Applications | I207: Industrial Electronics | J207: S Vazquez | K207: http://ieeexplore.ieee.org/xpls/abs_all.jsp?arnumber=5582228
A208: 206 | B208: Grid wind OR solar OR storage | C208: google scholar | D208: FS | E208: 1170000 | F208: 4 | G208: 2010 | H208: Grid stability battery systems for renewable energy success | I208: Energy Conversion Congress and Exposition | J208: C Vartanian | K208: http://ieeexplore.ieee.org/xpls/abs_all.jsp?arnumber=5618059
A209: 207 | B209: Grid wind OR solar OR storage | C209: google scholar | D209: FS | E209: 1170000 | F209: 3 | G209: 2010 | H209: A Reliability Perspective of the Smart Grid | I209: Smart Grid | J209: K Moslehi | K209: http://ieeexplore.ieee.org/xpls/abs_all.jsp?arnumber=5467283
A210: 208 | B210: Grid wind OR solar OR storage | C210: google scholar | D210: FS | E210: 1170000 | F210: 2 | G210: 2010 | H210: Agent-based micro-storage management for the Smart Grid | I210: AAMAS '10 | J210: P Vytelingum | K210: http://dl.acm.org/citation.cfm?id=1838212
A211: 209 | B211: Grid wind OR solar OR storage | C211: google scholar | D211: FS | E211: 1170000 | F211: 4 | G211: 2010 | H211: A 24-h forecast of solar irradiance using artificial neural network: Application for performance prediction of a grid-connected PV plant at Trieste, Italy | I211: Solar Energy | J211: A Mellit | K211: http://www.sciencedirect.com/science/article/pii/S0038092X10000782
A212: 210 | B212: Grid wind OR solar OR storage | C212: google scholar | D212: FS | E212: 1170000 | F212: 3 | G212: 2008 | H212: Intelligent Scheduling of Hybrid and Electric Vehicle Storage Capacity in a Parking Lot for Profit Maximization in Grid Power Transactions | I212: Energy 2030 Conference | J212: C Hutson | K212: http://ieeexplore.ieee.org/xpls/abs_all.jsp?arnumber=4781051&tag=1
A213: 211 | B213: Grid wind OR solar OR storage | C213: google scholar | D213: FS | E213: 1170000 | F213: 4 | G213: 2010 | H213: Overview of recent grid codes for wind power integration | I213: Optimization of Electrical and Electronic Equipment (OPTIM) | J213: M Altın | K213: http://ieeexplore.ieee.org/xpls/abs_all.jsp?arnumber=5510521&tag=1 | L213: intertia
A214: 212 | B214: Grid wind OR solar OR storage | C214: google scholar | D214: FS | E214: 1170000 | F214: 3 | G214: 2008 | H214: Challenges in integrating distributed Energy storage systems into future smart grid | I214: Industrial Electronics | J214: A Mohd | K214: http://ieeexplore.ieee.org/xpls/abs_all.jsp?arnumber=4676896
A215: 213 | B215: Grid wind OR solar OR storage | C215: google scholar | D215: FS | E215: 1170000 | F215: 4 | G215: 2008 | H215: Stability augmentation of a grid-connected wind farm | I215: Book | J215: SM Muyeen | K215: https://books.google.co.uk/books?hl=en&lr=&id=RYRfCJNm6LcC&oi=fnd&pg=PA1&dq=Grid++wind+OR+solar+OR+storage&ots=t2xJST6S9Q&sig=ZobJF56tPW4JAI-GvJnEreWvlOE#v=onepage&q=Grid%20%20wind%20OR%20solar%20OR%20storage&f=false
A216: 214 | B216: Grid wind OR solar OR storage | C216: google scholar | D216: FS | E216: 1170000 | F216: 3 | G216: 2006 | H216: Integrating Large Wind Farms into Weak Power Grids with Long Transmission Lines | I216: Power Electronics and Motion Control Conference | J216: R Piwko | K216: http://ieeexplore.ieee.org/xpls/abs_all.jsp?arnumber=4778165
A217: 215 | B217: Grid wind OR solar OR storage | C217: google scholar | D217: FS | E217: 1170000 | F217: 1 | G217: 2009 | H217: The economics of wind energy | I217: EWEA Report | J217: Sarah Clifford | K217: https://books.google.co.uk/books?hl=en&lr=&id=3Uv5PEJYwvMC&oi=fnd&pg=PA8&dq=Grid++wind+OR+solar+OR+storage&ots=kQktdkZeGd&sig=dqD-MFyhNK_L1CNlEXbyuvd3lQ0#v=onepage&q=Grid%20%20wind%20OR%20solar%20OR%20storage&f=false
A218: 216 | B218: Grid wind OR solar OR storage | C218: google scholar | D218: FS | E218: 1170000 | F218: 3 | G218: 2010 | H218: Optimal Charging Strategies for Unidirectional Vehicle-to-Grid | I218: Smart Grid | J218: E Sortomme | K218: http://ieeexplore.ieee.org/xpls/abs_all.jsp?arnumber=5661888&tag=1
A219: 217 | B219: Grid wind OR solar OR storage | C219: google scholar | D219: FS | E219: 1170000 | F219: 1 | G219: 2013 | H219: The effect of diurnal profile and seasonal wind regime on sizing grid-connected and off-grid wind power plants | I219: Applied Energy | J219: R Carapellucci | K219: http://www.sciencedirect.com/science/article/pii/S0306261913001529
A220: 218 | B220: Grid wind OR solar OR storage | C220: google scholar | D220: FS | E220: 1170000 | F220: 3 | G220: 2009 | H220: Grid of the future | I220: Power and Energy Magazine | J220: A Ipakchi | K220: http://ieeexplore.ieee.org/xpls/abs_all.jsp?arnumber=4787536&tag=1
A221: 219 | B221: Grid wind OR solar OR storage | C221: google scholar | D221: FS | E221: 1170000 | F221: 3 | G221: 2010 | H221: Smart grid-a reliability perspective | I221: Smart Grid Technologies | J221: K Moslehi | K221: http://ieeexplore.ieee.org/xpls/abs_all.jsp?arnumber=5434765
A222: 220 | B222: Grid wind OR solar OR storage | C222: google scholar | D222: FS | E222: 1170000 | F222: 1 | G222: 2006 | H222: Frequency deviation of thermal power plants due to wind farms | I222: Energy Conversion | J222: C Luo | K222: http://ieeexplore.ieee.org/xpls/abs_all.jsp?arnumber=1677661
A223: 221 | B223: Grid wind OR solar OR storage | C223: google scholar | D223: FS | E223: 1170000 | F223: 2 | G223: 2009 | H223: The value of compressed air energy storage with wind in transmission-constrained electric power systems | I223: Energy Policy | J223: P Denholm | K223: http://www.sciencedirect.com/science/article/pii/S0301421509002328
A224: 222 | B224: Grid wind OR solar OR storage | C224: google scholar | D224: FS | E224: 1170000 | F224: 3 | G224: 2009 | H224: The economics of using PHEV battery packs for grid storage | I224: Carnegie Mellon Electricity Industry Center Working paper | J224: S Peterson | K224: https://wpweb2.tepper.cmu.edu/ceic/PDFS/CEIC_09_03_teo.pdf
A225: 223 | B225: Transmission wind OR solar OR storage | C225: google scholar | D225: FS | E225: 1580000 | F225: 3 | G225: 2011 | H225: Providing all global energy with wind, water, and solar power, Part II: Reliability, system and transmission costs, and policies | I225: Energy Policy | J225: MA Delucchi | K225: http://www.sciencedirect.com/science/article/pii/S0301421510008694
... A322: 320 | B322: Inertia wind OR solar OR storage | C322: google scholar | D322: FS | E322: 17600 | F322: 1 | G322: 2012 | H322: Grid Inertia and Frequency Control in Power Systems with High Penetration of Renewables | I322: Young Researchers Symposium in Electrical Power Engineering | J322: P Tielens | K322: https://lirias.kuleuven.be/handle/123456789/345286
A323: 321 | B323: Inertia wind OR solar OR storage | C323: google scholar | D323: FS | E323: 17600 | F323: 1 | G323: 2007 | H323: Estimation of Wind Penetration as Limited by Frequency Deviation | I323: Energy Conversion | K323: http://ieeexplore.ieee.org/xpls/abs_all.jsp?arnumber=4292192
A324: 322 | B324: Inertia wind OR solar OR storage | C324: google scholar | D324: FS | E324: 17600 | F324: 4 | G324: 2010 | H324: Review on frequency control of power systems with wind power penetration | I324: Power System Technology | J324: YZ Sun | K324: http://ieeexplore.ieee.org/xpls/abs_all.jsp?arnumber=5666151
A325: 323 | B325: Inertia wind OR solar OR storage | C325: google scholar | D325: FS | E325: 17600 | F325: 3 | G325: 2012 | H325: Understanding inertial and frequency response of wind power plants | I325: Power Electronics and Machines in Wind Applications (PEMWA) | J325: E Muljadi | K325: http://ieeexplore.ieee.org/xpls/abs_all.jsp?arnumber=6316361&tag=1
A326: 324 | B326: Inertia wind OR solar OR storage | C326: google scholar | D326: FS | E326: 17600 | F326: 3 | G326: 2006 | H326: Wind energy and power system inertia | I326: Power Engineering Society General Meeting | J326: LVL Abreu | K326: http://ieeexplore.ieee.org/xpls/abs_all.jsp?arnumber=1709240&tag=1
A327: 325 | B327: Inertia wind OR solar OR storage | C327: google scholar | D327: FS | E327: 17600 | F327: 3 | G327: 2007 | H327: Impact of wind farms on a power system. An eigenvalue analysis approach | I327: Renewable Energy | J327: RD Fernandez | K327: http://www.sciencedirect.com/science/article/pii/S0960148106002229
A328: 326 | B328: Inertia wind OR solar OR storage | C328: google scholar | D328: FS | E328: 17600 | F328: 1 | G328: 2010 | H328: Impact on transient and frequency stability for a power system at very high wind penetration | I328: Power and Energy Society General Meeting | J328: L Meegahapola | K328: http://ieeexplore.ieee.org/stamp/stamp.jsp?tp=&arnumber=5589908
A329: 327 | B329: Inertia wind OR solar OR storage | C329: google scholar | D329: FS | E329: 17600 | F329: 1 | G329: 2012 | H329: Frequency Control in Autonomous Power Systems With High Wind Power Penetration | I329: Sustainable Energy | J329: ID Margaris | K329: http://ieeexplore.ieee.org/xpls/abs_all.jsp?arnumber=6170988&tag=1
A330: 328 | B330: Inertia wind OR solar OR storage | C330: google scholar | D330: FS | E330: 17600 | F330: 3 | G330: 2012 | H330: Frequency response of power systems with variable speed wind turbines | I330: Sustainable Energy | J330: L Ruttledge | K330: http://ieeexplore.ieee.org/xpls/abs_all.jsp?arnumber=6289406&tag=1
A331: 329 | B331: Inertia wind OR solar OR storage | C331: google scholar | D331: FS | E331: 17600 | F331: 1 | G331: 2012 | H331: Grid code requirements for artificial inertia control systems in the New Zealand power system | I331: Power and Energy Society General Meeting | J331: MA Pelletier | K331: http://ieeexplore.ieee.org/stamp/stamp.jsp?tp=&arnumber=6345212
A332: 330 | B332: Inertia wind OR solar OR storage | C332: google scholar | D332: FS | E332: 17600 | F332: 2 | G332: 2008 | H332: Impacts of Wind Power Minute-to-Minute Variations on Power System Operation | I332: Power Systems | J332: H Banakar | K332: http://ieeexplore.ieee.org/xpls/abs_all.jsp?arnumber=4435941&tag=1
A333: 331 | B333: Inertia wind OR solar OR storage | C333: google scholar | D333: FS | E333: 17600 | F333: 2 | G333: 2013 | H333: Virtual inertia for variable speed wind turbines | I333: Wind Energy | J333: L Zeni | K333: http://onlinelibrary.wiley.com/doi/10.1002/we.1549/full
A334: 332 | B334: Inertia wind OR solar OR storage | C334: google scholar | D334: FS | E334: 17600 | F334: 3 | G334: 2006 | H334: Wind power impact on system frequency deviation and an ESS based power filtering algorithm solution | I334: Power Systems Conference and Exposition | J334: W Li | K334: http://ieeexplore.ieee.org/xpls/abs_all.jsp?arnumber=4076057
A335: 333 | B335: "Ramp rate" thermal wind OR solar OR storage | C335: google scholar | D335: FS | E335: 14400 | F335: 3 | G335: 2008 | H335: On the use of energy storage technologies for regulation services in electric power systems with significant penetration of wind energy | I335: Electricity Market | J335: B Yang | K335: http://ieeexplore.ieee.org/xpls/abs_all.jsp?arnumber=4579075&tag=1
... A354: 352 | B354: "Power market" intermittent OR intermittency OR variable generation | C354: google scholar | D354: FS | E354: 14200 | F354: 4 | G354: 2011 | H354: The economics of offshore wind | I354: Energy Policy | J354: R Green | K354: http://www.sciencedirect.com/science/article/pii/S0301421510007615
A355: 353 | B355: "Power market" intermittent OR intermittency OR variable generation | C355: google scholar | D355: FS | E355: 14200 | F355: 3 | G355: 2008 | H355: The economic benefit of short-term forecasting for wind energy in the UK electricity market | I355: Renewable Power Generation | J355: H Bevrani | K355: http://ieeexplore.ieee.org/xpls/abs_all.jsp?arnumber=5559317&tag=1 | L355: Cost forecasting
A356: 354 | B356: "Power market" intermittent OR intermittency OR variable generation | C356: google scholar | D356: FS | E356: 14200 | F356: 2 | G356: 2013 | H356: Changes in the economic value of variable generation at high penetration levels: a pilot case study of California | I356: Lawrence Berkeley National Laboratory | J356: A Mills | K356: http://escholarship.org/uc/item/2g7677hn#page-1
A357: 355 | B357: "Power market" intermittent OR intermittency OR variable generation | C357: google scholar | D357: FS | E357: 14200 | F357: 1 | G357: 2013 | H357: System LCOE: What are the costs of variable renewables? | I357: Energy | J357: F Ueckerdt | K357: http://www.sciencedirect.com/science/article/pii/S0360544213009390
A358: 356 | B358: "Power market" intermittent OR intermittency OR variable generation | C358: google scholar | D358: FS | E358: 14200 | F358: 2 | G358: 2008 | H358: Conditions and costs for renewables electricity grid connection: examples in Europe | I358: Renewable Energy | J358: DJ Swider | K358: http://www.sciencedirect.com/science/article/pii/S0960148107003631 | L358: Grid connection costs
A359: 357 | B359: "Power market" intermittent OR intermittency OR variable generation | C359: google scholar | D359: FS | E359: 14200 | F359: 3 | G359: 2010 | H359: Supplying renewable energy to deferrable loads: Algorithms and economic analysis | I359: Power and Energy Society General Meeting | J359: A Papavasiliou | K359: http://ieeexplore.ieee.org/stamp/stamp.jsp?tp=&arnumber=5589405
A360: 358 | B360: "Power market" intermittent OR intermittency OR variable generation | C360: google scholar | D360: FS | E360: 14200 | F360: 3 | G360: 2010 | H360: Coordination of intermittent generation with storage, demand control and conventional energy sources | I360: Bulk Power System Dynamics and Control (iREP) | J360: G Hug-Glanzmann | K360: http://ieeexplore.ieee.org/xpls/abs_all.jsp?arnumber=5563304
A361: 359 | B361: "Power market" intermittent OR intermittency OR variable generation | C361: google scholar | D361: FS | E361: 14200 | F361: 3 | G361: 2011 | H361: Impact of wind power on the unit commitment, operating reserves, and market design | I361: Power and Energy Society General Meeting | J361: J Kiviluoma | K361: http://ieeexplore.ieee.org/xpls/abs_all.jsp?arnumber=6039621
A362: 360 | B362: "Power market" intermittent OR intermittency OR variable generation | C362: google scholar | D362: FS | E362: 14200 | F362: 2 | G362: 2011 | H362: Sizing Energy Storage to Accommodate High Penetration of Variable Energy Resources | I362: Sustainable Energy | J362: YV Makarov | K362: http://ieeexplore.ieee.org/xpls/abs_all.jsp?arnumber=6095383
A363: 361 | B363: "Power market" intermittent OR intermittency OR variable generation | C363: google scholar | D363: FS | E363: 14200 | F363: 2 | G363: 2008 | H363: Models for Quantifying the Economic Benefits of Distributed Generation | I363: Power Systems | J363: HA Gil | K363: http://ieeexplore.ieee.org/xpls/abs_all.jsp?arnumber=4494597
A364: 362 | B364: "Power market" intermittent OR intermittency OR variable generation | C364: google scholar | D364: FS | E364: 14200 | F364: 1 | G364: 2010 | H364: Modelling An Integrated Northern European Regulating Power Market Based On A Common Day-Ahead Market | I364: The Future of Energy: Global Challenges, Diverse Solutions | J364: G Doorman | K364: http://brage.bibsys.no/xmlui/handle/11250/256992
A365: 363 | B365: "Power market" intermittent OR intermittency OR variable generation | C365: google scholar | D365: FS | E365: 14200 | F365: 2 | G365: 2011 | H365: Challenges and options for a large wind power uptake by the European electricity system | I365: Applied Energy | J365: A Purvins | K365: http://www.sciencedirect.com/science/article/pii/S0306261910005246
A366: 364 | B366: Institutions | C366: google | D366: FS | E366: n/a | F366: 2 | G366: 2012 | H366: Understanding the Balancing Challenge | I366: Report | J366: Imperial College & NERA | K366: https://www.gov.uk/government/uploads/system/uploads/attachment_data/file/48553/5767-understanding-the-balancing-challenge.pdf
A367: 365 | B367: Institutions | C367: google | D367: FS | E367: n/a | F367: 3 | G367: 2014 | H367: Intermittent Electricity Generation | I367: Postnote | J367: House of Parlament | K367: http://www.google.de/url?sa=t&rct=j&q=&esrc=s&source=web&cd=3&ved=0CC8QFjACahUKEwib18CwkdHIAhWHsxQKHSBEBZk&url=http%3A%2F%2Fresearchbriefings.files.parliament.uk%2Fdocuments%2FPOST-PN-464%2FPOST-PN-464.pdf&usg=AFQjCNE22Jnw3zXh0gEwlaC09_QU0LOdig
A368: 366 | B368: Institutions | C368: google | D368: FS | E368: n/a | F368: 2 | G368: 2014 | H368: Electricity Capacity Assessment Report | I368: Report | J368: OFGEM | K368: https://www.ofgem.gov.uk/ofgem-publications/88523/electricitycapacityassessment2014-fullreportfinalforpublication.pdf
A369: 367 | B369: Institutions | C369: google | D369: FS | E369: n/a | F369: 3 | G369: 2015 | H369: Electricity Ten Year Statement | I369: Report | J369: National Grid | K369: http://www2.nationalgrid.com/UK/Industry-information/Future-of-Energy/Electricity-Ten-Year-Statement/
A370: 368 | B370: Institutions | C370: google | D370: FS | E370: n/a | F370: 3 | G370: 2014 | H370: UK Future Energy Scenarios | I370: Report | J370: National Grid | K370: http://www.bre.co.uk/filelibrary/nsc/Documents%20Library/National%20Grid/NAT-G_Info_UK-FES_0714.pdf
A371: 369 | B371: Institutions | C371: google | D371: FS | E371: n/a | F371: 1 | G371: 2015 | H371: Winter Outlook Report | I371: Report | J371: National Grid | K371: http://www2.nationalgrid.com/UK/Industry-information/Future-of-Energy/FES/Winter-Outlook/
A372: 370 | B372: Institutions | C372: google | D372: FS | E372: n/a | F372: 4 | G372: 2014 | H372: Energy Trends | I372: Report | J372: DECC | K372: https://www.gov.uk/government/uploads/system/uploads/attachment_data/file/295362/ET_March_2014.PDF
A373: 371 | B373: Institutions | C373: google | D373: FS | E373: n/a | F373: 3 | G373: 2013 | H373: Statutory Security of Supply Report | I373: Report | J373: DECC / OFGEM | K373: https://www.gov.uk/government/uploads/system/uploads/attachment_data/file/261604/HC_675_updated_accessible.pdf
A374: 372 | B374: Institutions | C374: google | D374: FS | E374: n/a | F374: 2 | G374: 2011 | H374: Operating the Electricity Transmission Networks in 2020 | I374: Report | J374: National Grid | K374: http://www.nationalgrid.com/NR/rdonlyres/DF928C19-9210-4629-AB78-BBAA7AD8B89D/47178/Operatingin2020_finalversion0806_final.pdf
A375: 373 | B375: Institutions | C375: google | D375: FS | E375: n/a | F375: 3 | G375: 2012 | H375: Flexible Technology Options: Priorities for Innovation | I375: Report | J375: Energy Research Partnership | K375: http://erpuk.org/project/flexible-technology-options-priorities-for-innovation/
A376: 374 | B376: Institutions | C376: google | D376: FS | E376: n/a | F376: 1 | G376: 2012 | H376: Nuclear Energy and Renewables | I376: Report | J376: Nuclear Energy Agency, OECD | K376: https://www.oecd-nea.org/ndd/pubs/2012/7056-system-effects.pdf
A377: 375 | B377: Institutions | C377: google | D377: FS | E377: n/a | F377: 3 | G377: 2010 | H377: Brattle Report - Alternative Trading Arrangements for Intermittent Renewable Power | I377: Report | J377: OFGEM | K377: https://www.ofgem.gov.uk/publications-and-updates/brattle-report-alternative-trading-arrangements-intermittent-renewable-power
... A419: 417 | B419: Already known' documents | C419: n/a | D419: PH | E419: n/a | F419: 3 | G419: 2014 | H419: Cost and revenue related impacts of integrating impacts of integrating electricity from variable renewable energy into the power system - A review of recent literature | I419: ECN report | J419: J Sijm | K419: ftp://ftp.ecn.nl/pub/www/library/report/2014/e14022.pdf
A420: 418 | B420: Already known' documents | C420: n/a | D420: PH | E420: n/a | F420: 1 | G420: 2014 | H420: Imperial College' report cited in Frontier Economics 2015 report but not in their ref list! | I420: Report for DECC | J420: Frontier Economics
A421: 419 | B421: Already known' documents | C421: n/a | D421: PH | E421: n/a | F421: 2 | G421: 2013 | H421: Revision of reserve requirements following wind power integration in island power systems | I421: Renewable Energy | J421: K De Vos | K421: http://www.sciencedirect.com/science/article/pii/S0960148112003990
A422: 420 | B422: Already known' documents | C422: n/a | D422: PH | E422: n/a | F422: 3 | G422: 2011 | H422: Impacts of Wind Generation Integration | I422: EPRI report | J422: EPRI | K422: http://www.epri.com/abstracts/pages/productabstract.aspx?ProductID=000000000001023166
A423: 421 | B423: Already known' documents | C423: n/a | D423: PH | E423: n/a | F423: 3 | G423: 2009 | H423: Quantifying the system balancing cost when wind energy is incorporated into electricity generation system | I423: PhD thesis | J423: N Issaeva | K423: https://www.era.lib.ed.ac.uk/handle/1842/3804
A424: 422 | B424: Already known' documents | C424: n/a | D424: PH | E424: n/a | F424: 2 | G424: 2012 | H424: The cost of wind power variability | I424: Energy Policy | J424: W Katzenstein | K424: http://www.sciencedirect.com/science/article/pii/S0301421512006246
A425: 423 | B425: Already known' documents | C425: n/a | D425: PH | E425: n/a | F425: 3 | G425: 2011 | H425: Impact Assessment Of Increasing Unpredictability In Gas Balancing Caused By Massive Wind Power Integration | I425: TME working paper | J425: N Keyaerts | K425: https://www.mech.kuleuven.be/en/tme/research/energy_environment/Pdf/wp-en2011-05.pdf
A426: 424 | B426: Already known' documents | C426: n/a | D426: PH | E426: n/a | F426: 2 | G426: 2012 | H426: Renewable energy deployment - do the benefits outweigh the costs? | I426: GWS Discussion Paper | J426: U Lehr | K426: https://www.econstor.eu/dspace/bitstream/10419/94390/1/gws-paper12-5.pdf
A427: 425 | B427: Already known' documents | C427: n/a | D427: PH | E427: n/a | F427: 1 | G427: 2009 | H427: Operational costs induced by fluctuating wind power production in Germany and Scandinavia | I427: IET Renewable Power Generation | J427: P Meibom | K427: http://ieeexplore.ieee.org/xpls/abs_all.jsp?arnumber=4694984
A428: 426 | B428: Already known' documents | C428: n/a | D428: PH | E428: n/a | F428: 3 | G428: 2013 | H428: A Review of Variable Generation Integration Charges | I428: NREL technical report | J428: K Porter | K428: http://www.nrel.gov/docs/fy13osti/57583.pdf
A429: 427 | B429: Already known' documents | C429: n/a | D429: PH | E429: n/a | F429: 2 | G429: 2013 | H429: The Western Wind and Solar Integration Study Phase 2 | I429: NREL technical report | J429: D Lew | K429: https://www.researchgate.net/profile/Eduardo_Ibanez/publication/273000140_The_Western_Wind_and_Solar_Integration_Study_Phase_2/links/54f485ab0cf2ba6150634872.pdf
A430: 428 | B430: Already known' documents | C430: n/a | D430: PH | E430: n/a | F430: 2 | G430: 2008 | H430: All Island Electricity Grid Study | I430: Report for DECNR | J430: Various | K430: http://www.eirgrid.com/renewables/all-islandgridstudy/
A431: 429 | B431: Already known' documents | C431: n/a | D431: PH | E431: n/a | F431: 2 | G431: 2010 | H431: Facilitation of Renewables | I431: Report for EirGrid and SONI | J431: ECOFYS | K431: http://www.eirgrid.com/renewables/facilitationofrenewables/
A432: 430 | B432: Already known' documents | C432: n/a | D432: PH | E432: n/a | F432: 2 | G432: 2013 | H432: Exploration of the integration of renewable resources into California's electric system using the Holistic Grid Resource Integration and Deployment (HiGRID) tool | I432: Energy | J432: J Eichman | K432: http://www.sciencedirect.com/science/article/pii/S0360544212008857
... A459: 457 | B459: Follow-on from 347 | C459: n/a | D459: PH | E459: n/a | F459: 1 | G459: 2015 | H459: Integration costs revisited – An economic framework for wind and solar variability | I459: Renewable Energy | J459: Hirth | K459: https://www.sciencedirect.com/science/article/pii/S0960148114005357?via%3Dihub
...

Sheet Res, Cap, Agg, Pro Costs
A1: Operating reserve Costs | F1: Capacity Costs | K1: Aggregated Costs | T1: Profile Costs
A2: ID | B2: Penetration level | C2: 2017 €/MWh | D2: Region | F2: ID | G2: Penetration level | H2: 2017 €/MWh | I2: Region | K2: ID | L2: Year | M2: CCY | N2: Penetration level | O2: 2015 £/MWh | P2: 2017 €/MWh | Q2: Region | R2: Notes | T2: ID | U2: Year | V2: CCY | W2: Penetration level | X2: Reported value | Y2: 2017 €/MWh | Z2: Region | AA2: Notes
A3: 17 | B3: 0.4 | C3: 26.232572 | D3: n/a | F3: 50 | G3: 0.2 | H3: 0.92899907 | I3: UK | K3: 403/455 | L3: 2015 | M3: GBP | N3: 0.364 | O3: 6.4 | P3: =O3*(1/(INDEX(Currency!$A$1:$E$20,MATCH(L3,Currency!$A$1:$A$20,0),MATCH(M3,Currency!$A$1:$E$1,0))))*(Inflation!$B$23/(VLOOKUP(L3,Inflation!$A$1:$B$23,2,FALSE))) -> 8.9942435 | Q3: UK | R3: Offshore wind, CCC 2015 | T3: 347 | U3: 2001 | V3: EUR | W3: 0.02 | X3: -1 | Y3: =X3*(1/(INDEX(Currency!$A$1:$E$20,MATCH(U3,Currency!$A$1:$A$20,0),MATCH(V3,Currency!$A$1:$E$1,0))))*(Inflation!$B$23/(VLOOKUP(U3,Inflation!$A$1:$B$23,2,FALSE))) -> -1.3352102 | Z3: Germany | AA3: Wind, Table 3
A4: 17 | B4: 0.8 | C4: 17.657365 | D4: n/a | F4: 400 | G4: 0.02 | H4: 6.1507992 | I4: in Austria | K4: 403/455 | L4: 2015 | M4: GBP | N4: 0.363 | O4: 13.6 | P4: =O4*(1/(INDEX(Currency!$A$1:$E$20,MATCH(L4,Currency!$A$1:$A$20,0),MATCH(M4,Currency!$A$1:$E$1,0))))*(Inflation!$B$23/(VLOOKUP(L4,Inflation!$A$1:$B$23,2,FALSE))) -> 19.112767 | Q4: UK | R4: Offshore wind, CCC 2015 | T4: 347 | U4: 2004 | V4: EUR | W4: 0.03 | X4: 0 | Y4: =X4*(1/(INDEX(Currency!$A$1:$E$20,MATCH(U4,Currency!$A$1:$A$20,0),MATCH(V4,Currency!$A$1:$E$1,0))))*(Inflation!$B$23/(VLOOKUP(U4,Inflation!$A$1:$B$23,2,FALSE))) -> 0 | Z4: Germany | AA4: Wind, Table 3
A5: 50 | B5: 0.04 | C5: 0.034407373 | D5: UK | F5: 400 | G5: 0.04 | H5: 8.5086056 | I5: in Austria | K5: 403/455 | L5: 2015 | M5: GBP | N5: 0.361 | O5: 23 | P5: =O5*(1/(INDEX(Currency!$A$1:$E$20,MATCH(L5,Currency!$A$1:$A$20,0),MATCH(M5,Currency!$A$1:$E$1,0))))*(Inflation!$B$23/(VLOOKUP(L5,Inflation!$A$1:$B$23,2,FALSE))) -> 32.323062 | Q5: UK | R5: Offshore wind, CCC 2015 | T5: 347 | U5: 2005 | V5: EUR | W5: 0.035 | X5: 0 | Y5: =X5*(1/(INDEX(Currency!$A$1:$E$20,MATCH(U5,Currency!$A$1:$A$20,0),MATCH(V5,Currency!$A$1:$E$1,0))))*(Inflation!$B$23/(VLOOKUP(U5,Inflation!$A$1:$B$23,2,FALSE))) -> 0 | Z5: Germany | AA5: Wind, Table 3
A6: 50 | B6: 0.08 | C6: 0.13762949 | D6: UK | F6: 400 | G6: 0.06 | H6: 10.866412 | I6: in Austria | K6: 403/455 | L6: 2015 | M6: GBP | N6: 0.47 | O6: 36.9 | P6: =O6*(1/(INDEX(Currency!$A$1:$E$20,MATCH(L6,Currency!$A$1:$A$20,0),MATCH(M6,Currency!$A$1:$E$1,0))))*(Inflation!$B$23/(VLOOKUP(L6,Inflation!$A$1:$B$23,2,FALSE))) -> 51.857435 | Q6: UK | R6: Offshore wind, CCC 2015 | T6: 347 | U6: 2006 | V6: EUR | W6: 0.047 | X6: 2 | Y6: =X6*(1/(INDEX(Currency!$A$1:$E$20,MATCH(U6,Currency!$A$1:$A$20,0),MATCH(V6,Currency!$A$1:$E$1,0))))*(Inflation!$B$23/(VLOOKUP(U6,Inflation!$A$1:$B$23,2,FALSE))) -> 2.4086453 | Z6: Germany | AA6: Wind, Table 3
A7: 50 | B7: 0.12 | C7: 0.2580553 | D7: UK | F7: 400 | G7: 0.08 | H7: 11.994059 | I7: in Austria | K7: 403/455 | L7: 2015 | M7: GBP | N7: 0.48 | O7: 35.4 | P7: =O7*(1/(INDEX(Currency!$A$1:$E$20,MATCH(L7,Currency!$A$1:$A$20,0),MATCH(M7,Currency!$A$1:$E$1,0))))*(Inflation!$B$23/(VLOOKUP(L7,Inflation!$A$1:$B$23,2,FALSE))) -> 49.749409 | Q7: UK | R7: Offshore wind, CCC 2015 | T7: 347 | U7: 2007 | V7: EUR | W7: 0.049 | X7: 5 | Y7: =X7*(1/(INDEX(Currency!$A$1:$E$20,MATCH(U7,Currency!$A$1:$A$20,0),MATCH(V7,Currency!$A$1:$E$1,0))))*(Inflation!$B$23/(VLOOKUP(U7,Inflation!$A$1:$B$23,2,FALSE))) -> 5.8840162 | Z7: Germany | AA7: Wind, Table 3
A8: 50 | B8: 0.16 | C8: 0.3784811 | D8: UK | F8: 400 | G8: 0.1 | H8: 12.609138 | I8: in Austria | K8: 403/455 | L8: 2015 | M8: GBP | N8: 0.512 | O8: 13.9 | P8: =O8*(1/(INDEX(Currency!$A$1:$E$20,MATCH(L8,Currency!$A$1:$A$20,0),MATCH(M8,Currency!$A$1:$E$1,0))))*(Inflation!$B$23/(VLOOKUP(L8,Inflation!$A$1:$B$23,2,FALSE))) -> 19.534373 | Q8: UK | R8: Offshore wind, CCC 2015 | T8: 347 | U8: 2008 | V8: EUR | W8: 0.055 | X8: 6 | Y8: =X8*(1/(INDEX(Currency!$A$1:$E$20,MATCH(U8,Currency!$A$1:$A$20,0),MATCH(V8,Currency!$A$1:$E$1,0))))*(Inflation!$B$23/(VLOOKUP(U8,Inflation!$A$1:$B$23,2,FALSE))) -> 6.8116232 | Z8: Germany | AA8: Wind, Table 3
A9: 50 | B9: 0.2 | C9: 0.51611059 | D9: UK | F9: 400 | G9: 0.12 | H9: 13.121705 | I9: in Austria | K9: 403/455 | L9: 2015 | M9: GBP | N9: 0.518 | O9: 12.8 | P9: =O9*(1/(INDEX(Currency!$A$1:$E$20,MATCH(L9,Currency!$A$1:$A$20,0),MATCH(M9,Currency!$A$1:$E$1,0))))*(Inflation!$B$23/(VLOOKUP(L9,Inflation!$A$1:$B$23,2,FALSE))) -> 17.988487 | Q9: UK | R9: Offshore wind, CCC 2015 | T9: 347 | U9: 2009 | V9: EUR | W9: 0.071 | X9: 3 | Y9: =X9*(1/(INDEX(Currency!$A$1:$E$20,MATCH(U9,Currency!$A$1:$A$20,0),MATCH(V9,Currency!$A$1:$E$1,0))))*(Inflation!$B$23/(VLOOKUP(U9,Inflation!$A$1:$B$23,2,FALSE))) -> 3.3723955 | Z9: Germany | AA9: Wind, Table 3
A10: 50 | B10: 0.04 | C10: 0.086018432 | D10: UK | F10: 400 | G10: 0.14 | H10: 13.531758 | I10: in Austria | K10: 403/455 | L10: 2015 | M10: GBP | N10: 0.513 | O10: 7.1 | P10: =O10*(1/(INDEX(Currency!$A$1:$E$20,MATCH(L10,Currency!$A$1:$A$20,0),MATCH(M10,Currency!$A$1:$E$1,0))))*(Inflation!$B$23/(VLOOKUP(L10,Inflation!$A$1:$B$23,2,FALSE))) -> 9.9779888 | Q10: UK | R10: Offshore wind, CCC 2015 | T10: 347 | U10: 2010 | V10: EUR | W10: 0.073 | X10: 2 | Y10: =X10*(1/(INDEX(Currency!$A$1:$E$20,MATCH(U10,Currency!$A$1:$A$20,0),MATCH(V10,Currency!$A$1:$E$1,0))))*(Inflation!$B$23/(VLOOKUP(U10,Inflation!$A$1:$B$23,2,FALSE))) -> 2.2023758 | Z10: Germany | AA10: Wind, Table 3
A11: 50 | B11: 0.08 | C11: 0.2580553 | D11: UK | F11: 400 | G11: 0.16 | H11: 13.736785 | I11: in Austria | K11: 403/455 | L11: 2015 | M11: GBP | N11: 0.519 | O11: 8.2 | P11: =O11*(1/(INDEX(Currency!$A$1:$E$20,MATCH(L11,Currency!$A$1:$A$20,0),MATCH(M11,Currency!$A$1:$E$1,0))))*(Inflation!$B$23/(VLOOKUP(L11,Inflation!$A$1:$B$23,2,FALSE))) -> 11.523874 | Q11: UK | R11: Offshore wind, CCC 2015 | T11: 347 | U11: 2011 | V11: EUR | W11: 0.088 | X11: 3 | Y11: =X11*(1/(INDEX(Currency!$A$1:$E$20,MATCH(U11,Currency!$A$1:$A$20,0),MATCH(V11,Currency!$A$1:$E$1,0))))*(Inflation!$B$23/(VLOOKUP(U11,Inflation!$A$1:$B$23,2,FALSE))) -> 3.2042526 | Z11: Germany | AA11: Wind, Table 3
A12: 50 | B12: 0.12 | C12: 0.46449953 | D12: UK | F12: 400 | G12: 0.18 | H12: 13.941812 | I12: in Austria | K12: 456 | L12: 2015 | M12: GBP | N12: 0.266 | O12: 10.6 | P12: =O12*(1/(INDEX(Currency!$A$1:$E$20,MATCH(L12,Currency!$A$1:$A$20,0),MATCH(M12,Currency!$A$1:$E$1,0))))*(Inflation!$B$23/(VLOOKUP(L12,Inflation!$A$1:$B$23,2,FALSE))) -> 14.896716 | Q12: UK | R12: Offshore wind, No progress | T12: 347 | U12: 2012 | V12: EUR | W12: 0.08 | X12: 5 | Y12: =X12*(1/(INDEX(Currency!$A$1:$E$20,MATCH(U12,Currency!$A$1:$A$20,0),MATCH(V12,Currency!$A$1:$E$1,0))))*(Inflation!$B$23/(VLOOKUP(U12,Inflation!$A$1:$B$23,2,FALSE))) -> 5.2030819 | Z12: Germany | AA12: Wind, Table 3
A13: 50 | B13: 0.16 | C13: 0.70535114 | D13: UK | F13: 400 | G13: 0.02 | H13: 6.1507992 | I13: in Austria | K13: 456 | L13: 2015 | M13: GBP | N13: 0.37 | O13: 31.8 | P13: =O13*(1/(INDEX(Currency!$A$1:$E$20,MATCH(L13,Currency!$A$1:$A$20,0),MATCH(M13,Currency!$A$1:$E$1,0))))*(Inflation!$B$23/(VLOOKUP(L13,Inflation!$A$1:$B$23,2,FALSE))) -> 44.690147 | Q13: UK | R13: Offshore wind, No progress | T13: 347 | U13: 2006 | V13: EUR | W13: 0.004 | X13: -17 | Y13: =X13*(1/(INDEX(Currency!$A$1:$E$20,MATCH(U13,Currency!$A$1:$A$20,0),MATCH(V13,Currency!$A$1:$E$1,0))))*(Inflation!$B$23/(VLOOKUP(U13,Inflation!$A$1:$B$23,2,FALSE))) -> -20.473485 | Z13: Germany | AA13: Solar, Table 3
A14: 50 | B14: 0.2 | C14: 0.94620275 | D14: UK | F14: 400 | G14: 0.04 | H14: 8.5086056 | I14: in Austria | K14: 456 | L14: 2015 | M14: GBP | N14: 0.504 | O14: 48.4 | P14: =O14*(1/(INDEX(Currency!$A$1:$E$20,MATCH(L14,Currency!$A$1:$A$20,0),MATCH(M14,Currency!$A$1:$E$1,0))))*(Inflation!$B$23/(VLOOKUP(L14,Inflation!$A$1:$B$23,2,FALSE))) -> 68.018966 | Q14: UK | R14: Offshore wind, No progress | T14: 347 | U14: 2007 | V14: EUR | W14: 0.005 | X14: -6 | Y14: =X14*(1/(INDEX(Currency!$A$1:$E$20,MATCH(U14,Currency!$A$1:$A$20,0),MATCH(V14,Currency!$A$1:$E$1,0))))*(Inflation!$B$23/(VLOOKUP(U14,Inflation!$A$1:$B$23,2,FALSE))) -> -7.0608194 | Z14: Germany | AA14: Solar, Table 3
A15: 336 | B15: 0.33 | C15: 20.232619 | D15: California | F15: 400 | G15: 0.06 | H15: 10.558872 | I15: in Austria | K15: 456 | L15: 2015 | M15: GBP | N15: 0.266 | O15: 10.2 | P15: =O15*(1/(INDEX(Currency!$A$1:$E$20,MATCH(L15,Currency!$A$1:$A$20,0),MATCH(M15,Currency!$A$1:$E$1,0))))*(Inflation!$B$23/(VLOOKUP(L15,Inflation!$A$1:$B$23,2,FALSE))) -> 14.334576 | Q15: UK | R15: Offshore wind, Moderate progress | T15: 347 | U15: 2008 | V15: EUR | W15: 0.007 | X15: -16 | Y15: =X15*(1/(INDEX(Currency!$A$1:$E$20,MATCH(U15,Currency!$A$1:$A$20,0),MATCH(V15,Currency!$A$1:$E$1,0))))*(Inflation!$B$23/(VLOOKUP(U15,Inflation!$A$1:$B$23,2,FALSE))) -> -18.164329 | Z15: Germany | AA15: Solar, Table 3
A16: 355 | B16: 0.05 | C16: 3.3665374 | D16: EU | F16: 400 | G16: 0.08 | H16: 10.558872 | I16: in Austria | K16: 456 | L16: 2015 | M16: GBP | N16: 0.37 | O16: 11 | P16: =O16*(1/(INDEX(Currency!$A$1:$E$20,MATCH(L16,Currency!$A$1:$A$20,0),MATCH(M16,Currency!$A$1:$E$1,0))))*(Inflation!$B$23/(VLOOKUP(L16,Inflation!$A$1:$B$23,2,FALSE))) -> 15.458856 | Q16: UK | R16: Offshore wind, Moderate progress | T16: 347 | U16: 2009 | V16: EUR | W16: 0.011 | X16: -5 | Y16: =X16*(1/(INDEX(Currency!$A$1:$E$20,MATCH(U16,Currency!$A$1:$A$20,0),MATCH(V16,Currency!$A$1:$E$1,0))))*(Inflation!$B$23/(VLOOKUP(U16,Inflation!$A$1:$B$23,2,FALSE))) -> -5.6206592 | Z16: Germany | AA16: Solar, Table 3
A17: 355 | B17: 0.1 | C17: 4.1415382 | D17: EU | F17: 400 | G17: 0.1 | H17: 11.276465 | I17: in Austria | K17: 456 | L17: 2015 | M17: GBP | N17: 0.47 | O17: 11.2 | P17: =O17*(1/(INDEX(Currency!$A$1:$E$20,MATCH(L17,Currency!$A$1:$A$20,0),MATCH(M17,Currency!$A$1:$E$1,0))))*(Inflation!$B$23/(VLOOKUP(L17,Inflation!$A$1:$B$23,2,FALSE))) -> 15.739926 | Q17: UK | R17: Offshore wind, Moderate progress | T17: 347 | U17: 2010 | V17: EUR | W17: 0.021 | X17: -5 | Y17: =X17*(1/(INDEX(Currency!$A$1:$E$20,MATCH(U17,Currency!$A$1:$A$20,0),MATCH(V17,Currency!$A$1:$E$1,0))))*(Inflation!$B$23/(VLOOKUP(U17,Inflation!$A$1:$B$23,2,FALSE))) -> -5.5059395 | Z17: Germany | AA17: Solar, Table 3
A18: 355 | B18: 0.15 | C18: 4.2235488 | D18: EU | F18: 400 | G18: 0.12 | H18: 11.686519 | I18: in Austria | K18: 456 | L18: 2015 | M18: GBP | N18: 0.265 | O18: 6.6 | P18: =O18*(1/(INDEX(Currency!$A$1:$E$20,MATCH(L18,Currency!$A$1:$A$20,0),MATCH(M18,Currency!$A$1:$E$1,0))))*(Inflation!$B$23/(VLOOKUP(L18,Inflation!$A$1:$B$23,2,FALSE))) -> 9.2753136 | Q18: UK | R18: Offshore wind, Fast progress | T18: 347 | U18: 2011 | V18: EUR | W18: 0.033 | X18: -5 | Y18: =X18*(1/(INDEX(Currency!$A$1:$E$20,MATCH(U18,Currency!$A$1:$A$20,0),MATCH(V18,Currency!$A$1:$E$1,0))))*(Inflation!$B$23/(VLOOKUP(U18,Inflation!$A$1:$B$23,2,FALSE))) -> -5.3404211 | Z18: Germany | AA18: Solar, Table 3
A19: 355 | B19: 0.2 | C19: 4.2368755 | D19: EU | F19: 400 | G19: 0.14 | H19: 12.096572 | I19: in Austria | K19: 456 | L19: 2015 | M19: GBP | N19: 0.279 | O19: 7.4 | P19: =O19*(1/(INDEX(Currency!$A$1:$E$20,MATCH(L19,Currency!$A$1:$A$20,0),MATCH(M19,Currency!$A$1:$E$1,0))))*(Inflation!$B$23/(VLOOKUP(L19,Inflation!$A$1:$B$23,2,FALSE))) -> 10.399594 | Q19: UK | R19: Offshore wind, Fast progress | T19: 347 | U19: 2012 | V19: EUR | W19: 0.045 | X19: -2 | Y19: =X19*(1/(INDEX(Currency!$A$1:$E$20,MATCH(U19,Currency!$A$1:$A$20,0),MATCH(V19,Currency!$A$1:$E$1,0))))*(Inflation!$B$23/(VLOOKUP(U19,Inflation!$A$1:$B$23,2,FALSE))) -> -2.0812328 | Z19: Germany | AA19: Solar, Table 3
A20: 355 | B20: 0.25 | C20: 4.663331 | D20: EU | F20: 400 | G20: 0.16 | H20: 12.301598 | I20: in Austria | K20: 456 | L20: 2015 | M20: GBP | N20: 0.355 | O20: 7.7 | P20: =O20*(1/(INDEX(Currency!$A$1:$E$20,MATCH(L20,Currency!$A$1:$A$20,0),MATCH(M20,Currency!$A$1:$E$1,0))))*(Inflation!$B$23/(VLOOKUP(L20,Inflation!$A$1:$B$23,2,FALSE))) -> 10.821199 | Q20: UK | R20: Offshore wind, Fast progress | T20: 347 | U20: 2013 | V20: EUR | W20: 0.1 | X20: 8.4 | Y20: =X20*(1/(INDEX(Currency!$A$1:$E$20,MATCH(U20,Currency!$A$1:$A$20,0),MATCH(V20,Currency!$A$1:$E$1,0))))*(Inflation!$B$23/(VLOOKUP(U20,Inflation!$A$1:$B$23,2,FALSE))) -> 8.6111189 | Z20: Germany | AA20: Wind, Fig 9
A21: 355 | B21: 0.3 | C21: 5.0200773 | D21: EU | F21: 400 | G21: 0.18 | H21: 12.506625 | I21: in Austria | K21: 456 | L21: 2015 | M21: GBP | N21: 0.37 | O21: 7.6 | P21: =O21*(1/(INDEX(Currency!$A$1:$E$20,MATCH(L21,Currency!$A$1:$A$20,0),MATCH(M21,Currency!$A$1:$E$1,0))))*(Inflation!$B$23/(VLOOKUP(L21,Inflation!$A$1:$B$23,2,FALSE))) -> 10.680664 | Q21: UK | R21: Offshore wind, Fast progress | T21: 347 | U21: 2013 | V21: EUR | W21: 0.2 | X21: 13.9 | Y21: =X21*(1/(INDEX(Currency!$A$1:$E$20,MATCH(U21,Currency!$A$1:$A$20,0),MATCH(V21,Currency!$A$1:$E$1,0))))*(Inflation!$B$23/(VLOOKUP(U21,Inflation!$A$1:$B$23,2,FALSE))) -> 14.249352 | Z21: Germany | AA21: Wind, Fig 9
A22: 355 | B22: 0.35 | C22: 4.9001367 | D22: EU | F22: 400 | G22: 0.02 | H22: 9.2261989 | I22: in Belgium | K22: 456 | L22: 2015 | M22: GBP | N22: 0.415 | O22: 6.5 | P22: =O22*(1/(INDEX(Currency!$A$1:$E$20,MATCH(L22,Currency!$A$1:$A$20,0),MATCH(M22,Currency!$A$1:$E$1,0))))*(Inflation!$B$23/(VLOOKUP(L22,Inflation!$A$1:$B$23,2,FALSE))) -> 9.1347785 | Q22: UK | R22: Offshore wind, Fast progress | T22: 347 | U22: 2013 | V22: EUR | W22: 0.3 | X22: 16.7 | Y22: =X22*(1/(INDEX(Currency!$A$1:$E$20,MATCH(U22,Currency!$A$1:$A$20,0),MATCH(V22,Currency!$A$1:$E$1,0))))*(Inflation!$B$23/(VLOOKUP(U22,Inflation!$A$1:$B$23,2,FALSE))) -> 17.119725 | Z22: Germany | AA22: Wind, Fig 9
A23: 355 | B23: 0.4 | C23: 5.3891253 | D23: EU | F23: 400 | G23: 0.04 | H23: 9.2261989 | I23: in Belgium | K23: 456 | L23: 2015 | M23: GBP | N23: 0.46 | O23: 7.7 | P23: =O23*(1/(INDEX(Currency!$A$1:$E$20,MATCH(L23,Currency!$A$1:$A$20,0),MATCH(M23,Currency!$A$1:$E$1,0))))*(Inflation!$B$23/(VLOOKUP(L23,Inflation!$A$1:$B$23,2,FALSE))) -> 10.821199 | Q23: UK | R23: Offshore wind, Fast progress | T23: 347 | U23: 2013 | V23: EUR | W23: 0.1 | X23: 10.2 | Y23: =X23*(1/(INDEX(Currency!$A$1:$E$20,MATCH(U23,Currency!$A$1:$A$20,0),MATCH(V23,Currency!$A$1:$E$1,0))))*(Inflation!$B$23/(VLOOKUP(U23,Inflation!$A$1:$B$23,2,FALSE))) -> 10.456359 | Z23: Germany | AA23: Wind, Fig 19
A24: 403 | D24: In UK | F24: 400 | G24: 0.06 | H24: 10.763899 | I24: in Belgium | K24: 456 | L24: 2015 | M24: GBP | N24: 0.46 | O24: 8.2 | P24: =O24*(1/(INDEX(Currency!$A$1:$E$20,MATCH(L24,Currency!$A$1:$A$20,0),MATCH(M24,Currency!$A$1:$E$1,0))))*(Inflation!$B$23/(VLOOKUP(L24,Inflation!$A$1:$B$23,2,FALSE))) -> 11.523874 | Q24: UK | R24: Offshore wind, Fast progress | T24: 347 | U24: 2013 | V24: EUR | W24: 0.2 | X24: 19.4 | Y24: =X24*(1/(INDEX(Currency!$A$1:$E$20,MATCH(U24,Currency!$A$1:$A$20,0),MATCH(V24,Currency!$A$1:$E$1,0))))*(Inflation!$B$23/(VLOOKUP(U24,Inflation!$A$1:$B$23,2,FALSE))) -> 19.887584 | Z24: Germany | AA24: Wind, Fig 19
A25: 403 | D25: In UK | F25: 400 | G25: 0.08 | H25: 11.584005 | I25: in Belgium | K25: 456 | L25: 2015 | M25: GBP | N25: 0.538 | O25: 11.1 | P25: =O25*(1/(INDEX(Currency!$A$1:$E$20,MATCH(L25,Currency!$A$1:$A$20,0),MATCH(M25,Currency!$A$1:$E$1,0))))*(Inflation!$B$23/(VLOOKUP(L25,Inflation!$A$1:$B$23,2,FALSE))) -> 15.599391 | Q25: UK | R25: Offshore wind, Fast progress | T25: 347 | U25: 2013 | V25: EUR | W25: 0.3 | X25: 24.1 | Y25: =X25*(1/(INDEX(Currency!$A$1:$E$20,MATCH(U25,Currency!$A$1:$A$20,0),MATCH(V25,Currency!$A$1:$E$1,0))))*(Inflation!$B$23/(VLOOKUP(U25,Inflation!$A$1:$B$23,2,FALSE))) -> 24.70571 | Z25: Germany | AA25: Wind, Fig 19
A26: 403 | D26: In UK | F26: 400 | G26: 0.1 | H26: 12.096572 | I26: in Belgium | K26: 456 | L26: 2015 | M26: GBP | N26: 0.538 | O26: 11.4 | P26: =O26*(1/(INDEX(Currency!$A$1:$E$20,MATCH(L26,Currency!$A$1:$A$20,0),MATCH(M26,Currency!$A$1:$E$1,0))))*(Inflation!$B$23/(VLOOKUP(L26,Inflation!$A$1:$B$23,2,FALSE))) -> 16.020996 | Q26: UK | R26: Offshore wind, Fast progress | T26: 355 | U26: 2013 | V26: EUR | W26: 0.05 | X26: 15.2 | Y26: =X26*(1/(INDEX(Currency!$A$1:$E$20,MATCH(U26,Currency!$A$1:$A$20,0),MATCH(V26,Currency!$A$1:$E$1,0))))*(Inflation!$B$23/(VLOOKUP(U26,Inflation!$A$1:$B$23,2,FALSE))) -> 15.582025 | Z26: Germany | AA26: Wind, Fig 10
A27: 403 | D27: In UK | F27: 400 | G27: 0.12 | H27: 12.404112 | I27: in Belgium | K27: 456 | L27: 2015 | M27: GBP | N27: 0.56 | O27: 18.6 | P27: =O27*(1/(INDEX(Currency!$A$1:$E$20,MATCH(L27,Currency!$A$1:$A$20,0),MATCH(M27,Currency!$A$1:$E$1,0))))*(Inflation!$B$23/(VLOOKUP(L27,Inflation!$A$1:$B$23,2,FALSE))) -> 26.13952 | Q27: UK | R27: Offshore wind, Fast progress | T27: 355 | U27: 2013 | V27: EUR | W27: 0.1 | X27: 18.7 | Y27: =X27*(1/(INDEX(Currency!$A$1:$E$20,MATCH(U27,Currency!$A$1:$A$20,0),MATCH(V27,Currency!$A$1:$E$1,0))))*(Inflation!$B$23/(VLOOKUP(U27,Inflation!$A$1:$B$23,2,FALSE))) -> 19.169991 | Z27: Germany | AA27: Wind, Fig 10
A28: 403 | D28: In UK | F28: 400 | G28: 0.14 | H28: 12.711652 | I28: in Belgium | K28: 456 | L28: 2015 | M28: GBP | N28: 0.602 | O28: 17.6 | P28: =O28*(1/(INDEX(Currency!$A$1:$E$20,MATCH(L28,Currency!$A$1:$A$20,0),MATCH(M28,Currency!$A$1:$E$1,0))))*(Inflation!$B$23/(VLOOKUP(L28,Inflation!$A$1:$B$23,2,FALSE))) -> 24.73417 | Q28: UK | R28: Offshore wind, Fast progress | T28: 355 | U28: 2013 | V28: EUR | W28: 0.15 | X28: 21.8 | Y28: =X28*(1/(INDEX(Currency!$A$1:$E$20,MATCH(U28,Currency!$A$1:$A$20,0),MATCH(V28,Currency!$A$1:$E$1,0))))*(Inflation!$B$23/(VLOOKUP(U28,Inflation!$A$1:$B$23,2,FALSE))) -> 22.347904 | Z28: Germany | AA28: Wind, Fig 10
A29: 403 | D29: In UK | F29: 400 | G29: 0.16 | H29: 12.814165 | I29: in Belgium | K29: 456 | L29: 2015 | M29: GBP | N29: 0.602 | O29: 22.7 | P29: =O29*(1/(INDEX(Currency!$A$1:$E$20,MATCH(L29,Currency!$A$1:$A$20,0),MATCH(M29,Currency!$A$1:$E$1,0))))*(Inflation!$B$23/(VLOOKUP(L29,Inflation!$A$1:$B$23,2,FALSE))) -> 31.901457 | Q29: UK | R29: Offshore wind, Fast progress | T29: 355 | U29: 2013 | V29: EUR | W29: 0.2 | X29: 24.7 | Y29: =X29*(1/(INDEX(Currency!$A$1:$E$20,MATCH(U29,Currency!$A$1:$A$20,0),MATCH(V29,Currency!$A$1:$E$1,0))))*(Inflation!$B$23/(VLOOKUP(U29,Inflation!$A$1:$B$23,2,FALSE))) -> 25.32079 | Z29: Germany | AA29: Wind, Fig 10
A30: 403 | D30: In UK | F30: 400 | G30: 0.18 | H30: 13.019192 | I30: in Belgium | K30: 456 | L30: 2015 | M30: GBP | N30: 0.452 | O30: 5.5 | P30: =O30*(1/(INDEX(Currency!$A$1:$E$20,MATCH(L30,Currency!$A$1:$A$20,0),MATCH(M30,Currency!$A$1:$E$1,0))))*(Inflation!$B$23/(VLOOKUP(L30,Inflation!$A$1:$B$23,2,FALSE))) -> 7.729428 | Q30: UK | R30: Offshore wind, Maximum progress | T30: 355 | U30: 2013 | V30: EUR | W30: 0.25 | X30: 26.8 | Y30: =X30*(1/(INDEX(Currency!$A$1:$E$20,MATCH(U30,Currency!$A$1:$A$20,0),MATCH(V30,Currency!$A$1:$E$1,0))))*(Inflation!$B$23/(VLOOKUP(U30,Inflation!$A$1:$B$23,2,FALSE))) -> 27.47357 | Z30: Germany | AA30: Wind, Fig 10
A31: 403 | D31: In UK | F31: 400 | G31: 0.02 | H31: 8.4060923 | I31: in Belgium | K31: 456 | L31: 2015 | M31: GBP | N31: 0.453 | O31: 5.6 | P31: =O31*(1/(INDEX(Currency!$A$1:$E$20,MATCH(L31,Currency!$A$1:$A$20,0),MATCH(M31,Currency!$A$1:$E$1,0))))*(Inflation!$B$23/(VLOOKUP(L31,Inflation!$A$1:$B$23,2,FALSE))) -> 7.869963 | Q31: UK | R31: Offshore wind, Maximum progress | T31: 355 | U31: 2013 | V31: EUR | W31: 0.3 | X31: 31.7 | Y31: =X31*(1/(INDEX(Currency!$A$1:$E$20,MATCH(U31,Currency!$A$1:$A$20,0),MATCH(V31,Currency!$A$1:$E$1,0))))*(Inflation!$B$23/(VLOOKUP(U31,Inflation!$A$1:$B$23,2,FALSE))) -> 32.496723 | Z31: Germany | AA31: Wind, Fig 10
A32: 403 | D32: In UK | F32: 400 | G32: 0.04 | H32: 8.4060923 | I32: in Belgium | K32: 456 | L32: 2015 | M32: GBP | N32: 0.528 | O32: 6.7 | P32: =O32*(1/(INDEX(Currency!$A$1:$E$20,MATCH(L32,Currency!$A$1:$A$20,0),MATCH(M32,Currency!$A$1:$E$1,0))))*(Inflation!$B$23/(VLOOKUP(L32,Inflation!$A$1:$B$23,2,FALSE))) -> 9.4158486 | Q32: UK | R32: Offshore wind, Maximum progress | T32: 355 | U32: 2013 | V32: EUR | W32: 0.35 | X32: 36.7 | Y32: =X32*(1/(INDEX(Currency!$A$1:$E$20,MATCH(U32,Currency!$A$1:$A$20,0),MATCH(V32,Currency!$A$1:$E$1,0))))*(Inflation!$B$23/(VLOOKUP(U32,Inflation!$A$1:$B$23,2,FALSE))) -> 37.622389 | Z32: Germany | AA32: Wind, Fig 10
A33: 403 | D33: In UK | F33: 400 | G33: 0.06 | H33: 10.046305 | I33: in Belgium | K33: 456 | L33: 2015 | M33: GBP | N33: 0.53 | O33: 6.7 | P33: =O33*(1/(INDEX(Currency!$A$1:$E$20,MATCH(L33,Currency!$A$1:$A$20,0),MATCH(M33,Currency!$A$1:$E$1,0))))*(Inflation!$B$23/(VLOOKUP(L33,Inflation!$A$1:$B$23,2,FALSE))) -> 9.4158486 | Q33: UK | R33: Offshore wind, Maximum progress | T33: 355 | U33: 2013 | V33: EUR | W33: 0.4 | X33: 44.7 | Y33: =X33*(1/(INDEX(Currency!$A$1:$E$20,MATCH(U33,Currency!$A$1:$A$20,0),MATCH(V33,Currency!$A$1:$E$1,0))))*(Inflation!$B$23/(VLOOKUP(U33,Inflation!$A$1:$B$23,2,FALSE))) -> 45.823454 | Z33: Germany | AA33: Wind, Fig 10
A34: 403 | D34: In UK | F34: 400 | G34: 0.08 | H34: 10.046305 | I34: in Belgium | K34: 456 | L34: 2015 | M34: GBP | N34: 0.589 | O34: 7.8 | P34: =O34*(1/(INDEX(Currency!$A$1:$E$20,MATCH(L34,Currency!$A$1:$A$20,0),MATCH(M34,Currency!$A$1:$E$1,0))))*(Inflation!$B$23/(VLOOKUP(L34,Inflation!$A$1:$B$23,2,FALSE))) -> 10.961734 | Q34: UK | R34: Offshore wind, Maximum progress | T34: 355 | U34: 2013 | V34: EUR | W34: 0.05 | X34: 13.5 | Y34: =X34*(1/(INDEX(Currency!$A$1:$E$20,MATCH(U34,Currency!$A$1:$A$20,0),MATCH(V34,Currency!$A$1:$E$1,0))))*(Inflation!$B$23/(VLOOKUP(U34,Inflation!$A$1:$B$23,2,FALSE))) -> 13.839298 | Z34: Germany | AA34: Solar, Fig 10
A35: 403 | D35: In UK | F35: 400 | G35: 0.1 | H35: 10.046305 | I35: in Belgium | K35: 456 | L35: 2015 | M35: GBP | N35: 0.589 | O35: 7.4 | P35: =O35*(1/(INDEX(Currency!$A$1:$E$20,MATCH(L35,Currency!$A$1:$A$20,0),MATCH(M35,Currency!$A$1:$E$1,0))))*(Inflation!$B$23/(VLOOKUP(L35,Inflation!$A$1:$B$23,2,FALSE))) -> 10.399594 | Q35: UK | R35: Offshore wind, Maximum progress | T35: 355 | U35: 2013 | V35: EUR | W35: 0.1 | X35: 27.4 | Y35: =X35*(1/(INDEX(Currency!$A$1:$E$20,MATCH(U35,Currency!$A$1:$A$20,0),MATCH(V35,Currency!$A$1:$E$1,0))))*(Inflation!$B$23/(VLOOKUP(U35,Inflation!$A$1:$B$23,2,FALSE))) -> 28.08865 | Z35: Germany | AA35: Solar, Fig 10
A36: 403 | D36: In UK | F36: 400 | G36: 0.12 | H36: 10.046305 | I36: in Belgium | K36: 403/455 | L36: 2015 | M36: GBP | N36: 0.362 | O36: 23 | P36: =O36*(1/(INDEX(Currency!$A$1:$E$20,MATCH(L36,Currency!$A$1:$A$20,0),MATCH(M36,Currency!$A$1:$E$1,0))))*(Inflation!$B$23/(VLOOKUP(L36,Inflation!$A$1:$B$23,2,FALSE))) -> 32.323062 | Q36: UK | R36: Onshore wind, CCC 2015 | T36: 355 | U36: 2013 | V36: EUR | W36: 0.15 | X36: 33.4 | Y36: =X36*(1/(INDEX(Currency!$A$1:$E$20,MATCH(U36,Currency!$A$1:$A$20,0),MATCH(V36,Currency!$A$1:$E$1,0))))*(Inflation!$B$23/(VLOOKUP(U36,Inflation!$A$1:$B$23,2,FALSE))) -> 34.239449 | Z36: Germany | AA36: Solar, Fig 10
A37: 403 | D37: In UK | F37: 400 | G37: 0.14 | H37: 10.456359 | I37: in Belgium | K37: 403/455 | L37: 2015 | M37: GBP | N37: 0.364 | O37: 13.5 | P37: =O37*(1/(INDEX(Currency!$A$1:$E$20,MATCH(L37,Currency!$A$1:$A$20,0),MATCH(M37,Currency!$A$1:$E$1,0))))*(Inflation!$B$23/(VLOOKUP(L37,Inflation!$A$1:$B$23,2,FALSE))) -> 18.972232 | Q37: UK | R37: Onshore wind, CCC 2015 | T37: 355 | U37: 2013 | V37: EUR | W37: 0.2 | X37: 49.2 | Y37: =X37*(1/(INDEX(Currency!$A$1:$E$20,MATCH(U37,Currency!$A$1:$A$20,0),MATCH(V37,Currency!$A$1:$E$1,0))))*(Inflation!$B$23/(VLOOKUP(U37,Inflation!$A$1:$B$23,2,FALSE))) -> 50.436554 | Z37: Germany | AA37: Solar, Fig 10
A38: 403 | D38: In UK | F38: 400 | G38: 0.16 | H38: 10.866412 | I38: in Belgium | K38: 403/455 | L38: 2015 | M38: GBP | N38: 0.364 | O38: 6.3 | P38: =O38*(1/(INDEX(Currency!$A$1:$E$20,MATCH(L38,Currency!$A$1:$A$20,0),MATCH(M38,Currency!$A$1:$E$1,0))))*(Inflation!$B$23/(VLOOKUP(L38,Inflation!$A$1:$B$23,2,FALSE))) -> 8.8537084 | Q38: UK | R38: Onshore wind, CCC 2015 | T38: 355 | U38: 2013 | V38: EUR | W38: 0.25 | X38: 100 | Y38: =X38*(1/(INDEX(Currency!$A$1:$E$20,MATCH(U38,Currency!$A$1:$A$20,0),MATCH(V38,Currency!$A$1:$E$1,0))))*(Inflation!$B$23/(VLOOKUP(U38,Inflation!$A$1:$B$23,2,FALSE))) -> 102.51332 | Z38: Germany | AA38: Solar, Fig 10
A39: 403 | D39: In UK | F39: 400 | G39: 0.18 | H39: 11.071439 | I39: in Belgium | K39: 403/455 | L39: 2015 | M39: GBP | N39: 0.471 | O39: 36.8 | P39: =O39*(1/(INDEX(Currency!$A$1:$E$20,MATCH(L39,Currency!$A$1:$A$20,0),MATCH(M39,Currency!$A$1:$E$1,0))))*(Inflation!$B$23/(VLOOKUP(L39,Inflation!$A$1:$B$23,2,FALSE))) -> 51.7169 | Q39: UK | R39: Onshore wind, CCC 2015 | T39: 457 | U39: 2015 | V39: EUR | W39: 0.001 | X39: 2.7 | Y39: =X39*(1/(INDEX(Currency!$A$1:$E$20,MATCH(U39,Currency!$A$1:$A$20,0),MATCH(V39,Currency!$A$1:$E$1,0))))*(Inflation!$B$23/(VLOOKUP(U39,Inflation!$A$1:$B$23,2,FALSE))) -> 2.75319 | Z39: Various | AA39: Wind, Fig 13
A40: 403 | D40: In UK | F40: 400 | G40: 0.02 | H40: 10.866412 | I40: in Czech Republic | K40: 403/455 | L40: 2015 | M40: GBP | N40: 0.48 | O40: 35.4 | P40: =O40*(1/(INDEX(Currency!$A$1:$E$20,MATCH(L40,Currency!$A$1:$A$20,0),MATCH(M40,Currency!$A$1:$E$1,0))))*(Inflation!$B$23/(VLOOKUP(L40,Inflation!$A$1:$B$23,2,FALSE))) -> 49.749409 | Q40: UK | R40: Onshore wind, CCC 2015 | T40: 457 | U40: 2015 | V40: EUR | W40: 0.002 | X40: -6.7 | Y40: =X40*(1/(INDEX(Currency!$A$1:$E$20,MATCH(U40,Currency!$A$1:$A$20,0),MATCH(V40,Currency!$A$1:$E$1,0))))*(Inflation!$B$23/(VLOOKUP(U40,Inflation!$A$1:$B$23,2,FALSE))) -> -6.83199 | Z40: Various | AA40: Wind, Fig 13
A41: 403 | D41: In UK | F41: 400 | G41: 0.04 | H41: 10.866412 | I41: in Czech Republic | K41: 403/455 | L41: 2015 | M41: GBP | N41: 0.513 | O41: 13.8 | P41: =O41*(1/(INDEX(Currency!$A$1:$E$20,MATCH(L41,Currency!$A$1:$A$20,0),MATCH(M41,Currency!$A$1:$E$1,0))))*(Inflation!$B$23/(VLOOKUP(L41,Inflation!$A$1:$B$23,2,FALSE))) -> 19.393837 | Q41: UK | R41: Onshore wind, CCC 2015 | T41: 457 | U41: 2015 | V41: EUR | W41: 0.002 | X41: -1.3 | Y41: =X41*(1/(INDEX(Currency!$A$1:$E$20,MATCH(U41,Currency!$A$1:$A$20,0),MATCH(V41,Currency!$A$1:$E$1,0))))*(Inflation!$B$23/(VLOOKUP(U41,Inflation!$A$1:$B$23,2,FALSE))) -> -1.32561 | Z41: Various | AA41: Wind, Fig 13
A42: 413 | B42: 0.271 | C42: 6.4308535 | D42: In UK | F42: 400 | G42: 0.06 | H42: 10.866412 | I42: in Czech Republic | K42: 403/455 | L42: 2015 | M42: GBP | N42: 0.518 | O42: 12.7 | P42: =O42*(1/(INDEX(Currency!$A$1:$E$20,MATCH(L42,Currency!$A$1:$A$20,0),MATCH(M42,Currency!$A$1:$E$1,0))))*(Inflation!$B$23/(VLOOKUP(L42,Inflation!$A$1:$B$23,2,FALSE))) -> 17.847952 | Q42: UK | R42: Onshore wind, CCC 2015 | T42: 457 | U42: 2015 | V42: EUR | W42: 0.008 | X42: -3.4 | Y42: =X42*(1/(INDEX(Currency!$A$1:$E$20,MATCH(U42,Currency!$A$1:$A$20,0),MATCH(V42,Currency!$A$1:$E$1,0))))*(Inflation!$B$23/(VLOOKUP(U42,Inflation!$A$1:$B$23,2,FALSE))) -> -3.46698 | Z42: Various | AA42: Wind, Fig 13
A43: 413 | B43: 0.326 | C43: 7.5741164 | D43: In UK | F43: 400 | G43: 0.08 | H43: 11.789032 | I43: in Czech Republic | K43: 403/455 | L43: 2015 | M43: GBP | N43: 0.514 | O43: 6.9 | P43: =O43*(1/(INDEX(Currency!$A$1:$E$20,MATCH(L43,Currency!$A$1:$A$20,0),MATCH(M43,Currency!$A$1:$E$1,0))))*(Inflation!$B$23/(VLOOKUP(L43,Inflation!$A$1:$B$23,2,FALSE))) -> 9.6969187 | Q43: UK | R43: Onshore wind, CCC 2015 | T43: 457 | U43: 2015 | V43: EUR | W43: 0.008 | X43: -1.3 | Y43: =X43*(1/(INDEX(Currency!$A$1:$E$20,MATCH(U43,Currency!$A$1:$A$20,0),MATCH(V43,Currency!$A$1:$E$1,0))))*(Inflation!$B$23/(VLOOKUP(U43,Inflation!$A$1:$B$23,2,FALSE))) -> -1.32561 | Z43: Various | AA43: Wind, Fig 13
A44: 413 | B44: 0.417 | C44: 9.2890106 | D44: In UK | F44: 400 | G44: 0.1 | H44: 12.404112 | I44: in Czech Republic | K44: 403/455 | L44: 2015 | M44: GBP | N44: 0.519 | O44: 8.1 | P44: =O44*(1/(INDEX(Currency!$A$1:$E$20,MATCH(L44,Currency!$A$1:$A$20,0),MATCH(M44,Currency!$A$1:$E$1,0))))*(Inflation!$B$23/(VLOOKUP(L44,Inflation!$A$1:$B$23,2,FALSE))) -> 11.383339 | Q44: UK | R44: Onshore wind, CCC 2015 | T44: 457 | U44: 2015 | V44: EUR | W44: 0.009 | X44: -9.8 | Y44: =X44*(1/(INDEX(Currency!$A$1:$E$20,MATCH(U44,Currency!$A$1:$A$20,0),MATCH(V44,Currency!$A$1:$E$1,0))))*(Inflation!$B$23/(VLOOKUP(U44,Inflation!$A$1:$B$23,2,FALSE))) -> -9.99306 | Z44: Various | AA44: Wind, Fig 13
A45: 433 | B45: 0.05 | C45: 1.5737846 | D45: UK | F45: 400 | G45: 0.12 | H45: 12.711652 | I45: in Czech Republic | K45: 456 | L45: 2015 | M45: GBP | N45: 0.266 | O45: 10.9 | P45: =O45*(1/(INDEX(Currency!$A$1:$E$20,MATCH(L45,Currency!$A$1:$A$20,0),MATCH(M45,Currency!$A$1:$E$1,0))))*(Inflation!$B$23/(VLOOKUP(L45,Inflation!$A$1:$B$23,2,FALSE))) -> 15.318321 | Q45: UK | R45: Onshore wind, No progress | T45: 457 | U45: 2015 | V45: EUR | W45: 0.009 | X45: 7.1 | Y45: =X45*(1/(INDEX(Currency!$A$1:$E$20,MATCH(U45,Currency!$A$1:$A$20,0),MATCH(V45,Currency!$A$1:$E$1,0))))*(Inflation!$B$23/(VLOOKUP(U45,Inflation!$A$1:$B$23,2,FALSE))) -> 7.23987 | Z45: Various | AA45: Wind, Fig 13
A46: 433 | B46: 0.1 | C46: 2.6979164 | D46: UK | F46: 400 | G46: 0.14 | H46: 13.019192 | I46: in Czech Republic | K46: 456 | L46: 2015 | M46: GBP | N46: 0.37 | O46: 22.8 | P46: =O46*(1/(INDEX(Currency!$A$1:$E$20,MATCH(L46,Currency!$A$1:$A$20,0),MATCH(M46,Currency!$A$1:$E$1,0))))*(Inflation!$B$23/(VLOOKUP(L46,Inflation!$A$1:$B$23,2,FALSE))) -> 32.041992 | Q46: UK | R46: Onshore wind, No progress | T46: 457 | U46: 2015 | V46: EUR | W46: 0.009 | X46: 9.4 | Y46: =X46*(1/(INDEX(Currency!$A$1:$E$20,MATCH(U46,Currency!$A$1:$A$20,0),MATCH(V46,Currency!$A$1:$E$1,0))))*(Inflation!$B$23/(VLOOKUP(U46,Inflation!$A$1:$B$23,2,FALSE))) -> 9.58518 | Z46: Various | AA46: Wind, Fig 13
A47: 433 | B47: 0.15 | C47: 3.2599824 | D47: UK | F47: 400 | G47: 0.16 | H47: 13.224218 | I47: in Czech Republic | K47: 456 | L47: 2015 | M47: GBP | N47: 0.506 | O47: 40.2 | P47: =O47*(1/(INDEX(Currency!$A$1:$E$20,MATCH(L47,Currency!$A$1:$A$20,0),MATCH(M47,Currency!$A$1:$E$1,0))))*(Inflation!$B$23/(VLOOKUP(L47,Inflation!$A$1:$B$23,2,FALSE))) -> 56.495092 | Q47: UK | R47: Onshore wind, No progress | T47: 457 | U47: 2015 | V47: EUR | W47: 0.01 | X47: 2.6 | Y47: =X47*(1/(INDEX(Currency!$A$1:$E$20,MATCH(U47,Currency!$A$1:$A$20,0),MATCH(V47,Currency!$A$1:$E$1,0))))*(Inflation!$B$23/(VLOOKUP(U47,Inflation!$A$1:$B$23,2,FALSE))) -> 2.65122 | Z47: Various | AA47: Wind, Fig 13
A48: 433 | B48: 0.2 | C48: 3.8220483 | D48: UK | F48: 400 | G48: 0.18 | H48: 13.429245 | I48: in Czech Republic | K48: 456 | L48: 2015 | M48: GBP | N48: 0.266 | O48: 10.3 | P48: =O48*(1/(INDEX(Currency!$A$1:$E$20,MATCH(L48,Currency!$A$1:$A$20,0),MATCH(M48,Currency!$A$1:$E$1,0))))*(Inflation!$B$23/(VLOOKUP(L48,Inflation!$A$1:$B$23,2,FALSE))) -> 14.475111 | Q48: UK | R48: Onshore wind, Moderate progress | T48: 457 | U48: 2015 | V48: EUR | W48: 0.019 | X48: -1.3 | Y48: =X48*(1/(INDEX(Currency!$A$1:$E$20,MATCH(U48,Currency!$A$1:$A$20,0),MATCH(V48,Currency!$A$1:$E$1,0))))*(Inflation!$B$23/(VLOOKUP(U48,Inflation!$A$1:$B$23,2,FALSE))) -> -1.32561 | Z48: Various | AA48: Wind, Fig 13
A49: 433 | B49: 0.053 | C49: 3.1475692 | D49: US | F49: 400 | G49: 0.02 | H49: 10.046305 | I49: in Czech Republic | K49: 456 | L49: 2015 | M49: GBP | N49: 0.37 | O49: 11.9 | P49: =O49*(1/(INDEX(Currency!$A$1:$E$20,MATCH(L49,Currency!$A$1:$A$20,0),MATCH(M49,Currency!$A$1:$E$1,0))))*(Inflation!$B$23/(VLOOKUP(L49,Inflation!$A$1:$B$23,2,FALSE))) -> 16.723671 | Q49: UK | R49: Onshore wind, Moderate progress | T49: 457 | U49: 2015 | V49: EUR | W49: 0.05 | X49: -3.4 | Y49: =X49*(1/(INDEX(Currency!$A$1:$E$20,MATCH(U49,Currency!$A$1:$A$20,0),MATCH(V49,Currency!$A$1:$E$1,0))))*(Inflation!$B$23/(VLOOKUP(U49,Inflation!$A$1:$B$23,2,FALSE))) -> -3.46698 | Z49: Various | AA49: Wind, Fig 13
A50: 433 | B50: 0.076 | C50: 4.271701 | D50: US | F50: 400 | G50: 0.04 | H50: 10.046305 | I50: in Czech Republic | K50: 456 | L50: 2015 | M50: GBP | N50: 0.47 | O50: 10.2 | P50: =O50*(1/(INDEX(Currency!$A$1:$E$20,MATCH(L50,Currency!$A$1:$A$20,0),MATCH(M50,Currency!$A$1:$E$1,0))))*(Inflation!$B$23/(VLOOKUP(L50,Inflation!$A$1:$B$23,2,FALSE))) -> 14.334576 | Q50: UK | R50: Onshore wind, Moderate progress | T50: 457 | U50: 2015 | V50: EUR | W50: 0.05 | X50: 4.4 | Y50: =X50*(1/(INDEX(Currency!$A$1:$E$20,MATCH(U50,Currency!$A$1:$A$20,0),MATCH(V50,Currency!$A$1:$E$1,0))))*(Inflation!$B$23/(VLOOKUP(U50,Inflation!$A$1:$B$23,2,FALSE))) -> 4.48668 | Z50: Various | AA50: Wind, Fig 13
A51: 433 | B51: 0.15 | C51: 2.5855033 | D51: US | F51: 400 | G51: 0.06 | H51: 10.046305 | I51: in Czech Republic | K51: 456 | L51: 2015 | M51: GBP | N51: 0.266 | O51: 6.5 | P51: =O51*(1/(INDEX(Currency!$A$1:$E$20,MATCH(L51,Currency!$A$1:$A$20,0),MATCH(M51,Currency!$A$1:$E$1,0))))*(Inflation!$B$23/(VLOOKUP(L51,Inflation!$A$1:$B$23,2,FALSE))) -> 9.1347785 | Q51: UK | R51: Onshore wind, Fast progress | T51: 457 | U51: 2015 | V51: EUR | W51: 0.05 | X51: 8.5 | Y51: =X51*(1/(INDEX(Currency!$A$1:$E$20,MATCH(U51,Currency!$A$1:$A$20,0),MATCH(V51,Currency!$A$1:$E$1,0))))*(Inflation!$B$23/(VLOOKUP(U51,Inflation!$A$1:$B$23,2,FALSE))) -> 8.66745 | Z51: Various | AA51: Wind, Fig 13
A52: 433 | B52: 0.2 | C52: 3.4848087 | D52: US | F52: 400 | G52: 0.08 | H52: 11.071439 | I52: in Czech Republic | K52: 456 | L52: 2015 | M52: GBP | N52: 0.279 | O52: 7.2 | P52: =O52*(1/(INDEX(Currency!$A$1:$E$20,MATCH(L52,Currency!$A$1:$A$20,0),MATCH(M52,Currency!$A$1:$E$1,0))))*(Inflation!$B$23/(VLOOKUP(L52,Inflation!$A$1:$B$23,2,FALSE))) -> 10.118524 | Q52: UK | R52: Onshore wind, Fast progress | T52: 457 | U52: 2015 | V52: EUR | W52: 0.06 | X52: 2.1 | Y52: =X52*(1/(INDEX(Currency!$A$1:$E$20,MATCH(U52,Currency!$A$1:$A$20,0),MATCH(V52,Currency!$A$1:$E$1,0))))*(Inflation!$B$23/(VLOOKUP(U52,Inflation!$A$1:$B$23,2,FALSE))) -> 2.14137 | Z52: Various | AA52: Wind, Fig 13
A53: 433 | B53: 0.25 | C53: 3.8220483 | D53: US | F53: 400 | G53: 0.1 | H53: 11.071439 | I53: in Czech Republic | K53: 456 | L53: 2015 | M53: GBP | N53: 0.356 | O53: 4.8 | P53: =O53*(1/(INDEX(Currency!$A$1:$E$20,MATCH(L53,Currency!$A$1:$A$20,0),MATCH(M53,Currency!$A$1:$E$1,0))))*(Inflation!$B$23/(VLOOKUP(L53,Inflation!$A$1:$B$23,2,FALSE))) -> 6.7456826 | Q53: UK | R53: Onshore wind, Fast progress | T53: 457 | U53: 2015 | V53: EUR | W53: 0.06 | X53: 3 | Y53: =X53*(1/(INDEX(Currency!$A$1:$E$20,MATCH(U53,Currency!$A$1:$A$20,0),MATCH(V53,Currency!$A$1:$E$1,0))))*(Inflation!$B$23/(VLOOKUP(U53,Inflation!$A$1:$B$23,2,FALSE))) -> 3.0591 | Z53: Various | AA53: Wind, Fig 13
A54: 433 | B54: 0.02 | C54: 0.33723955 | D54: US | F54: 400 | G54: 0.12 | H54: 11.071439 | I54: in Czech Republic | K54: 456 | L54: 2015 | M54: GBP | N54: 0.37 | O54: 7.5 | P54: =O54*(1/(INDEX(Currency!$A$1:$E$20,MATCH(L54,Currency!$A$1:$A$20,0),MATCH(M54,Currency!$A$1:$E$1,0))))*(Inflation!$B$23/(VLOOKUP(L54,Inflation!$A$1:$B$23,2,FALSE))) -> 10.540129 | Q54: UK | R54: Onshore wind, Fast progress | T54: 457 | U54: 2015 | V54: EUR | W54: 0.06 | X54: 9.2 | Y54: =X54*(1/(INDEX(Currency!$A$1:$E$20,MATCH(U54,Currency!$A$1:$A$20,0),MATCH(V54,Currency!$A$1:$E$1,0))))*(Inflation!$B$23/(VLOOKUP(U54,Inflation!$A$1:$B$23,2,FALSE))) -> 9.38124 | Z54: Various | AA54: Wind, Fig 13
A55: 434 | B55: 0.15 | C55: 4.3055595 | D55: Ireland | F55: 400 | G55: 0.14 | H55: 11.071439 | I55: in Czech Republic | K55: 456 | L55: 2015 | M55: GBP | N55: 0.415 | O55: 6.3 | P55: =O55*(1/(INDEX(Currency!$A$1:$E$20,MATCH(L55,Currency!$A$1:$A$20,0),MATCH(M55,Currency!$A$1:$E$1,0))))*(Inflation!$B$23/(VLOOKUP(L55,Inflation!$A$1:$B$23,2,FALSE))) -> 8.8537084 | Q55: UK | R55: Onshore wind, Fast progress | T55: 457 | U55: 2015 | V55: EUR | W55: 0.07 | X55: 7 | Y55: =X55*(1/(INDEX(Currency!$A$1:$E$20,MATCH(U55,Currency!$A$1:$A$20,0),MATCH(V55,Currency!$A$1:$E$1,0))))*(Inflation!$B$23/(VLOOKUP(U55,Inflation!$A$1:$B$23,2,FALSE))) -> 7.1379 | Z55: Various | AA55: Wind, Fig 13
A56: 434 | B56: 0.053 | C56: 2.870373 | D56: US | F56: 400 | G56: 0.16 | H56: 11.071439 | I56: in Czech Republic | K56: 456 | L56: 2015 | M56: GBP | N56: 0.46 | O56: 7.2 | P56: =O56*(1/(INDEX(Currency!$A$1:$E$20,MATCH(L56,Currency!$A$1:$A$20,0),MATCH(M56,Currency!$A$1:$E$1,0))))*(Inflation!$B$23/(VLOOKUP(L56,Inflation!$A$1:$B$23,2,FALSE))) -> 10.118524 | Q56: UK | R56: Onshore wind, Fast progress | T56: 457 | U56: 2015 | V56: EUR | W56: 0.072 | X56: 1.1 | Y56: =X56*(1/(INDEX(Currency!$A$1:$E$20,MATCH(U56,Currency!$A$1:$A$20,0),MATCH(V56,Currency!$A$1:$E$1,0))))*(Inflation!$B$23/(VLOOKUP(U56,Inflation!$A$1:$B$23,2,FALSE))) -> 1.12167 | Z56: Various | AA56: Wind, Fig 13
... A68: 374 | B68: 0.1 | C68: 1.5388531 | D68: France | F68: 400 | G68: 0.04 | H68: 9.0211722 | I68: in UK | K68: 456 | L68: 2015 | M68: GBP | N68: 0.589 | O68: 8.5 | P68: =O68*(1/(INDEX(Currency!$A$1:$E$20,MATCH(L68,Currency!$A$1:$A$20,0),MATCH(M68,Currency!$A$1:$E$1,0))))*(Inflation!$B$23/(VLOOKUP(L68,Inflation!$A$1:$B$23,2,FALSE))) -> 11.94548 | Q68: UK | R68: Onshore wind, Maximum progress | T68: 457 | U68: 2015 | V68: EUR | W68: 0.2 | X68: 12.7 | Y68: =X68*(1/(INDEX(Currency!$A$1:$E$20,MATCH(U68,Currency!$A$1:$A$20,0),MATCH(V68,Currency!$A$1:$E$1,0))))*(Inflation!$B$23/(VLOOKUP(U68,Inflation!$A$1:$B$23,2,FALSE))) -> 12.95019 | Z68: Various | AA68: Wind, Fig 13
A69: 374 | B69: 0.3 | C69: 4.0577126 | D69: France | F69: 400 | G69: 0.06 | H69: 9.0211722 | I69: in UK | K69: 403/455 | L69: 2015 | M69: GBP | N69: 0.361 | O69: 22.9 | P69: =O69*(1/(INDEX(Currency!$A$1:$E$20,MATCH(L69,Currency!$A$1:$A$20,0),MATCH(M69,Currency!$A$1:$E$1,0))))*(Inflation!$B$23/(VLOOKUP(L69,Inflation!$A$1:$B$23,2,FALSE))) -> 32.182527 | Q69: UK | R69: Solar PV, CCC 2015 | T69: 457 | U69: 2015 | V69: EUR | W69: 0.2 | X69: 17.8 | Y69: =X69*(1/(INDEX(Currency!$A$1:$E$20,MATCH(U69,Currency!$A$1:$A$20,0),MATCH(V69,Currency!$A$1:$E$1,0))))*(Inflation!$B$23/(VLOOKUP(U69,Inflation!$A$1:$B$23,2,FALSE))) -> 18.15066 | Z69: Various | AA69: Wind, Fig 13
A70: 374 | B70: 0.1 | C70: 1.5388531 | D70: France | F70: 400 | G70: 0.08 | H70: 9.0211722 | I70: in UK | K70: 403/455 | L70: 2015 | M70: GBP | N70: 0.363 | O70: 12 | P70: =O70*(1/(INDEX(Currency!$A$1:$E$20,MATCH(L70,Currency!$A$1:$A$20,0),MATCH(M70,Currency!$A$1:$E$1,0))))*(Inflation!$B$23/(VLOOKUP(L70,Inflation!$A$1:$B$23,2,FALSE))) -> 16.864206 | Q70: UK | R70: Solar PV, CCC 2015 | T70: 457 | U70: 2015 | V70: EUR | W70: 0.2 | X70: 24.7 | Y70: =X70*(1/(INDEX(Currency!$A$1:$E$20,MATCH(U70,Currency!$A$1:$A$20,0),MATCH(V70,Currency!$A$1:$E$1,0))))*(Inflation!$B$23/(VLOOKUP(U70,Inflation!$A$1:$B$23,2,FALSE))) -> 25.18659 | Z70: Various | AA70: Wind, Fig 13
A71: 374 | B71: 0.3 | C71: 4.0577126 | D71: France | F71: 400 | G71: 0.1 | H71: 9.5337388 | I71: in UK | K71: 403/455 | L71: 2015 | M71: GBP | N71: 0.364 | O71: 10.4 | P71: =O71*(1/(INDEX(Currency!$A$1:$E$20,MATCH(L71,Currency!$A$1:$A$20,0),MATCH(M71,Currency!$A$1:$E$1,0))))*(Inflation!$B$23/(VLOOKUP(L71,Inflation!$A$1:$B$23,2,FALSE))) -> 14.615646 | Q71: UK | R71: Solar PV, CCC 2015 | T71: 457 | U71: 2015 | V71: EUR | W71: 0.2 | X71: 38.7 | Y71: =X71*(1/(INDEX(Currency!$A$1:$E$20,MATCH(U71,Currency!$A$1:$A$20,0),MATCH(V71,Currency!$A$1:$E$1,0))))*(Inflation!$B$23/(VLOOKUP(U71,Inflation!$A$1:$B$23,2,FALSE))) -> 39.46239 | Z71: Various | AA71: Wind, Fig 13
A72: 374 | B72: 0.1 | C72: 2.6727448 | D72: Germany | F72: 400 | G72: 0.12 | H72: 9.5337388 | I72: in UK | K72: 403/455 | L72: 2015 | M72: GBP | N72: 0.471 | O72: 35.7 | P72: =O72*(1/(INDEX(Currency!$A$1:$E$20,MATCH(L72,Currency!$A$1:$A$20,0),MATCH(M72,Currency!$A$1:$E$1,0))))*(Inflation!$B$23/(VLOOKUP(L72,Inflation!$A$1:$B$23,2,FALSE))) -> 50.171014 | Q72: UK | R72: Solar PV, CCC 2015 | T72: 457 | U72: 2015 | V72: EUR | W72: 0.25 | X72: 13.7 | Y72: =X72*(1/(INDEX(Currency!$A$1:$E$20,MATCH(U72,Currency!$A$1:$A$20,0),MATCH(V72,Currency!$A$1:$E$1,0))))*(Inflation!$B$23/(VLOOKUP(U72,Inflation!$A$1:$B$23,2,FALSE))) -> 13.96989 | Z72: Various | AA72: Wind, Fig 13
A73: 374 | B73: 0.3 | C73: 5.1916044 | D73: Germany | F73: 400 | G73: 0.14 | H73: 9.5337388 | I73: in UK | K73: 403/455 | L73: 2015 | M73: GBP | N73: 0.519 | O73: 25.2 | P73: =O73*(1/(INDEX(Currency!$A$1:$E$20,MATCH(L73,Currency!$A$1:$A$20,0),MATCH(M73,Currency!$A$1:$E$1,0))))*(Inflation!$B$23/(VLOOKUP(L73,Inflation!$A$1:$B$23,2,FALSE))) -> 35.414834 | Q73: UK | R73: Solar PV, CCC 2015 | T73: 457 | U73: 2015 | V73: EUR | W73: 0.3 | X73: 10.5 | Y73: =X73*(1/(INDEX(Currency!$A$1:$E$20,MATCH(U73,Currency!$A$1:$A$20,0),MATCH(V73,Currency!$A$1:$E$1,0))))*(Inflation!$B$23/(VLOOKUP(U73,Inflation!$A$1:$B$23,2,FALSE))) -> 10.70685 | Z73: Various | AA73: Wind, Fig 13
A74: 374 | B74: 0.1 | C74: 2.6727448 | D74: Germany | F74: 400 | G74: 0.16 | H74: 9.9437921 | I74: in UK | K74: 403/455 | L74: 2015 | M74: GBP | N74: 0.518 | O74: 24.4 | P74: =O74*(1/(INDEX(Currency!$A$1:$E$20,MATCH(L74,Currency!$A$1:$A$20,0),MATCH(M74,Currency!$A$1:$E$1,0))))*(Inflation!$B$23/(VLOOKUP(L74,Inflation!$A$1:$B$23,2,FALSE))) -> 34.290553 | Q74: UK | R74: Solar PV, CCC 2015 | T74: 457 | U74: 2015 | V74: EUR | W74: 0.3 | X74: 15.6 | Y74: =X74*(1/(INDEX(Currency!$A$1:$E$20,MATCH(U74,Currency!$A$1:$A$20,0),MATCH(V74,Currency!$A$1:$E$1,0))))*(Inflation!$B$23/(VLOOKUP(U74,Inflation!$A$1:$B$23,2,FALSE))) -> 15.90732 | Z74: Various | AA74: Wind, Fig 13
A75: 374 | B75: 0.3 | C75: 5.1916044 | D75: Germany | F75: 400 | G75: 0.18 | H75: 10.251332 | I75: in UK | K75: 403/455 | L75: 2015 | M75: GBP | N75: 0.513 | O75: 12.2 | P75: =O75*(1/(INDEX(Currency!$A$1:$E$20,MATCH(L75,Currency!$A$1:$A$20,0),MATCH(M75,Currency!$A$1:$E$1,0))))*(Inflation!$B$23/(VLOOKUP(L75,Inflation!$A$1:$B$23,2,FALSE))) -> 17.145277 | Q75: UK | R75: Solar PV, CCC 2015 | T75: 457 | U75: 2015 | V75: EUR | W75: 0.3 | X75: 17.7 | Y75: =X75*(1/(INDEX(Currency!$A$1:$E$20,MATCH(U75,Currency!$A$1:$A$20,0),MATCH(V75,Currency!$A$1:$E$1,0))))*(Inflation!$B$23/(VLOOKUP(U75,Inflation!$A$1:$B$23,2,FALSE))) -> 18.04869 | Z75: Various | AA75: Wind, Fig 13
A76: 374 | B76: 0.1 | C76: 2.6727448 | D76: Germany | F76: 400 | G76: 0.02 | H76: 12.814165 | I76: in Spain | K76: 403/455 | L76: 2015 | M76: GBP | N76: 0.514 | O76: 11.1 | P76: =O76*(1/(INDEX(Currency!$A$1:$E$20,MATCH(L76,Currency!$A$1:$A$20,0),MATCH(M76,Currency!$A$1:$E$1,0))))*(Inflation!$B$23/(VLOOKUP(L76,Inflation!$A$1:$B$23,2,FALSE))) -> 15.599391 | Q76: UK | R76: Solar PV, CCC 2015 | T76: 457 | U76: 2015 | V76: EUR | W76: 0.3 | X76: 24.1 | Y76: =X76*(1/(INDEX(Currency!$A$1:$E$20,MATCH(U76,Currency!$A$1:$A$20,0),MATCH(V76,Currency!$A$1:$E$1,0))))*(Inflation!$B$23/(VLOOKUP(U76,Inflation!$A$1:$B$23,2,FALSE))) -> 24.57477 | Z76: Various | AA76: Wind, Fig 13
A77: 374 | B77: 0.3 | C77: 5.1916044 | D77: Germany | F77: 400 | G77: 0.04 | H77: 12.814165 | I77: in Spain | K77: 456 | L77: 2015 | M77: GBP | N77: 0.266 | O77: 10.4 | P77: =O77*(1/(INDEX(Currency!$A$1:$E$20,MATCH(L77,Currency!$A$1:$A$20,0),MATCH(M77,Currency!$A$1:$E$1,0))))*(Inflation!$B$23/(VLOOKUP(L77,Inflation!$A$1:$B$23,2,FALSE))) -> 14.615646 | Q77: UK | R77: Solar PV, No progress | T77: 457 | U77: 2015 | V77: EUR | W77: 0.35 | X77: 21.3 | Y77: =X77*(1/(INDEX(Currency!$A$1:$E$20,MATCH(U77,Currency!$A$1:$A$20,0),MATCH(V77,Currency!$A$1:$E$1,0))))*(Inflation!$B$23/(VLOOKUP(U77,Inflation!$A$1:$B$23,2,FALSE))) -> 21.71961 | Z77: Various | AA77: Wind, Fig 13
A78: 374 | B78: 0.1 | C78: 6.17971 | D78: Korea | F78: 400 | G78: 0.06 | H78: 12.814165 | I78: in Spain | K78: 456 | L78: 2015 | M78: GBP | N78: 0.37 | O78: 28.9 | P78: =O78*(1/(INDEX(Currency!$A$1:$E$20,MATCH(L78,Currency!$A$1:$A$20,0),MATCH(M78,Currency!$A$1:$E$1,0))))*(Inflation!$B$23/(VLOOKUP(L78,Inflation!$A$1:$B$23,2,FALSE))) -> 40.614631 | Q78: UK | R78: Solar PV, No progress | T78: 457 | U78: 2015 | V78: EUR | W78: 0.354 | X78: 20.6 | Y78: =X78*(1/(INDEX(Currency!$A$1:$E$20,MATCH(U78,Currency!$A$1:$A$20,0),MATCH(V78,Currency!$A$1:$E$1,0))))*(Inflation!$B$23/(VLOOKUP(U78,Inflation!$A$1:$B$23,2,FALSE))) -> 21.00582 | Z78: Various | AA78: Wind, Fig 13
A79: 374 | B79: 0.3 | C79: 11.460406 | D79: Korea | F79: 400 | G79: 0.08 | H79: 12.814165 | I79: in Spain | K79: 456 | L79: 2015 | M79: GBP | N79: 0.505 | O79: 43.5 | P79: =O79*(1/(INDEX(Currency!$A$1:$E$20,MATCH(L79,Currency!$A$1:$A$20,0),MATCH(M79,Currency!$A$1:$E$1,0))))*(Inflation!$B$23/(VLOOKUP(L79,Inflation!$A$1:$B$23,2,FALSE))) -> 61.132748 | Q79: UK | R79: Solar PV, No progress | T79: 457 | U79: 2015 | V79: EUR | W79: 0.392 | X79: 17 | Y79: =X79*(1/(INDEX(Currency!$A$1:$E$20,MATCH(U79,Currency!$A$1:$A$20,0),MATCH(V79,Currency!$A$1:$E$1,0))))*(Inflation!$B$23/(VLOOKUP(U79,Inflation!$A$1:$B$23,2,FALSE))) -> 17.3349 | Z79: Various | AA79: Wind, Fig 13
A80: 374 | B80: 0.1 | C80: 6.17971 | D80: Korea | F80: 400 | G80: 0.1 | H80: 12.814165 | I80: in Spain | K80: 456 | L80: 2015 | M80: GBP | N80: 0.265 | O80: 9.7 | P80: =O80*(1/(INDEX(Currency!$A$1:$E$20,MATCH(L80,Currency!$A$1:$A$20,0),MATCH(M80,Currency!$A$1:$E$1,0))))*(Inflation!$B$23/(VLOOKUP(L80,Inflation!$A$1:$B$23,2,FALSE))) -> 13.6319 | Q80: UK | R80: Solar PV, Moderate progress | T80: 457 | U80: 2015 | V80: EUR | W80: 0.4 | X80: 19 | Y80: =X80*(1/(INDEX(Currency!$A$1:$E$20,MATCH(U80,Currency!$A$1:$A$20,0),MATCH(V80,Currency!$A$1:$E$1,0))))*(Inflation!$B$23/(VLOOKUP(U80,Inflation!$A$1:$B$23,2,FALSE))) -> 19.3743 | Z80: Various | AA80: Wind, Fig 13
A81: 374 | B81: 0.3 | C81: 11.460406 | D81: Korea | F81: 400 | G81: 0.12 | H81: 13.121705 | I81: in Spain | K81: 456 | L81: 2015 | M81: GBP | N81: 0.37 | O81: 11.2 | P81: =O81*(1/(INDEX(Currency!$A$1:$E$20,MATCH(L81,Currency!$A$1:$A$20,0),MATCH(M81,Currency!$A$1:$E$1,0))))*(Inflation!$B$23/(VLOOKUP(L81,Inflation!$A$1:$B$23,2,FALSE))) -> 15.739926 | Q81: UK | R81: Solar PV, Moderate progress | T81: 457 | U81: 2015 | V81: EUR | W81: 0.4 | X81: 20.6 | Y81: =X81*(1/(INDEX(Currency!$A$1:$E$20,MATCH(U81,Currency!$A$1:$A$20,0),MATCH(V81,Currency!$A$1:$E$1,0))))*(Inflation!$B$23/(VLOOKUP(U81,Inflation!$A$1:$B$23,2,FALSE))) -> 21.00582 | Z81: Various | AA81: Wind, Fig 13
A82: 374 | B82: 0.1 | C82: 6.17971 | D82: Korea | F82: 400 | G82: 0.14 | H82: 13.224218 | I82: in Spain | K82: 456 | L82: 2015 | M82: GBP | N82: 0.47 | O82: 17.4 | P82: =O82*(1/(INDEX(Currency!$A$1:$E$20,MATCH(L82,Currency!$A$1:$A$20,0),MATCH(M82,Currency!$A$1:$E$1,0))))*(Inflation!$B$23/(VLOOKUP(L82,Inflation!$A$1:$B$23,2,FALSE))) -> 24.453099 | Q82: UK | R82: Solar PV, Moderate progress | T82: 457 | U82: 2015 | V82: EUR | W82: 0.4 | X82: 21.2 | Y82: =X82*(1/(INDEX(Currency!$A$1:$E$20,MATCH(U82,Currency!$A$1:$A$20,0),MATCH(V82,Currency!$A$1:$E$1,0))))*(Inflation!$B$23/(VLOOKUP(U82,Inflation!$A$1:$B$23,2,FALSE))) -> 21.61764 | Z82: Various | AA82: Wind, Fig 13
A83: 374 | B83: 0.3 | C83: 11.460406 | D83: Korea | F83: 400 | G83: 0.16 | H83: 13.326732 | I83: in Spain | K83: 456 | L83: 2015 | M83: GBP | N83: 0.265 | O83: 7 | P83: =O83*(1/(INDEX(Currency!$A$1:$E$20,MATCH(L83,Currency!$A$1:$A$20,0),MATCH(M83,Currency!$A$1:$E$1,0))))*(Inflation!$B$23/(VLOOKUP(L83,Inflation!$A$1:$B$23,2,FALSE))) -> 9.8374538 | Q83: UK | R83: Solar PV, Fast progress | T83: 459 | U83: 2015 | V83: EUR | W83: 0.25 | X83: 11 | Y83: =X83*(1/(INDEX(Currency!$A$1:$E$20,MATCH(U83,Currency!$A$1:$A$20,0),MATCH(V83,Currency!$A$1:$E$1,0))))*(Inflation!$B$24/(VLOOKUP(U83,Inflation!$A$1:$B$24,2,FALSE))) -> 11.4543 | Z83: Germany | AA83: Wind, from text
A84: 374 | B84: 0.1 | C84: 6.17971 | D84: UK | F84: 400 | G84: 0.18 | H84: 13.326732 | I84: in Spain | K84: 456 | L84: 2015 | M84: GBP | N84: 0.278 | O84: 12.3 | P84: =O84*(1/(INDEX(Currency!$A$1:$E$20,MATCH(L84,Currency!$A$1:$A$20,0),MATCH(M84,Currency!$A$1:$E$1,0))))*(Inflation!$B$23/(VLOOKUP(L84,Inflation!$A$1:$B$23,2,FALSE))) -> 17.285812 | Q84: UK | R84: Solar PV, Fast progress | T84: 459 | U84: 2015 | V84: EUR | W84: 0.1 | X84: 1.5 | Y84: =X84*(1/(INDEX(Currency!$A$1:$E$20,MATCH(U84,Currency!$A$1:$A$20,0),MATCH(V84,Currency!$A$1:$E$1,0))))*(Inflation!$B$24/(VLOOKUP(U84,Inflation!$A$1:$B$24,2,FALSE))) -> 1.56195 | Z84: Germany | AA84: Solar, from text
A85: 374 | B85: 0.3 | C85: 11.460406 | D85: UK | F85: 400 | G85: 0.02 | H85: 6.7658792 | I85: in Spain | K85: 456 | L85: 2015 | M85: GBP | N85: 0.355 | O85: 12.7 | P85: =O85*(1/(INDEX(Currency!$A$1:$E$20,MATCH(L85,Currency!$A$1:$A$20,0),MATCH(M85,Currency!$A$1:$E$1,0))))*(Inflation!$B$23/(VLOOKUP(L85,Inflation!$A$1:$B$23,2,FALSE))) -> 17.847952 | Q85: UK | R85: Solar PV, Fast progress | T85: 460 | U85: 2014 | V85: EUR | W85: 0.15 | X85: 3.8 | Y85: =X85*(1/(INDEX(Currency!$A$1:$E$20,MATCH(U85,Currency!$A$1:$A$20,0),MATCH(V85,Currency!$A$1:$E$1,0))))*(Inflation!$B$24/(VLOOKUP(U85,Inflation!$A$1:$B$24,2,FALSE))) -> 3.9565443 | Z85: Nordic | AA85: Table 4
A86: 374 | B86: 0.1 | C86: 6.17971 | D86: UK | F86: 400 | G86: 0.04 | H86: 6.7658792 | I86: in Spain | K86: 456 | L86: 2015 | M86: GBP | N86: 0.37 | O86: 8.1 | P86: =O86*(1/(INDEX(Currency!$A$1:$E$20,MATCH(L86,Currency!$A$1:$A$20,0),MATCH(M86,Currency!$A$1:$E$1,0))))*(Inflation!$B$23/(VLOOKUP(L86,Inflation!$A$1:$B$23,2,FALSE))) -> 11.383339 | Q86: UK | R86: Solar PV, Fast progress | T86: 460 | U86: 2014 | V86: EUR | W86: 0.2 | X86: 3.5 | Y86: =X86*(1/(INDEX(Currency!$A$1:$E$20,MATCH(U86,Currency!$A$1:$A$20,0),MATCH(V86,Currency!$A$1:$E$1,0))))*(Inflation!$B$24/(VLOOKUP(U86,Inflation!$A$1:$B$24,2,FALSE))) -> 3.6441856 | Z86: Nordic | AA86: Table 4
A87: 374 | B87: 0.3 | C87: 11.460406 | D87: UK | F87: 400 | G87: 0.06 | H87: 6.7658792 | I87: in Spain | K87: 456 | L87: 2015 | M87: GBP | N87: 0.415 | O87: 13.3 | P87: =O87*(1/(INDEX(Currency!$A$1:$E$20,MATCH(L87,Currency!$A$1:$A$20,0),MATCH(M87,Currency!$A$1:$E$1,0))))*(Inflation!$B$23/(VLOOKUP(L87,Inflation!$A$1:$B$23,2,FALSE))) -> 18.691162 | Q87: UK | R87: Solar PV, Fast progress | T87: 460 | U87: 2014 | V87: EUR | W87: 0.15 | X87: 0.1 | Y87: =X87*(1/(INDEX(Currency!$A$1:$E$20,MATCH(U87,Currency!$A$1:$A$20,0),MATCH(V87,Currency!$A$1:$E$1,0))))*(Inflation!$B$24/(VLOOKUP(U87,Inflation!$A$1:$B$24,2,FALSE))) -> 0.10411959 | Z87: Nordic | AA87: Table 4
A88: 374 | B88: 0.1 | C88: 6.17971 | D88: UK | F88: 400 | G88: 0.08 | H88: 8.303579 | I88: in Spain | K88: 456 | L88: 2015 | M88: GBP | N88: 0.46 | O88: 13.6 | P88: =O88*(1/(INDEX(Currency!$A$1:$E$20,MATCH(L88,Currency!$A$1:$A$20,0),MATCH(M88,Currency!$A$1:$E$1,0))))*(Inflation!$B$23/(VLOOKUP(L88,Inflation!$A$1:$B$23,2,FALSE))) -> 19.112767 | Q88: UK | R88: Solar PV, Fast progress | T88: 460 | U88: 2014 | V88: EUR | W88: 0.2 | X88: 0.4 | Y88: =X88*(1/(INDEX(Currency!$A$1:$E$20,MATCH(U88,Currency!$A$1:$A$20,0),MATCH(V88,Currency!$A$1:$E$1,0))))*(Inflation!$B$24/(VLOOKUP(U88,Inflation!$A$1:$B$24,2,FALSE))) -> 0.41647835 | Z88: Nordic | AA88: Table 4
A89: 374 | B89: 0.3 | C89: 11.460406 | D89: UK | F89: 400 | G89: 0.1 | H89: 8.303579 | I89: in Spain | K89: 456 | L89: 2015 | M89: GBP | N89: 0.46 | O89: 14.4 | P89: =O89*(1/(INDEX(Currency!$A$1:$E$20,MATCH(L89,Currency!$A$1:$A$20,0),MATCH(M89,Currency!$A$1:$E$1,0))))*(Inflation!$B$23/(VLOOKUP(L89,Inflation!$A$1:$B$23,2,FALSE))) -> 20.237048 | Q89: UK | R89: Solar PV, Fast progress | T89: 460 | U89: 2014 | V89: EUR | W89: 0.15 | X89: 0 | Y89: =X89*(1/(INDEX(Currency!$A$1:$E$20,MATCH(U89,Currency!$A$1:$A$20,0),MATCH(V89,Currency!$A$1:$E$1,0))))*(Inflation!$B$24/(VLOOKUP(U89,Inflation!$A$1:$B$24,2,FALSE))) -> 0 | Z89: Nordic | AA89: Table 4
A90: 374 | B90: 0.1 | C90: 1.6198454 | D90: US | F90: 400 | G90: 0.12 | H90: 8.303579 | I90: in Spain | K90: 456 | L90: 2015 | M90: GBP | N90: 0.539 | O90: 14.6 | P90: =O90*(1/(INDEX(Currency!$A$1:$E$20,MATCH(L90,Currency!$A$1:$A$20,0),MATCH(M90,Currency!$A$1:$E$1,0))))*(Inflation!$B$23/(VLOOKUP(L90,Inflation!$A$1:$B$23,2,FALSE))) -> 20.518118 | Q90: UK | R90: Solar PV, Fast progress | T90: 460 | U90: 2014 | V90: EUR | W90: 0.2 | X90: 0 | Y90: =X90*(1/(INDEX(Currency!$A$1:$E$20,MATCH(U90,Currency!$A$1:$A$20,0),MATCH(V90,Currency!$A$1:$E$1,0))))*(Inflation!$B$24/(VLOOKUP(U90,Inflation!$A$1:$B$24,2,FALSE))) -> 0 | Z90: Nordic | AA90: Table 4
A91: 374 | B91: 0.3 | C91: 4.0496134 | D91: US | F91: 400 | G91: 0.14 | H91: 8.303579 | I91: in Spain | K91: 456 | L91: 2015 | M91: GBP | N91: 0.539 | O91: 17.1 | P91: =O91*(1/(INDEX(Currency!$A$1:$E$20,MATCH(L91,Currency!$A$1:$A$20,0),MATCH(M91,Currency!$A$1:$E$1,0))))*(Inflation!$B$23/(VLOOKUP(L91,Inflation!$A$1:$B$23,2,FALSE))) -> 24.031494 | Q91: UK | R91: Solar PV, Fast progress
A92: 374 | B92: 0.1 | C92: 1.6198454 | D92: US | F92: 400 | G92: 0.16 | H92: 8.303579 | I92: in Spain | K92: 456 | L92: 2015 | M92: GBP | N92: 0.561 | O92: 22.5 | P92: =O92*(1/(INDEX(Currency!$A$1:$E$20,MATCH(L92,Currency!$A$1:$A$20,0),MATCH(M92,Currency!$A$1:$E$1,0))))*(Inflation!$B$23/(VLOOKUP(L92,Inflation!$A$1:$B$23,2,FALSE))) -> 31.620387 | Q92: UK | R92: Solar PV, Fast progress
A93: 374 | B93: 0.3 | C93: 4.0496134 | D93: US | F93: 400 | G93: 0.18 | H93: 8.303579 | I93: in Spain | K93: 456 | L93: 2015 | M93: GBP | N93: 0.602 | O93: 29 | P93: =O93*(1/(INDEX(Currency!$A$1:$E$20,MATCH(L93,Currency!$A$1:$A$20,0),MATCH(M93,Currency!$A$1:$E$1,0))))*(Inflation!$B$23/(VLOOKUP(L93,Inflation!$A$1:$B$23,2,FALSE))) -> 40.755166 | Q93: UK | R93: Solar PV, Fast progress
A94: 374 | B94: 0.1 | C94: 1.6198454 | D94: US | F94: 400 | G94: 0.02 | H94: 12.096572 | I94: in Germany | K94: 456 | L94: 2015 | M94: GBP | N94: 0.602 | O94: 27.3 | P94: =O94*(1/(INDEX(Currency!$A$1:$E$20,MATCH(L94,Currency!$A$1:$A$20,0),MATCH(M94,Currency!$A$1:$E$1,0))))*(Inflation!$B$23/(VLOOKUP(L94,Inflation!$A$1:$B$23,2,FALSE))) -> 38.36607 | Q94: UK | R94: Solar PV, Fast progress
A95: 374 | B95: 0.3 | C95: 4.0496134 | D95: US | F95: 400 | G95: 0.04 | H95: 12.096572 | I95: in Germany | K95: 456 | L95: 2015 | M95: GBP | N95: 0.452 | O95: 8.1 | P95: =O95*(1/(INDEX(Currency!$A$1:$E$20,MATCH(L95,Currency!$A$1:$A$20,0),MATCH(M95,Currency!$A$1:$E$1,0))))*(Inflation!$B$23/(VLOOKUP(L95,Inflation!$A$1:$B$23,2,FALSE))) -> 11.383339 | Q95: UK | R95: Solar PV, Maximum progress
A96: 133 | B96: 0.05 | C96: 1.4953179 | D96: UK | F96: 400 | G96: 0.06 | H96: 12.609138 | I96: in Germany | K96: 456 | L96: 2015 | M96: GBP | N96: 0.454 | O96: 11.8 | P96: =O96*(1/(INDEX(Currency!$A$1:$E$20,MATCH(L96,Currency!$A$1:$A$20,0),MATCH(M96,Currency!$A$1:$E$1,0))))*(Inflation!$B$23/(VLOOKUP(L96,Inflation!$A$1:$B$23,2,FALSE))) -> 16.583136 | Q96: UK | R96: Solar PV, Maximum progress
A97: 133 | B97: 0.1 | C97: 2.5099979 | D97: UK | F97: 400 | G97: 0.08 | H97: 12.711652 | I97: in Germany | K97: 456 | L97: 2015 | M97: GBP | N97: 0.528 | O97: 5.8 | P97: =O97*(1/(INDEX(Currency!$A$1:$E$20,MATCH(L97,Currency!$A$1:$A$20,0),MATCH(M97,Currency!$A$1:$E$1,0))))*(Inflation!$B$23/(VLOOKUP(L97,Inflation!$A$1:$B$23,2,FALSE))) -> 8.1510331 | Q97: UK | R97: Solar PV, Maximum progress
A98: 133 | B98: 0.15 | C98: 3.1401676 | D98: UK | F98: 400 | G98: 0.1 | H98: 12.916678 | I98: in Germany | K98: 456 | L98: 2015 | M98: GBP | N98: 0.53 | O98: 10.4 | P98: =O98*(1/(INDEX(Currency!$A$1:$E$20,MATCH(L98,Currency!$A$1:$A$20,0),MATCH(M98,Currency!$A$1:$E$1,0))))*(Inflation!$B$23/(VLOOKUP(L98,Inflation!$A$1:$B$23,2,FALSE))) -> 14.615646 | Q98: UK | R98: Solar PV, Maximum progress
A99: 133 | B99: 0.2 | C99: 3.5674013 | D99: UK | F99: 400 | G99: 0.12 | H99: 13.019192 | I99: in Germany | K99: 456 | L99: 2015 | M99: GBP | N99: 0.589 | O99: 10 | P99: =O99*(1/(INDEX(Currency!$A$1:$E$20,MATCH(L99,Currency!$A$1:$A$20,0),MATCH(M99,Currency!$A$1:$E$1,0))))*(Inflation!$B$23/(VLOOKUP(L99,Inflation!$A$1:$B$23,2,FALSE))) -> 14.053505 | Q99: UK | R99: Solar PV, Maximum progress
A100: 133 | B100: 0.054 | C100: 3.0333592 | D100: Colorado | F100: 400 | G100: 0.14 | H100: 13.121705 | I100: in Germany | K100: 456 | L100: 2015 | M100: GBP | N100: 0.59 | O100: 14.6 | P100: =O100*(1/(INDEX(Currency!$A$1:$E$20,MATCH(L100,Currency!$A$1:$A$20,0),MATCH(M100,Currency!$A$1:$E$1,0))))*(Inflation!$B$23/(VLOOKUP(L100,Inflation!$A$1:$B$23,2,FALSE))) -> 20.518118 | Q100: UK | R100: Solar PV, Maximum progress
A101: 133 | B101: 0.075 | C101: 4.0694009 | D101: Colorado | F101: 400 | G101: 0.16 | H101: 13.121705 | I101: in Germany | K101: 461 | L101: 2009 | M101: EUR | N101: 0.189 | O101: 10.8 | P101: =O101*(1/(INDEX(Currency!$A$1:$E$20,MATCH(L101,Currency!$A$1:$A$20,0),MATCH(M101,Currency!$A$1:$E$1,0))))*(Inflation!$B$23/(VLOOKUP(L101,Inflation!$A$1:$B$23,2,FALSE))) -> 12.140624 | Q101: Europe | R101: Solar 20, Wind 80
A102: 133 | B102: 0.15 | C102: 2.4672745 | D102: Minesota | F102: 400 | G102: 0.18 | H102: 13.121705 | I102: in Germany | K102: 461 | L102: 2009 | M102: EUR | N102: 0.189 | O102: 12.1 | P102: =O102*(1/(INDEX(Currency!$A$1:$E$20,MATCH(L102,Currency!$A$1:$A$20,0),MATCH(M102,Currency!$A$1:$E$1,0))))*(Inflation!$B$23/(VLOOKUP(L102,Inflation!$A$1:$B$23,2,FALSE))) -> 13.601995 | Q102: Europe | R102: Solar 50, Wind 50
... A115: 133 | B115: 0.196 | C115: 0.87582906 | D115: SWE | F115: 400 | G115: 0.08 | H115: 14.864431 | I115: In Europe | K115: 461 | L115: 2009 | M115: EUR | N115: 0.762 | O115: 39.7 | P115: =O115*(1/(INDEX(Currency!$A$1:$E$20,MATCH(L115,Currency!$A$1:$A$20,0),MATCH(M115,Currency!$A$1:$E$1,0))))*(Inflation!$B$23/(VLOOKUP(L115,Inflation!$A$1:$B$23,2,FALSE))) -> 44.628034 | Q115: Europe | R115: Solar 80, Wind 20
A116: 118 | B116: 0.35 | C116: 2.642851 | D116: GER | F116: 400 | G116: 0.1 | H116: 14.864431 | I116: In Europe
A117: 118 | B117: 0.35 | C117: 6.3868898 | D117: GER | F117: 400 | G117: 0.12 | H117: 14.864431 | I117: In Europe
A118: 118 | B118: 0.19 | C118: 2.9732073 | D118: UK | F118: 400 | G118: 0.14 | H118: 14.864431 | I118: In Europe
A119: 118 | B119: 0.19 | C119: 5.2857019 | D119: UK | F119: 400 | G119: 0.16 | H119: 14.864431 | I119: In Europe
A120: 118 | B120: 0.25 | C120: -0.11011879 | D120: US | F120: 400 | G120: 0.18 | H120: 14.864431 | I120: In Europe
A121: 118 | B121: 0.25 | C121: 0.22023758 | D121: US | F121: 400 | G121: 0.02 | H121: 9.0211722 | I121: In Europe
A122: 118 | B122: 0.2 | C122: 3.7440389 | D122: US | F122: 400 | G122: 0.04 | H122: 9.0211722 | I122: In Europe
A123: 118 | B123: 0.25 | C123: 0.55059395 | D123: US | F123: 400 | G123: 0.06 | H123: 9.0211722 | I123: In Europe
...

Sheet Inflation
A1: Year | B1: Inflation
A2: 1996 | E2: Note: Data from the Office for National Statistics, document 'CPI-Consumer Prices Index (COICOP)'
A3: 1997 | E3: http://www.ons.gov.uk/ons/rel/cpi/consumer-price-indices/october-2015/index.html
A4: 1998
A5: 1999 | E5: original data: | L5: November 2015 GDP deflator values from:
A6: 2000 | B6: 74.73 | E6: Jan 1996 | G6: 86.8 | L6: https://www.gov.uk/government/statistics/gdp-deflators-at-market-prices-and-money-gdp-november-2015-the-autumn-statement
A7: 2001 | B7: 76.37 | E7: Feb 1996 | G7: 87.2 | L7: Year | M7: Index
A8: 2002 | B8: 77.96 | E8: Mar 1996 | G8: 87.5 | L8: 1955 | M8: 4.434
A9: 2003 | B9: 79.49 | E9: Apr 1996 | G9: 88 | L9: 1956 | M9: 4.734
A10: 2004 | B10: 81.09 | E10: May 1996 | G10: 88.3 | L10: 1957 | M10: 4.922
A11: 2005 | B11: 82.85 | E11: Jun 1996 | G11: 88.4 | L11: 1958 | M11: 5.099 | Q11: Eurozone harmonized index of consumer prices from:
A12: 2006 | B12: 84.67 | E12: Jul 1996 | G12: 87.8 | L12: 1959 | M12: 5.131 | Q12: https://ec.europa.eu/eurostat/web/hicp/data/database
A13: 2007 | B13: 86.65 | E13: Aug 1996 | G13: 88.3 | L13: 1960 | M13: 5.179
A14: 2008 | B14: 89.82 | E14: Sep 1996 | G14: 88.7 | L14: 1961 | M14: 5.355 | Q14: 2000 | R14: 74.73
A15: 2009 | B15: 90.71 | E15: Oct 1996 | G15: 88.7 | L15: 1962 | M15: 5.536 | Q15: 2001 | R15: 76.37
A16: 2010 | B16: 92.6 | E16: Nov 1996 | G16: 88.7 | L16: 1963 | M16: 5.622 | Q16: 2002 | R16: 77.96
A17: 2011 | B17: 95.47 | E17: Dec 1996 | G17: 89 | L17: 1964 | M17: 5.808 | Q17: 2003 | R17: 79.49
A18: 2012 | B18: 97.99 | E18: Jan 1997 | G18: 88.6 | L18: 1965 | M18: 6.134 | Q18: 2004 | R18: 81.09
A19: 2013 | B19: 99.47 | E19: Feb 1997 | G19: 88.8 | L19: 1966 | M19: 6.44 | Q19: 2005 | R19: 82.85
A20: 2014 | B20: 100.01 | E20: Mar 1997 | G20: 89 | L20: 1967 | M20: 6.618 | Q20: 2006 | R20: 84.67
A21: 2015 | B21: 100 | E21: Apr 1997 | G21: 89.4 | L21: 1968 | M21: 6.876 | Q21: 2007 | R21: 86.65
A22: 2016 | B22: 100.25 | E22: May 1997 | G22: 89.6 | L22: 1969 | M22: 7.29 | Q22: 2008 | R22: 89.82
A23: 2017 | B23: 101.97 | E23: Jun 1997 | G23: 89.8 | L23: 1970 | M23: 7.961 | Q23: 2009 | R23: 90.71
A24: 2018 | B24: 104.13 | E24: Jul 1997 | G24: 89.5 | L24: 1971 | M24: 8.6 | Q24: 2010 | R24: 92.6
E25: Aug 1997 | G25: 90 | L25: 1972 | M25: 9.225 | Q25: 2011 | R25: 95.47
E26: Sep 1997 | G26: 90.3 | L26: 1973 | M26: 10.006 | Q26: 2012 | R26: 97.99
E27: Oct 1997 | G27: 90.3 | L27: 1974 | M27: 11.514 | Q27: 2013 | R27: 99.47
E28: Nov 1997 | G28: 90.4 | L28: 1975 | M28: 14.497 | Q28: 2014 | R28: 100.01
E29: Dec 1997 | G29: 90.5 | L29: 1976 | M29: 16.658 | Q29: 2015 | R29: 100
E30: Jan 1998 | G30: 89.9 | L30: 1977 | M30: 18.92 | Q30: 2016 | R30: 100.25
E31: Feb 1998 | G31: 90.3 | L31: 1978 | M31: 21.101 | Q31: 2017 | R31: 101.97
E32: Mar 1998 | G32: 90.5 | L32: 1979 | M32: 24.086 | Q32: 2018 | R32: 104.13
E33: Apr 1998 | G33: 91 | L33: 1980 | M33: 28.896
E34: May 1998 | G34: 91.5 | L34: 1981 | M34: 32.238
E35: Jun 1998 | G35: 91.3 | L35: 1982 | M35: 34.603
E36: Jul 1998 | G36: 90.8 | L36: 1983 | M36: 36.381
E37: Aug 1998 | G37: 91.2 | L37: 1984 | M37: 38.218
E38: Sep 1998 | G38: 91.6 | L38: 1985 | M38: 40.415
E39: Oct 1998 | G39: 91.6 | L39: 1986 | M39: 42.169
E40: Nov 1998 | G40: 91.7 | L40: 1987 | M40: 44.365
E41: Dec 1998 | G41: 91.9 | L41: 1988 | M41: 47
E42: Jan 1999 | G42: 91.4 | L42: 1989 | M42: 50.769
E43: Feb 1999 | G43: 91.5 | L43: 1990 | M43: 54.891
E44: Mar 1999 | G44: 92 | L44: 1991 | M44: 58.493
... E68: Mar 2001 | G68: 93.4 | L68: 2015 | M68: 101.2
E69: Apr 2001 | G69: 94
E70: May 2001 | G70: 94.7
E71: Jun 2001 | G71: 94.9
E72: Jul 2001 | G72: 94.2
E73: Aug 2001 | G73: 94.5
E74: Sep 2001 | G74: 94.8
E75: Oct 2001 | G75: 94.7
E76: Nov 2001 | G76: 94.5
E77: Dec 2001 | G77: 94.7
E78: Jan 2002 | G78: 94.4
E79: Feb 2002 | G79: 94.5
E80: Mar 2002 | G80: 94.9
... E243: Oct 2015 | G243: 128.4

Sheet Currency
A1: Year | B1: USD | C1: EUR | D1: CAD | E1: GBP
A2: 2000 | B2: 0.92260382 | C2: 1 | D2: 1.3695652 | E2: 0.60893923
A3: 2001 | B3: 0.89513272 | C3: 1 | D3: 1.3861503 | E3: 0.62161994
A4: 2002 | B4: 0.94506254 | C4: 1 | D4: 1.4840028 | E4: 0.62857502
A5: 2003 | B5: 1.1312258 | C5: 1 | D5: 1.5825263 | E5: 0.69175429
A6: 2004 | B6: 1.2431644 | C6: 1 | D6: 1.6168668 | E6: 0.67847208 | H6: Note: Exchange rate data is "spot exchange rate against £ sterling" from Bank of England "Statistical Interactive Database "
A7: 2005 | B7: 1.2433522 | C7: 1 | D7: 1.5071433 | E7: 0.68357372 | H7: http://www.bankofengland.co.uk/mfsd/iadb/index.asp?Travel=NIxIRx&levels=2&XNotes=Y&A3790XNode3790.x=2&A3790XNode3790.y=7&Nodes=&SectionRequired=I&HideNums=-1&ExtraInfo=true#BM
A8: 2006 | B8: 1.2563054 | C8: 1 | D8: 1.4246762 | E8: 0.68166326
A9: 2007 | B9: 1.3695875 | C9: 1 | D9: 1.4684315 | E9: 0.68404132 | H9: (Annual average exchange rates)
A10: 2008 | B10: 1.471878 | C10: 1 | D10: 1.5587067 | E10: 0.79440737
A11: 2009 | B11: 1.3945518 | C11: 1 | D11: 1.5846168 | E11: 0.89023413
A12: 2010 | B12: 1.3254458 | C12: 1 | D12: 1.3653121 | E12: 0.85733882
A13: 2011 | B13: 1.390648 | C13: 1 | D13: 1.3760736 | E13: 0.86752841
A14: 2012 | B14: 1.2848342 | C14: 1 | D14: 1.2838616 | E14: 0.81056983
A15: 2013 | B15: 1.3284647 | C15: 1 | D15: 1.3688859 | E15: 0.84918478
A16: 2014 | B16: 1.3276126 | C16: 1 | D16: 1.4654742 | E16: 0.80573685
A17: 2015 | B17: 1.1091278 | C17: 1 | D17: 1.418662 | E17: 0.7255841
A18: 2016 | B18: 1.1070056 | C18: 1 | D18: 1.4671789 | E18: 0.81746097
A19: 2017 | B19: 1.1292386 | C19: 1 | D19: 1.4646456 | E19: 0.87619381
A20: 2018 | B20: 1.1945807 | C20: 1 | D20: 1.5376754 | E20: 0.88375549

Sheet CPI USA
A1: FRED Graph Observations
A2: Federal Reserve Economic Data
A3: Link: https://fred.stlouisfed.org
A4: Help: https://fredhelp.stlouisfed.org
A5: Economic Research Division
A6: Federal Reserve Bank of St. Louis
A8: CPALTT01USA661S | B8: Consumer Price Indices (CPIs, HICPs), COICOP 1999: Consumer Price Index: Total for United States, Index 2015=100, Annual, Seasonally Adjusted
A10: Frequency: Annual
A11: observation_date | B11: CPALTT01USA661S | D11: Exchange Rate in 2017
A12: 20090 | B12: 11.29666 | D12: 1 euro = | E12: 1.1304 | F12: USD
A13: 20455 | B13: 11.46894
A14: 20821 | B14: 11.85217
A15: 21186 | B15: 12.17564
A16: 21551 | B16: 12.2987
A17: 21916 | B17: 12.47801
A18: 22282 | B18: 12.61161
A19: 22647 | B19: 12.7628
A20: 23012 | B20: 12.92101
A21: 23377 | B21: 13.08626
A22: 23743 | B22: 13.2937
A23: 24108 | B23: 13.69452
A24: 24473 | B24: 14.07424
... A80: 44927 | B80: 128.5569

Sheet OP RES COSTS
A1: Operating reserve Costs
A2: ID | B2: Penetration level | C2: 2017 €/MWh | D2: Region | E2: 2023 USD / MWh | F2: LCOE Solar | G2: Operating Reserve Costs as a % LCOE) | H2: LCOE Solar + Storage | J2: LCOE Wind (Onshore)
A3: 17 | B3: 0.4 | C3: 26.232572 | D3: n/a | E3: =C3*('CPI USA'!$E$12)*('CPI USA'!$B$80/'CPI USA'!$B$74) -> 36.861224 | F3: 23.22 | G3: =E3/$F$3 -> 1.5874773 | H3: 36.27 | J3: 31.07
A4: 17 | B4: 0.8 | C4: 17.657365 | D4: n/a | E4: =C4*('CPI USA'!$E$12)*('CPI USA'!$B$80/'CPI USA'!$B$74) -> 24.8116 | F4: 23.22 | G4: =E4/$F$3 -> 1.0685444
A5: 50 | B5: 0.04 | C5: 0.034407373 | D5: UK | E5: =C5*('CPI USA'!$E$12)*('CPI USA'!$B$80/'CPI USA'!$B$74) -> 0.04834821 | F5: 23.22 | G5: =E5/$F$3 -> 0.0020821796
A6: 50 | B6: 0.08 | C6: 0.13762949 | D6: UK | E6: =C6*('CPI USA'!$E$12)*('CPI USA'!$B$80/'CPI USA'!$B$74) -> 0.19339284 | F6: 23.22 | G6: =E6/$F$3 -> 0.0083287183
A7: 50 | B7: 0.12 | C7: 0.2580553 | D7: UK | E7: =C7*('CPI USA'!$E$12)*('CPI USA'!$B$80/'CPI USA'!$B$74) -> 0.36261158 | F7: 23.22 | G7: =E7/$F$3 -> 0.015616347
A8: 50 | B8: 0.16 | C8: 0.3784811 | D8: UK | E8: =C8*('CPI USA'!$E$12)*('CPI USA'!$B$80/'CPI USA'!$B$74) -> 0.53183031 | F8: 23.22 | G8: =E8/$F$3 -> 0.022903975
A9: 50 | B9: 0.2 | C9: 0.51611059 | D9: UK | E9: =C9*('CPI USA'!$E$12)*('CPI USA'!$B$80/'CPI USA'!$B$74) -> 0.72522315 | F9: 23.22 | G9: =E9/$F$3 -> 0.031232694
A10: 50 | B10: 0.04 | C10: 0.086018432 | D10: UK | E10: =C10*('CPI USA'!$E$12)*('CPI USA'!$B$80/'CPI USA'!$B$74) -> 0.12087053 | F10: 23.22 | G10: =E10/$F$3 -> 0.005205449
A11: 50 | B11: 0.08 | C11: 0.2580553 | D11: UK | E11: =C11*('CPI USA'!$E$12)*('CPI USA'!$B$80/'CPI USA'!$B$74) -> 0.36261158 | F11: 23.22 | G11: =E11/$F$3 -> 0.015616347
A12: 50 | B12: 0.12 | C12: 0.46449953 | D12: UK | E12: =C12*('CPI USA'!$E$12)*('CPI USA'!$B$80/'CPI USA'!$B$74) -> 0.65270084 | F12: 23.22 | G12: =E12/$F$3 -> 0.028109424
A13: 50 | B13: 0.16 | C13: 0.70535114 | D13: UK | E13: =C13*('CPI USA'!$E$12)*('CPI USA'!$B$80/'CPI USA'!$B$74) -> 0.99113831 | F13: 23.22 | G13: =E13/$F$3 -> 0.042684682
A14: 50 | B14: 0.2 | C14: 0.94620275 | D14: UK | E14: =C14*('CPI USA'!$E$12)*('CPI USA'!$B$80/'CPI USA'!$B$74) -> 1.3295758 | F14: 23.22 | G14: =E14/$F$3 -> 0.057259939
A15: 336 | B15: 0.33 | C15: 20.232619 | D15: California | E15: =C15*('CPI USA'!$E$12)*('CPI USA'!$B$80/'CPI USA'!$B$74) -> 28.430271 | F15: 23.22 | G15: =E15/$F$3 -> 1.2243872
... A23: 355 | B23: 0.4 | C23: 5.3891253 | D23: EU | E23: =C23*('CPI USA'!$E$12)*('CPI USA'!$B$80/'CPI USA'!$B$74) -> 7.5726374 | F23: 23.22 | G23: =E23/$F$3 -> 0.32612564
A24: 403 | D24: In UK | E24: =C24*('CPI USA'!$E$12)*('CPI USA'!$B$80/'CPI USA'!$B$74) -> 0
A25: 403 | D25: In UK | E25: =C25*('CPI USA'!$E$12)*('CPI USA'!$B$80/'CPI USA'!$B$74) -> 0
A26: 403 | D26: In UK | E26: =C26*('CPI USA'!$E$12)*('CPI USA'!$B$80/'CPI USA'!$B$74) -> 0
A27: 403 | D27: In UK | E27: =C27*('CPI USA'!$E$12)*('CPI USA'!$B$80/'CPI USA'!$B$74) -> 0
A28: 403 | D28: In UK | E28: =C28*('CPI USA'!$E$12)*('CPI USA'!$B$80/'CPI USA'!$B$74) -> 0
A29: 403 | D29: In UK | E29: =C29*('CPI USA'!$E$12)*('CPI USA'!$B$80/'CPI USA'!$B$74) -> 0
A30: 403 | D30: In UK | E30: =C30*('CPI USA'!$E$12)*('CPI USA'!$B$80/'CPI USA'!$B$74) -> 0
A31: 403 | D31: In UK | E31: =C31*('CPI USA'!$E$12)*('CPI USA'!$B$80/'CPI USA'!$B$74) -> 0
A32: 403 | D32: In UK | E32: =C32*('CPI USA'!$E$12)*('CPI USA'!$B$80/'CPI USA'!$B$74) -> 0
A33: 403 | D33: In UK | E33: =C33*('CPI USA'!$E$12)*('CPI USA'!$B$80/'CPI USA'!$B$74) -> 0
A34: 403 | D34: In UK | E34: =C34*('CPI USA'!$E$12)*('CPI USA'!$B$80/'CPI USA'!$B$74) -> 0
A35: 403 | D35: In UK | E35: =C35*('CPI USA'!$E$12)*('CPI USA'!$B$80/'CPI USA'!$B$74) -> 0
... A41: 403 | D41: In UK | E41: =C41*('CPI USA'!$E$12)*('CPI USA'!$B$80/'CPI USA'!$B$74) -> 0
A42: 413 | B42: 0.271 | C42: 6.4308535 | D42: In UK | E42: =C42*('CPI USA'!$E$12)*('CPI USA'!$B$80/'CPI USA'!$B$74) -> 9.0364428 | F42: 23.22 | G42: =E42/$F$3 -> 0.38916636
A43: 413 | B43: 0.326 | C43: 7.5741164 | D43: In UK | E43: =C43*('CPI USA'!$E$12)*('CPI USA'!$B$80/'CPI USA'!$B$74) -> 10.642921 | F43: 23.22 | G43: =E43/$F$3 -> 0.45835149
A44: 413 | B44: 0.417 | C44: 9.2890106 | D44: In UK | E44: =C44*('CPI USA'!$E$12)*('CPI USA'!$B$80/'CPI USA'!$B$74) -> 13.05264 | F44: 23.22 | G44: =E44/$F$3 -> 0.56212918
A45: 433 | B45: 0.05 | C45: 1.5737846 | D45: UK | E45: =C45*('CPI USA'!$E$12)*('CPI USA'!$B$80/'CPI USA'!$B$74) -> 2.211435 | F45: 23.22 | G45: =E45/$F$3 -> 0.095238371
A46: 433 | B46: 0.1 | C46: 2.6979164 | D46: UK | E46: =C46*('CPI USA'!$E$12)*('CPI USA'!$B$80/'CPI USA'!$B$74) -> 3.7910314 | F46: 23.22 | G46: =E46/$F$3 -> 0.16326578
A47: 433 | B47: 0.15 | C47: 3.2599824 | D47: UK | E47: =C47*('CPI USA'!$E$12)*('CPI USA'!$B$80/'CPI USA'!$B$74) -> 4.5808296 | F47: 23.22 | G47: =E47/$F$3 -> 0.19727948
A48: 433 | B48: 0.2 | C48: 3.8220483 | D48: UK | E48: =C48*('CPI USA'!$E$12)*('CPI USA'!$B$80/'CPI USA'!$B$74) -> 5.3706278 | F48: 23.22 | G48: =E48/$F$3 -> 0.23129319
A49: 433 | B49: 0.053 | C49: 3.1475692 | D49: US | E49: =C49*('CPI USA'!$E$12)*('CPI USA'!$B$80/'CPI USA'!$B$74) -> 4.42287 | F49: 23.22 | G49: =E49/$F$3 -> 0.19047674
A50: 433 | B50: 0.076 | C50: 4.271701 | D50: US | E50: =C50*('CPI USA'!$E$12)*('CPI USA'!$B$80/'CPI USA'!$B$74) -> 6.0024664 | F50: 23.22 | G50: =E50/$F$3 -> 0.25850415
A51: 433 | B51: 0.15 | C51: 2.5855033 | D51: US | E51: =C51*('CPI USA'!$E$12)*('CPI USA'!$B$80/'CPI USA'!$B$74) -> 3.6330717 | F51: 23.22 | G51: =E51/$F$3 -> 0.15646304
A52: 433 | B52: 0.2 | C52: 3.4848087 | D52: US | E52: =C52*('CPI USA'!$E$12)*('CPI USA'!$B$80/'CPI USA'!$B$74) -> 4.8967489 | F52: 23.22 | G52: =E52/$F$3 -> 0.21088496
A53: 433 | B53: 0.25 | C53: 3.8220483 | D53: US | E53: =C53*('CPI USA'!$E$12)*('CPI USA'!$B$80/'CPI USA'!$B$74) -> 5.3706278 | F53: 23.22 | G53: =E53/$F$3 -> 0.23129319
... A130: 278 | B130: 0.1 | C130: 1.1342235 | D130: FIN | E130: =C130*('CPI USA'!$E$12)*('CPI USA'!$B$80/'CPI USA'!$B$74) -> 1.593777 | F130: 23.22 | G130: =E130/$F$3 -> 0.068638112

Sheet Capacity Costs
A1: Capacity Costs
A2: ID | B2: Penetration level | C2: 2017 €/MWh | D2: Region | E2: Costs in Inflation adjusted 2023 USD
A3: 50 | B3: 0.2 | C3: 0.92899907 | D3: UK | E3: =C3*('CPI USA'!$E$12)*('CPI USA'!$B$80/'CPI USA'!$B$74) -> 1.3054017
A4: 400 | B4: 0.02 | C4: 6.1507992 | D4: in Austria | E4: =C4*('CPI USA'!$E$12)*('CPI USA'!$B$80/'CPI USA'!$B$74) -> 8.6429189
A5: 400 | B5: 0.04 | C5: 8.5086056 | D5: in Austria | E5: =C5*('CPI USA'!$E$12)*('CPI USA'!$B$80/'CPI USA'!$B$74) -> 11.956038
A6: 400 | B6: 0.06 | C6: 10.866412 | D6: in Austria | E6: =C6*('CPI USA'!$E$12)*('CPI USA'!$B$80/'CPI USA'!$B$74) -> 15.269157
A7: 400 | B7: 0.08 | C7: 11.994059 | D7: in Austria | E7: =C7*('CPI USA'!$E$12)*('CPI USA'!$B$80/'CPI USA'!$B$74) -> 16.853692
A8: 400 | B8: 0.1 | C8: 12.609138 | D8: in Austria | E8: =C8*('CPI USA'!$E$12)*('CPI USA'!$B$80/'CPI USA'!$B$74) -> 17.717984
A9: 400 | B9: 0.12 | C9: 13.121705 | D9: in Austria | E9: =C9*('CPI USA'!$E$12)*('CPI USA'!$B$80/'CPI USA'!$B$74) -> 18.438227
A10: 400 | B10: 0.14 | C10: 13.531758 | D10: in Austria | E10: =C10*('CPI USA'!$E$12)*('CPI USA'!$B$80/'CPI USA'!$B$74) -> 19.014422
A11: 400 | B11: 0.16 | C11: 13.736785 | D11: in Austria | E11: =C11*('CPI USA'!$E$12)*('CPI USA'!$B$80/'CPI USA'!$B$74) -> 19.302519
A12: 400 | B12: 0.18 | C12: 13.941812 | D12: in Austria | E12: =C12*('CPI USA'!$E$12)*('CPI USA'!$B$80/'CPI USA'!$B$74) -> 19.590616
A13: 400 | B13: 0.02 | C13: 6.1507992 | D13: in Austria | E13: =C13*('CPI USA'!$E$12)*('CPI USA'!$B$80/'CPI USA'!$B$74) -> 8.6429189
A14: 400 | B14: 0.04 | C14: 8.5086056 | D14: in Austria | E14: =C14*('CPI USA'!$E$12)*('CPI USA'!$B$80/'CPI USA'!$B$74) -> 11.956038
... A115: 400 | B115: 0.08 | C115: 14.864431 | D115: In Europe | E115: =C115*('CPI USA'!$E$12)*('CPI USA'!$B$80/'CPI USA'!$B$74) -> 20.887054

Sheet Agg Costs
A1: Aggregated Costs
A2: ID | B2: Year | C2: CCY | D2: Penetration level | E2: 2015 £/MWh | F2: 2017 €/MWh | G2: Region | H2: Notes | K2: Costs in 2023 USD
A3: 403/455 | B3: 2015 | C3: GBP | D3: 0.364 | E3: 6.4 | F3: 8.9942435 | G3: UK | H3: Offshore wind, CCC 2015 | K3: =F3*('CPI USA'!$E$12)*('CPI USA'!$B$80/'CPI USA'!$B$74) -> 12.638442
A4: 403/455 | B4: 2015 | C4: GBP | D4: 0.363 | E4: 13.6 | F4: 19.112767 | G4: UK | H4: Offshore wind, CCC 2015 | K4: =F4*('CPI USA'!$E$12)*('CPI USA'!$B$80/'CPI USA'!$B$74) -> 26.856688
A5: 403/455 | B5: 2015 | C5: GBP | D5: 0.361 | E5: 23 | F5: 32.323062 | G5: UK | H5: Offshore wind, CCC 2015 | K5: =F5*('CPI USA'!$E$12)*('CPI USA'!$B$80/'CPI USA'!$B$74) -> 45.419399
A6: 403/455 | B6: 2015 | C6: GBP | D6: 0.47 | E6: 36.9 | F6: 51.857435 | G6: UK | H6: Offshore wind, CCC 2015 | K6: =F6*('CPI USA'!$E$12)*('CPI USA'!$B$80/'CPI USA'!$B$74) -> 72.868515
A7: 403/455 | B7: 2015 | C7: GBP | D7: 0.48 | E7: 35.4 | F7: 49.749409 | G7: UK | H7: Offshore wind, CCC 2015 | K7: =F7*('CPI USA'!$E$12)*('CPI USA'!$B$80/'CPI USA'!$B$74) -> 69.90638
A8: 403/455 | B8: 2015 | C8: GBP | D8: 0.512 | E8: 13.9 | F8: 19.534373 | G8: UK | H8: Offshore wind, CCC 2015 | K8: =F8*('CPI USA'!$E$12)*('CPI USA'!$B$80/'CPI USA'!$B$74) -> 27.449115
A9: 403/455 | B9: 2015 | C9: GBP | D9: 0.518 | E9: 12.8 | F9: 17.988487 | G9: UK | H9: Offshore wind, CCC 2015 | K9: =F9*('CPI USA'!$E$12)*('CPI USA'!$B$80/'CPI USA'!$B$74) -> 25.276883
A10: 403/455 | B10: 2015 | C10: GBP | D10: 0.513 | E10: 7.1 | F10: 9.9779888 | G10: UK | H10: Offshore wind, CCC 2015 | K10: =F10*('CPI USA'!$E$12)*('CPI USA'!$B$80/'CPI USA'!$B$74) -> 14.020771
A11: 403/455 | B11: 2015 | C11: GBP | D11: 0.519 | E11: 8.2 | F11: 11.523874 | G11: UK | H11: Offshore wind, CCC 2015 | K11: =F11*('CPI USA'!$E$12)*('CPI USA'!$B$80/'CPI USA'!$B$74) -> 16.193003
A12: 456 | B12: 2015 | C12: GBP | D12: 0.266 | E12: 10.6 | F12: 14.896716 | G12: UK | H12: Offshore wind, No progress | K12: =F12*('CPI USA'!$E$12)*('CPI USA'!$B$80/'CPI USA'!$B$74) -> 20.932419
A13: 456 | B13: 2015 | C13: GBP | D13: 0.37 | E13: 31.8 | F13: 44.690147 | G13: UK | H13: Offshore wind, No progress | K13: =F13*('CPI USA'!$E$12)*('CPI USA'!$B$80/'CPI USA'!$B$74) -> 62.797257
A14: 456 | B14: 2015 | C14: GBP | D14: 0.504 | E14: 48.4 | F14: 68.018966 | G14: UK | H14: Offshore wind, No progress | K14: =F14*('CPI USA'!$E$12)*('CPI USA'!$B$80/'CPI USA'!$B$74) -> 95.578214
A15: 456 | B15: 2015 | C15: GBP | D15: 0.266 | E15: 10.2 | F15: 14.334576 | G15: UK | H15: Offshore wind, Moderate progress | K15: =F15*('CPI USA'!$E$12)*('CPI USA'!$B$80/'CPI USA'!$B$74) -> 20.142516
A16: 456 | B16: 2015 | C16: GBP | D16: 0.37 | E16: 11 | F16: 15.458856 | G16: UK | H16: Offshore wind, Moderate progress | K16: =F16*('CPI USA'!$E$12)*('CPI USA'!$B$80/'CPI USA'!$B$74) -> 21.722321
A17: 456 | B17: 2015 | C17: GBP | D17: 0.47 | E17: 11.2 | F17: 15.739926 | G17: UK | H17: Offshore wind, Moderate progress | K17: =F17*('CPI USA'!$E$12)*('CPI USA'!$B$80/'CPI USA'!$B$74) -> 22.117273
A18: 456 | B18: 2015 | C18: GBP | D18: 0.265 | E18: 6.6 | F18: 9.2753136 | G18: UK | H18: Offshore wind, Fast progress | K18: =F18*('CPI USA'!$E$12)*('CPI USA'!$B$80/'CPI USA'!$B$74) -> 13.033393
A19: 456 | B19: 2015 | C19: GBP | D19: 0.279 | E19: 7.4 | F19: 10.399594 | G19: UK | H19: Offshore wind, Fast progress | K19: =F19*('CPI USA'!$E$12)*('CPI USA'!$B$80/'CPI USA'!$B$74) -> 14.613198
A20: 456 | B20: 2015 | C20: GBP | D20: 0.355 | E20: 7.7 | F20: 10.821199 | G20: UK | H20: Offshore wind, Fast progress | K20: =F20*('CPI USA'!$E$12)*('CPI USA'!$B$80/'CPI USA'!$B$74) -> 15.205625
A21: 456 | B21: 2015 | C21: GBP | D21: 0.37 | E21: 7.6 | F21: 10.680664 | G21: UK | H21: Offshore wind, Fast progress | K21: =F21*('CPI USA'!$E$12)*('CPI USA'!$B$80/'CPI USA'!$B$74) -> 15.008149
A22: 456 | B22: 2015 | C22: GBP | D22: 0.415 | E22: 6.5 | F22: 9.1347785 | G22: UK | H22: Offshore wind, Fast progress | K22: =F22*('CPI USA'!$E$12)*('CPI USA'!$B$80/'CPI USA'!$B$74) -> 12.835917
A23: 456 | B23: 2015 | C23: GBP | D23: 0.46 | E23: 7.7 | F23: 10.821199 | G23: UK | H23: Offshore wind, Fast progress | K23: =F23*('CPI USA'!$E$12)*('CPI USA'!$B$80/'CPI USA'!$B$74) -> 15.205625
... A35: 456 | B35: 2015 | C35: GBP | D35: 0.589 | E35: 7.4 | F35: 10.399594 | G35: UK | H35: Offshore wind, Maximum progress | K35: =F35*('CPI USA'!$E$12)*('CPI USA'!$B$80/'CPI USA'!$B$74) -> 14.613198
A36: 403/455 | B36: 2015 | C36: GBP | D36: 0.362 | E36: 23 | F36: 32.323062 | G36: UK | H36: Onshore wind, CCC 2015 | K36: =F36*('CPI USA'!$E$12)*('CPI USA'!$B$80/'CPI USA'!$B$74) -> 45.419399
A37: 403/455 | B37: 2015 | C37: GBP | D37: 0.364 | E37: 13.5 | F37: 18.972232 | G37: UK | H37: Onshore wind, CCC 2015 | K37: =F37*('CPI USA'!$E$12)*('CPI USA'!$B$80/'CPI USA'!$B$74) -> 26.659213
A38: 403/455 | B38: 2015 | C38: GBP | D38: 0.364 | E38: 6.3 | F38: 8.8537084 | G38: UK | H38: Onshore wind, CCC 2015 | K38: =F38*('CPI USA'!$E$12)*('CPI USA'!$B$80/'CPI USA'!$B$74) -> 12.440966
A39: 403/455 | B39: 2015 | C39: GBP | D39: 0.471 | E39: 36.8 | F39: 51.7169 | G39: UK | H39: Onshore wind, CCC 2015 | K39: =F39*('CPI USA'!$E$12)*('CPI USA'!$B$80/'CPI USA'!$B$74) -> 72.671039
A40: 403/455 | B40: 2015 | C40: GBP | D40: 0.48 | E40: 35.4 | F40: 49.749409 | G40: UK | H40: Onshore wind, CCC 2015 | K40: =F40*('CPI USA'!$E$12)*('CPI USA'!$B$80/'CPI USA'!$B$74) -> 69.90638
A41: 403/455 | B41: 2015 | C41: GBP | D41: 0.513 | E41: 13.8 | F41: 19.393837 | G41: UK | H41: Onshore wind, CCC 2015 | K41: =F41*('CPI USA'!$E$12)*('CPI USA'!$B$80/'CPI USA'!$B$74) -> 27.25164
A42: 403/455 | B42: 2015 | C42: GBP | D42: 0.518 | E42: 12.7 | F42: 17.847952 | G42: UK | H42: Onshore wind, CCC 2015 | K42: =F42*('CPI USA'!$E$12)*('CPI USA'!$B$80/'CPI USA'!$B$74) -> 25.079407
A43: 403/455 | B43: 2015 | C43: GBP | D43: 0.514 | E43: 6.9 | F43: 9.6969187 | G43: UK | H43: Onshore wind, CCC 2015 | K43: =F43*('CPI USA'!$E$12)*('CPI USA'!$B$80/'CPI USA'!$B$74) -> 13.62582
A44: 403/455 | B44: 2015 | C44: GBP | D44: 0.519 | E44: 8.1 | F44: 11.383339 | G44: UK | H44: Onshore wind, CCC 2015 | K44: =F44*('CPI USA'!$E$12)*('CPI USA'!$B$80/'CPI USA'!$B$74) -> 15.995528
A45: 456 | B45: 2015 | C45: GBP | D45: 0.266 | E45: 10.9 | F45: 15.318321 | G45: UK | H45: Onshore wind, No progress | K45: =F45*('CPI USA'!$E$12)*('CPI USA'!$B$80/'CPI USA'!$B$74) -> 21.524846
A46: 456 | B46: 2015 | C46: GBP | D46: 0.37 | E46: 22.8 | F46: 32.041992 | G46: UK | H46: Onshore wind, No progress | K46: =F46*('CPI USA'!$E$12)*('CPI USA'!$B$80/'CPI USA'!$B$74) -> 45.024448
A47: 456 | B47: 2015 | C47: GBP | D47: 0.506 | E47: 40.2 | F47: 56.495092 | G47: UK | H47: Onshore wind, No progress | K47: =F47*('CPI USA'!$E$12)*('CPI USA'!$B$80/'CPI USA'!$B$74) -> 79.385211
A48: 456 | B48: 2015 | C48: GBP | D48: 0.266 | E48: 10.3 | F48: 14.475111 | G48: UK | H48: Onshore wind, Moderate progress | K48: =F48*('CPI USA'!$E$12)*('CPI USA'!$B$80/'CPI USA'!$B$74) -> 20.339992
A49: 456 | B49: 2015 | C49: GBP | D49: 0.37 | E49: 11.9 | F49: 16.723671 | G49: UK | H49: Onshore wind, Moderate progress | K49: =F49*('CPI USA'!$E$12)*('CPI USA'!$B$80/'CPI USA'!$B$74) -> 23.499602
A50: 456 | B50: 2015 | C50: GBP | D50: 0.47 | E50: 10.2 | F50: 14.334576 | G50: UK | H50: Onshore wind, Moderate progress | K50: =F50*('CPI USA'!$E$12)*('CPI USA'!$B$80/'CPI USA'!$B$74) -> 20.142516
A51: 456 | B51: 2015 | C51: GBP | D51: 0.266 | E51: 6.5 | F51: 9.1347785 | G51: UK | H51: Onshore wind, Fast progress | K51: =F51*('CPI USA'!$E$12)*('CPI USA'!$B$80/'CPI USA'!$B$74) -> 12.835917
A52: 456 | B52: 2015 | C52: GBP | D52: 0.279 | E52: 7.2 | F52: 10.118524 | G52: UK | H52: Onshore wind, Fast progress | K52: =F52*('CPI USA'!$E$12)*('CPI USA'!$B$80/'CPI USA'!$B$74) -> 14.218247
A53: 456 | B53: 2015 | C53: GBP | D53: 0.356 | E53: 4.8 | F53: 6.7456826 | G53: UK | H53: Onshore wind, Fast progress | K53: =F53*('CPI USA'!$E$12)*('CPI USA'!$B$80/'CPI USA'!$B$74) -> 9.4788312
A54: 456 | B54: 2015 | C54: GBP | D54: 0.37 | E54: 7.5 | F54: 10.540129 | G54: UK | H54: Onshore wind, Fast progress | K54: =F54*('CPI USA'!$E$12)*('CPI USA'!$B$80/'CPI USA'!$B$74) -> 14.810674
A55: 456 | B55: 2015 | C55: GBP | D55: 0.415 | E55: 6.3 | F55: 8.8537084 | G55: UK | H55: Onshore wind, Fast progress | K55: =F55*('CPI USA'!$E$12)*('CPI USA'!$B$80/'CPI USA'!$B$74) -> 12.440966
A56: 456 | B56: 2015 | C56: GBP | D56: 0.46 | E56: 7.2 | F56: 10.118524 | G56: UK | H56: Onshore wind, Fast progress | K56: =F56*('CPI USA'!$E$12)*('CPI USA'!$B$80/'CPI USA'!$B$74) -> 14.218247
... A68: 456 | B68: 2015 | C68: GBP | D68: 0.589 | E68: 8.5 | F68: 11.94548 | G68: UK | H68: Onshore wind, Maximum progress | K68: =F68*('CPI USA'!$E$12)*('CPI USA'!$B$80/'CPI USA'!$B$74) -> 16.78543
A69: 403/455 | B69: 2015 | C69: GBP | D69: 0.361 | E69: 22.9 | F69: 32.182527 | G69: UK | H69: Solar PV, CCC 2015 | K69: =F69*('CPI USA'!$E$12)*('CPI USA'!$B$80/'CPI USA'!$B$74) -> 45.221924
A70: 403/455 | B70: 2015 | C70: GBP | D70: 0.363 | E70: 12 | F70: 16.864206 | G70: UK | H70: Solar PV, CCC 2015 | K70: =F70*('CPI USA'!$E$12)*('CPI USA'!$B$80/'CPI USA'!$B$74) -> 23.697078
A71: 403/455 | B71: 2015 | C71: GBP | D71: 0.364 | E71: 10.4 | F71: 14.615646 | G71: UK | H71: Solar PV, CCC 2015 | K71: =F71*('CPI USA'!$E$12)*('CPI USA'!$B$80/'CPI USA'!$B$74) -> 20.537468
A72: 403/455 | B72: 2015 | C72: GBP | D72: 0.471 | E72: 35.7 | F72: 50.171014 | G72: UK | H72: Solar PV, CCC 2015 | K72: =F72*('CPI USA'!$E$12)*('CPI USA'!$B$80/'CPI USA'!$B$74) -> 70.498807
A73: 403/455 | B73: 2015 | C73: GBP | D73: 0.519 | E73: 25.2 | F73: 35.414834 | G73: UK | H73: Solar PV, CCC 2015 | K73: =F73*('CPI USA'!$E$12)*('CPI USA'!$B$80/'CPI USA'!$B$74) -> 49.763864
A74: 403/455 | B74: 2015 | C74: GBP | D74: 0.518 | E74: 24.4 | F74: 34.290553 | G74: UK | H74: Solar PV, CCC 2015 | K74: =F74*('CPI USA'!$E$12)*('CPI USA'!$B$80/'CPI USA'!$B$74) -> 48.184058
A75: 403/455 | B75: 2015 | C75: GBP | D75: 0.513 | E75: 12.2 | F75: 17.145277 | G75: UK | H75: Solar PV, CCC 2015 | K75: =F75*('CPI USA'!$E$12)*('CPI USA'!$B$80/'CPI USA'!$B$74) -> 24.092029
A76: 403/455 | B76: 2015 | C76: GBP | D76: 0.514 | E76: 11.1 | F76: 15.599391 | G76: UK | H76: Solar PV, CCC 2015 | K76: =F76*('CPI USA'!$E$12)*('CPI USA'!$B$80/'CPI USA'!$B$74) -> 21.919797
A77: 456 | B77: 2015 | C77: GBP | D77: 0.266 | E77: 10.4 | F77: 14.615646 | G77: UK | H77: Solar PV, No progress | K77: =F77*('CPI USA'!$E$12)*('CPI USA'!$B$80/'CPI USA'!$B$74) -> 20.537468
A78: 456 | B78: 2015 | C78: GBP | D78: 0.37 | E78: 28.9 | F78: 40.614631 | G78: UK | H78: Solar PV, No progress | K78: =F78*('CPI USA'!$E$12)*('CPI USA'!$B$80/'CPI USA'!$B$74) -> 57.070463
A79: 456 | B79: 2015 | C79: GBP | D79: 0.505 | E79: 43.5 | F79: 61.132748 | G79: UK | H79: Solar PV, No progress | K79: =F79*('CPI USA'!$E$12)*('CPI USA'!$B$80/'CPI USA'!$B$74) -> 85.901908
A80: 456 | B80: 2015 | C80: GBP | D80: 0.265 | E80: 9.7 | F80: 13.6319 | G80: UK | H80: Solar PV, Moderate progress | K80: =F80*('CPI USA'!$E$12)*('CPI USA'!$B$80/'CPI USA'!$B$74) -> 19.155138
A81: 456 | B81: 2015 | C81: GBP | D81: 0.37 | E81: 11.2 | F81: 15.739926 | G81: UK | H81: Solar PV, Moderate progress | K81: =F81*('CPI USA'!$E$12)*('CPI USA'!$B$80/'CPI USA'!$B$74) -> 22.117273
A82: 456 | B82: 2015 | C82: GBP | D82: 0.47 | E82: 17.4 | F82: 24.453099 | G82: UK | H82: Solar PV, Moderate progress | K82: =F82*('CPI USA'!$E$12)*('CPI USA'!$B$80/'CPI USA'!$B$74) -> 34.360763
A83: 456 | B83: 2015 | C83: GBP | D83: 0.265 | E83: 7 | F83: 9.8374538 | G83: UK | H83: Solar PV, Fast progress | K83: =F83*('CPI USA'!$E$12)*('CPI USA'!$B$80/'CPI USA'!$B$74) -> 13.823295
A84: 456 | B84: 2015 | C84: GBP | D84: 0.278 | E84: 12.3 | F84: 17.285812 | G84: UK | H84: Solar PV, Fast progress | K84: =F84*('CPI USA'!$E$12)*('CPI USA'!$B$80/'CPI USA'!$B$74) -> 24.289505
A85: 456 | B85: 2015 | C85: GBP | D85: 0.355 | E85: 12.7 | F85: 17.847952 | G85: UK | H85: Solar PV, Fast progress | K85: =F85*('CPI USA'!$E$12)*('CPI USA'!$B$80/'CPI USA'!$B$74) -> 25.079407
A86: 456 | B86: 2015 | C86: GBP | D86: 0.37 | E86: 8.1 | F86: 11.383339 | G86: UK | H86: Solar PV, Fast progress | K86: =F86*('CPI USA'!$E$12)*('CPI USA'!$B$80/'CPI USA'!$B$74) -> 15.995528
A87: 456 | B87: 2015 | C87: GBP | D87: 0.415 | E87: 13.3 | F87: 18.691162 | G87: UK | H87: Solar PV, Fast progress | K87: =F87*('CPI USA'!$E$12)*('CPI USA'!$B$80/'CPI USA'!$B$74) -> 26.264261
A88: 456 | B88: 2015 | C88: GBP | D88: 0.46 | E88: 13.6 | F88: 19.112767 | G88: UK | H88: Solar PV, Fast progress | K88: =F88*('CPI USA'!$E$12)*('CPI USA'!$B$80/'CPI USA'!$B$74) -> 26.856688
... A115: 461 | B115: 2009 | C115: EUR | D115: 0.762 | E115: 39.7 | F115: 44.628034 | G115: Europe | H115: Solar 80, Wind 20 | K115: =F115*('CPI USA'!$E$12)*('CPI USA'!$B$80/'CPI USA'!$B$74) -> 62.709978

Sheet Profile Costs
A1: Profile Costs
A2: ID | B2: Year | C2: CCY | D2: Penetration level | E2: Reported value | F2: 2017 €/MWh | G2: Region | H2: Notes | J2: Costs (2023 USD)
A3: 347 | B3: 2001 | C3: EUR | D3: 0.02 | E3: -1 | F3: -1.3352102 | G3: Germany | H3: Wind, Table 3 | J3: =F3*'CPI USA'!$E$12*('CPI USA'!$B$80/'CPI USA'!$B$74) -> -1.8761973
A4: 347 | B4: 2004 | C4: EUR | D4: 0.03 | E4: 0 | F4: 0 | G4: Germany | H4: Wind, Table 3 | J4: =F4*'CPI USA'!$E$12*('CPI USA'!$B$80/'CPI USA'!$B$74) -> 0
A5: 347 | B5: 2005 | C5: EUR | D5: 0.035 | E5: 0 | F5: 0 | G5: Germany | H5: Wind, Table 3 | J5: =F5*'CPI USA'!$E$12*('CPI USA'!$B$80/'CPI USA'!$B$74) -> 0
A6: 347 | B6: 2006 | C6: EUR | D6: 0.047 | E6: 2 | F6: 2.4086453 | G6: Germany | H6: Wind, Table 3 | J6: =F6*'CPI USA'!$E$12*('CPI USA'!$B$80/'CPI USA'!$B$74) -> 3.3845563
A7: 347 | B7: 2007 | C7: EUR | D7: 0.049 | E7: 5 | F7: 5.8840162 | G7: Germany | H7: Wind, Table 3 | J7: =F7*'CPI USA'!$E$12*('CPI USA'!$B$80/'CPI USA'!$B$74) -> 8.2680433
A8: 347 | B8: 2008 | C8: EUR | D8: 0.055 | E8: 6 | F8: 6.8116232 | G8: Germany | H8: Wind, Table 3 | J8: =F8*'CPI USA'!$E$12*('CPI USA'!$B$80/'CPI USA'!$B$74) -> 9.571489
A9: 347 | B9: 2009 | C9: EUR | D9: 0.071 | E9: 3 | F9: 3.3723955 | G9: Germany | H9: Wind, Table 3 | J9: =F9*'CPI USA'!$E$12*('CPI USA'!$B$80/'CPI USA'!$B$74) -> 4.7387892
A10: 347 | B10: 2010 | C10: EUR | D10: 0.073 | E10: 2 | F10: 2.2023758 | G10: Germany | H10: Wind, Table 3 | J10: =F10*'CPI USA'!$E$12*('CPI USA'!$B$80/'CPI USA'!$B$74) -> 3.0947125
A11: 347 | B11: 2011 | C11: EUR | D11: 0.088 | E11: 3 | F11: 3.2042526 | G11: Germany | H11: Wind, Table 3 | J11: =F11*'CPI USA'!$E$12*('CPI USA'!$B$80/'CPI USA'!$B$74) -> 4.5025199
A12: 347 | B12: 2012 | C12: EUR | D12: 0.08 | E12: 5 | F12: 5.2030819 | G12: Germany | H12: Wind, Table 3 | J12: =F12*'CPI USA'!$E$12*('CPI USA'!$B$80/'CPI USA'!$B$74) -> 7.3112149
A13: 347 | B13: 2006 | C13: EUR | D13: 0.004 | E13: -17 | F13: -20.473485 | G13: Germany | H13: Solar, Table 3 | J13: =F13*'CPI USA'!$E$12*('CPI USA'!$B$80/'CPI USA'!$B$74) -> -28.768728
A14: 347 | B14: 2007 | C14: EUR | D14: 0.005 | E14: -6 | F14: -7.0608194 | G14: Germany | H14: Solar, Table 3 | J14: =F14*'CPI USA'!$E$12*('CPI USA'!$B$80/'CPI USA'!$B$74) -> -9.921652
... A90: 460 | B90: 2014 | C90: EUR | D90: 0.2 | E90: 0 | F90: 0 | G90: Nordic | H90: Table 4 | J90: =F90*'CPI USA'!$E$12*('CPI USA'!$B$80/'CPI USA'!$B$74) -> 0

Sheet Agg Costs filtered
A1: Aggregated Costs
A2: ID | B2: Year | C2: CCY | D2: Penetration level | E2: 2015 £/MWh | F2: 2017 €/MWh | G2: Region | H2: Notes | K2: Costs in 2023 USD | M2: Penetration Level
A3: 403/455 | B3: 2015 | C3: GBP | D3: 0.364 | E3: 6.4 | F3: 8.9942435 | G3: UK | H3: Offshore wind, CCC 2015 | K3: =F3*('CPI USA'!$E$12)*('CPI USA'!$B$80/'CPI USA'!$B$74) -> 12.638442
A4: 403/455 | B4: 2015 | C4: GBP | D4: 0.363 | E4: 13.6 | F4: 19.112767 | G4: UK | H4: Offshore wind, CCC 2015 | K4: =F4*('CPI USA'!$E$12)*('CPI USA'!$B$80/'CPI USA'!$B$74) -> 26.856688
A5: 403/455 | B5: 2015 | C5: GBP | D5: 0.361 | E5: 23 | F5: 32.323062 | G5: UK | H5: Offshore wind, CCC 2015 | K5: =F5*('CPI USA'!$E$12)*('CPI USA'!$B$80/'CPI USA'!$B$74) -> 45.419399
A6: 403/455 | B6: 2015 | C6: GBP | D6: 0.47 | E6: 36.9 | F6: 51.857435 | G6: UK | H6: Offshore wind, CCC 2015 | K6: =F6*('CPI USA'!$E$12)*('CPI USA'!$B$80/'CPI USA'!$B$74) -> 72.868515
A7: 403/455 | B7: 2015 | C7: GBP | D7: 0.48 | E7: 35.4 | F7: 49.749409 | G7: UK | H7: Offshore wind, CCC 2015 | K7: =F7*('CPI USA'!$E$12)*('CPI USA'!$B$80/'CPI USA'!$B$74) -> 69.90638
A8: 403/455 | B8: 2015 | C8: GBP | D8: 0.512 | E8: 13.9 | F8: 19.534373 | G8: UK | H8: Offshore wind, CCC 2015 | K8: =F8*('CPI USA'!$E$12)*('CPI USA'!$B$80/'CPI USA'!$B$74) -> 27.449115
A9: 403/455 | B9: 2015 | C9: GBP | D9: 0.518 | E9: 12.8 | F9: 17.988487 | G9: UK | H9: Offshore wind, CCC 2015 | K9: =F9*('CPI USA'!$E$12)*('CPI USA'!$B$80/'CPI USA'!$B$74) -> 25.276883
A10: 403/455 | B10: 2015 | C10: GBP | D10: 0.513 | E10: 7.1 | F10: 9.9779888 | G10: UK | H10: Offshore wind, CCC 2015 | K10: =F10*('CPI USA'!$E$12)*('CPI USA'!$B$80/'CPI USA'!$B$74) -> 14.020771
A11: 403/455 | B11: 2015 | C11: GBP | D11: 0.519 | E11: 8.2 | F11: 11.523874 | G11: UK | H11: Offshore wind, CCC 2015 | K11: =F11*('CPI USA'!$E$12)*('CPI USA'!$B$80/'CPI USA'!$B$74) -> 16.193003
A12: 456 | B12: 2015 | C12: GBP | D12: 0.266 | E12: 10.6 | F12: 14.896716 | G12: UK | H12: Offshore wind, No progress | K12: =F12*('CPI USA'!$E$12)*('CPI USA'!$B$80/'CPI USA'!$B$74) -> 20.932419
A13: 456 | B13: 2015 | C13: GBP | D13: 0.37 | E13: 31.8 | F13: 44.690147 | G13: UK | H13: Offshore wind, No progress | K13: =F13*('CPI USA'!$E$12)*('CPI USA'!$B$80/'CPI USA'!$B$74) -> 62.797257
A14: 456 | B14: 2015 | C14: GBP | D14: 0.504 | E14: 48.4 | F14: 68.018966 | G14: UK | H14: Offshore wind, No progress | K14: =F14*('CPI USA'!$E$12)*('CPI USA'!$B$80/'CPI USA'!$B$74) -> 95.578214
A15: 456 | B15: 2015 | C15: GBP | D15: 0.266 | E15: 10.2 | F15: 14.334576 | G15: UK | H15: Offshore wind, Moderate progress | K15: =F15*('CPI USA'!$E$12)*('CPI USA'!$B$80/'CPI USA'!$B$74) -> 20.142516
A16: 456 | B16: 2015 | C16: GBP | D16: 0.37 | E16: 11 | F16: 15.458856 | G16: UK | H16: Offshore wind, Moderate progress | K16: =F16*('CPI USA'!$E$12)*('CPI USA'!$B$80/'CPI USA'!$B$74) -> 21.722321
A17: 456 | B17: 2015 | C17: GBP | D17: 0.47 | E17: 11.2 | F17: 15.739926 | G17: UK | H17: Offshore wind, Moderate progress | K17: =F17*('CPI USA'!$E$12)*('CPI USA'!$B$80/'CPI USA'!$B$74) -> 22.117273
A18: 456 | B18: 2015 | C18: GBP | D18: 0.265 | E18: 6.6 | F18: 9.2753136 | G18: UK | H18: Offshore wind, Fast progress | K18: =F18*('CPI USA'!$E$12)*('CPI USA'!$B$80/'CPI USA'!$B$74) -> 13.033393
A19: 456 | B19: 2015 | C19: GBP | D19: 0.279 | E19: 7.4 | F19: 10.399594 | G19: UK | H19: Offshore wind, Fast progress | K19: =F19*('CPI USA'!$E$12)*('CPI USA'!$B$80/'CPI USA'!$B$74) -> 14.613198
A20: 456 | B20: 2015 | C20: GBP | D20: 0.355 | E20: 7.7 | F20: 10.821199 | G20: UK | H20: Offshore wind, Fast progress | K20: =F20*('CPI USA'!$E$12)*('CPI USA'!$B$80/'CPI USA'!$B$74) -> 15.205625
A21: 456 | B21: 2015 | C21: GBP | D21: 0.37 | E21: 7.6 | F21: 10.680664 | G21: UK | H21: Offshore wind, Fast progress | K21: =F21*('CPI USA'!$E$12)*('CPI USA'!$B$80/'CPI USA'!$B$74) -> 15.008149
A22: 456 | B22: 2015 | C22: GBP | D22: 0.415 | E22: 6.5 | F22: 9.1347785 | G22: UK | H22: Offshore wind, Fast progress | K22: =F22*('CPI USA'!$E$12)*('CPI USA'!$B$80/'CPI USA'!$B$74) -> 12.835917
A23: 456 | B23: 2015 | C23: GBP | D23: 0.46 | E23: 7.7 | F23: 10.821199 | G23: UK | H23: Offshore wind, Fast progress | K23: =F23*('CPI USA'!$E$12)*('CPI USA'!$B$80/'CPI USA'!$B$74) -> 15.205625
... A35: 456 | B35: 2015 | C35: GBP | D35: 0.589 | E35: 7.4 | F35: 10.399594 | G35: UK | H35: Offshore wind, Maximum progress | K35: =F35*('CPI USA'!$E$12)*('CPI USA'!$B$80/'CPI USA'!$B$74) -> 14.613198
A36: 403/455 | B36: 2015 | C36: GBP | D36: 0.362 | E36: 23 | F36: 32.323062 | G36: UK | H36: Onshore wind, CCC 2015 | K36: =F36*('CPI USA'!$E$12)*('CPI USA'!$B$80/'CPI USA'!$B$74) -> 45.419399
A37: 403/455 | B37: 2015 | C37: GBP | D37: 0.364 | E37: 13.5 | F37: 18.972232 | G37: UK | H37: Onshore wind, CCC 2015 | K37: =F37*('CPI USA'!$E$12)*('CPI USA'!$B$80/'CPI USA'!$B$74) -> 26.659213
A38: 403/455 | B38: 2015 | C38: GBP | D38: 0.364 | E38: 6.3 | F38: 8.8537084 | G38: UK | H38: Onshore wind, CCC 2015 | K38: =F38*('CPI USA'!$E$12)*('CPI USA'!$B$80/'CPI USA'!$B$74) -> 12.440966
A39: 403/455 | B39: 2015 | C39: GBP | D39: 0.471 | E39: 36.8 | F39: 51.7169 | G39: UK | H39: Onshore wind, CCC 2015 | K39: =F39*('CPI USA'!$E$12)*('CPI USA'!$B$80/'CPI USA'!$B$74) -> 72.671039
A40: 403/455 | B40: 2015 | C40: GBP | D40: 0.48 | E40: 35.4 | F40: 49.749409 | G40: UK | H40: Onshore wind, CCC 2015 | K40: =F40*('CPI USA'!$E$12)*('CPI USA'!$B$80/'CPI USA'!$B$74) -> 69.90638
A41: 403/455 | B41: 2015 | C41: GBP | D41: 0.513 | E41: 13.8 | F41: 19.393837 | G41: UK | H41: Onshore wind, CCC 2015 | K41: =F41*('CPI USA'!$E$12)*('CPI USA'!$B$80/'CPI USA'!$B$74) -> 27.25164
A42: 403/455 | B42: 2015 | C42: GBP | D42: 0.518 | E42: 12.7 | F42: 17.847952 | G42: UK | H42: Onshore wind, CCC 2015 | K42: =F42*('CPI USA'!$E$12)*('CPI USA'!$B$80/'CPI USA'!$B$74) -> 25.079407
A43: 403/455 | B43: 2015 | C43: GBP | D43: 0.514 | E43: 6.9 | F43: 9.6969187 | G43: UK | H43: Onshore wind, CCC 2015 | K43: =F43*('CPI USA'!$E$12)*('CPI USA'!$B$80/'CPI USA'!$B$74) -> 13.62582
A44: 403/455 | B44: 2015 | C44: GBP | D44: 0.519 | E44: 8.1 | F44: 11.383339 | G44: UK | H44: Onshore wind, CCC 2015 | K44: =F44*('CPI USA'!$E$12)*('CPI USA'!$B$80/'CPI USA'!$B$74) -> 15.995528
A45: 456 | B45: 2015 | C45: GBP | D45: 0.266 | E45: 10.9 | F45: 15.318321 | G45: UK | H45: Onshore wind, No progress | K45: =F45*('CPI USA'!$E$12)*('CPI USA'!$B$80/'CPI USA'!$B$74) -> 21.524846
A46: 456 | B46: 2015 | C46: GBP | D46: 0.37 | E46: 22.8 | F46: 32.041992 | G46: UK | H46: Onshore wind, No progress | K46: =F46*('CPI USA'!$E$12)*('CPI USA'!$B$80/'CPI USA'!$B$74) -> 45.024448
A47: 456 | B47: 2015 | C47: GBP | D47: 0.506 | E47: 40.2 | F47: 56.495092 | G47: UK | H47: Onshore wind, No progress | K47: =F47*('CPI USA'!$E$12)*('CPI USA'!$B$80/'CPI USA'!$B$74) -> 79.385211
A48: 456 | B48: 2015 | C48: GBP | D48: 0.266 | E48: 10.3 | F48: 14.475111 | G48: UK | H48: Onshore wind, Moderate progress | K48: =F48*('CPI USA'!$E$12)*('CPI USA'!$B$80/'CPI USA'!$B$74) -> 20.339992
A49: 456 | B49: 2015 | C49: GBP | D49: 0.37 | E49: 11.9 | F49: 16.723671 | G49: UK | H49: Onshore wind, Moderate progress | K49: =F49*('CPI USA'!$E$12)*('CPI USA'!$B$80/'CPI USA'!$B$74) -> 23.499602
A50: 456 | B50: 2015 | C50: GBP | D50: 0.47 | E50: 10.2 | F50: 14.334576 | G50: UK | H50: Onshore wind, Moderate progress | K50: =F50*('CPI USA'!$E$12)*('CPI USA'!$B$80/'CPI USA'!$B$74) -> 20.142516
A51: 456 | B51: 2015 | C51: GBP | D51: 0.266 | E51: 6.5 | F51: 9.1347785 | G51: UK | H51: Onshore wind, Fast progress | K51: =F51*('CPI USA'!$E$12)*('CPI USA'!$B$80/'CPI USA'!$B$74) -> 12.835917
A52: 456 | B52: 2015 | C52: GBP | D52: 0.279 | E52: 7.2 | F52: 10.118524 | G52: UK | H52: Onshore wind, Fast progress | K52: =F52*('CPI USA'!$E$12)*('CPI USA'!$B$80/'CPI USA'!$B$74) -> 14.218247
A53: 456 | B53: 2015 | C53: GBP | D53: 0.356 | E53: 4.8 | F53: 6.7456826 | G53: UK | H53: Onshore wind, Fast progress | K53: =F53*('CPI USA'!$E$12)*('CPI USA'!$B$80/'CPI USA'!$B$74) -> 9.4788312
A54: 456 | B54: 2015 | C54: GBP | D54: 0.37 | E54: 7.5 | F54: 10.540129 | G54: UK | H54: Onshore wind, Fast progress | K54: =F54*('CPI USA'!$E$12)*('CPI USA'!$B$80/'CPI USA'!$B$74) -> 14.810674
A55: 456 | B55: 2015 | C55: GBP | D55: 0.415 | E55: 6.3 | F55: 8.8537084 | G55: UK | H55: Onshore wind, Fast progress | K55: =F55*('CPI USA'!$E$12)*('CPI USA'!$B$80/'CPI USA'!$B$74) -> 12.440966
A56: 456 | B56: 2015 | C56: GBP | D56: 0.46 | E56: 7.2 | F56: 10.118524 | G56: UK | H56: Onshore wind, Fast progress | K56: =F56*('CPI USA'!$E$12)*('CPI USA'!$B$80/'CPI USA'!$B$74) -> 14.218247
... A68: 456 | B68: 2015 | C68: GBP | D68: 0.589 | E68: 8.5 | F68: 11.94548 | G68: UK | H68: Onshore wind, Maximum progress | K68: =F68*('CPI USA'!$E$12)*('CPI USA'!$B$80/'CPI USA'!$B$74) -> 16.78543
A69: 461 | B69: 2009 | C69: EUR | D69: 0.189 | E69: 10.8 | F69: 12.140624 | G69: Europe | H69: Solar 20, Wind 80 | K69: =F69*('CPI USA'!$E$12)*('CPI USA'!$B$80/'CPI USA'!$B$74) -> 17.059641 | M69: 0-20 | N69: =AVERAGE(K69:K71) -> 20.376794
A70: 461 | B70: 2009 | C70: EUR | D70: 0.189 | E70: 12.1 | F70: 13.601995 | G70: Europe | H70: Solar 50, Wind 50 | K70: =F70*('CPI USA'!$E$12)*('CPI USA'!$B$80/'CPI USA'!$B$74) -> 19.113117 | M70: 20-40 | N70: =AVERAGE(K72:K85) -> 26.077338
A71: 461 | B71: 2009 | C71: EUR | D71: 0.189 | E71: 15.8 | F71: 17.761283 | G71: Europe | H71: Solar 80, Wind 20 | K71: =F71*('CPI USA'!$E$12)*('CPI USA'!$B$80/'CPI USA'!$B$74) -> 24.957623 | M71: 40-60 | N71: =AVERAGE(K86:K107) -> 33.521823
A72: 456 | B72: 2015 | C72: GBP | D72: 0.265 | E72: 9.7 | F72: 13.6319 | G72: UK | H72: Solar PV, Moderate progress | K72: =F72*('CPI USA'!$E$12)*('CPI USA'!$B$80/'CPI USA'!$B$74) -> 19.155138 | M72: 60-80 | N72: =AVERAGE(K108:K113) -> 47.910292
A73: 456 | B73: 2015 | C73: GBP | D73: 0.265 | E73: 7 | F73: 9.8374538 | G73: UK | H73: Solar PV, Fast progress | K73: =F73*('CPI USA'!$E$12)*('CPI USA'!$B$80/'CPI USA'!$B$74) -> 13.823295 | M73: 80-100 | N73: =AVERAGE(K114:K115) -> 40.358688
A74: 456 | B74: 2015 | C74: GBP | D74: 0.266 | E74: 10.4 | F74: 14.615646 | G74: UK | H74: Solar PV, No progress | K74: =F74*('CPI USA'!$E$12)*('CPI USA'!$B$80/'CPI USA'!$B$74) -> 20.537468 | M74: PV LCOE | N74: 23.22
A75: 456 | B75: 2015 | C75: GBP | D75: 0.278 | E75: 12.3 | F75: 17.285812 | G75: UK | H75: Solar PV, Fast progress | K75: =F75*('CPI USA'!$E$12)*('CPI USA'!$B$80/'CPI USA'!$B$74) -> 24.289505 | M75: PV + Battery LCOE | N75: 36.27
A76: 456 | B76: 2015 | C76: GBP | D76: 0.355 | E76: 12.7 | F76: 17.847952 | G76: UK | H76: Solar PV, Fast progress | K76: =F76*('CPI USA'!$E$12)*('CPI USA'!$B$80/'CPI USA'!$B$74) -> 25.079407 | M76: Wind, Onshore LCOE | N76: =N87 -> 31.07
A77: 403/455 | B77: 2015 | C77: GBP | D77: 0.361 | E77: 22.9 | F77: 32.182527 | G77: UK | H77: Solar PV, CCC 2015 | K77: =F77*('CPI USA'!$E$12)*('CPI USA'!$B$80/'CPI USA'!$B$74) -> 45.221924
A78: 403/455 | B78: 2015 | C78: GBP | D78: 0.363 | E78: 12 | F78: 16.864206 | G78: UK | H78: Solar PV, CCC 2015 | K78: =F78*('CPI USA'!$E$12)*('CPI USA'!$B$80/'CPI USA'!$B$74) -> 23.697078 | M78: resource | N78: LCOE ($/MWh)
A79: 461 | B79: 2009 | C79: EUR | D79: 0.363 | E79: 21.1 | F79: 23.719182 | G79: Europe | H79: Solar 80, Wind 20 | K79: =F79*('CPI USA'!$E$12)*('CPI USA'!$B$80/'CPI USA'!$B$74) -> 33.329484 | M79: Ultra-super critical Coal | N79: 89.33
A80: 403/455 | B80: 2015 | C80: GBP | D80: 0.364 | E80: 10.4 | F80: 14.615646 | G80: UK | H80: Solar PV, CCC 2015 | K80: =F80*('CPI USA'!$E$12)*('CPI USA'!$B$80/'CPI USA'!$B$74) -> 20.537468 | M80: Biomass | N80: 77.16
A81: 456 | B81: 2015 | C81: GBP | D81: 0.37 | E81: 28.9 | F81: 40.614631 | G81: UK | H81: Solar PV, No progress | K81: =F81*('CPI USA'!$E$12)*('CPI USA'!$B$80/'CPI USA'!$B$74) -> 57.070463 | M81: Advanced nuclear | N81: 71
A82: 456 | B82: 2015 | C82: GBP | D82: 0.37 | E82: 11.2 | F82: 15.739926 | G82: UK | H82: Solar PV, Moderate progress | K82: =F82*('CPI USA'!$E$12)*('CPI USA'!$B$80/'CPI USA'!$B$74) -> 22.117273 | M82: Combined cycle | N82: 42.72
A83: 456 | B83: 2015 | C83: GBP | D83: 0.37 | E83: 8.1 | F83: 11.383339 | G83: UK | H83: Solar PV, Fast progress | K83: =F83*('CPI USA'!$E$12)*('CPI USA'!$B$80/'CPI USA'!$B$74) -> 15.995528 | M83: Geothermal | N83: 37.3
A84: 461 | B84: 2009 | C84: EUR | D84: 0.375 | E84: 13.4 | F84: 15.063367 | G84: Europe | H84: Solar 20, Wind 80 | K84: =F84*('CPI USA'!$E$12)*('CPI USA'!$B$80/'CPI USA'!$B$74) -> 21.166592 | M84: Wind, offshore | N84: 100.34
A85: 461 | B85: 2009 | C85: EUR | D85: 0.375 | E85: 14.6 | F85: 16.412325 | G85: Europe | H85: Solar 50, Wind 50 | K85: =F85*('CPI USA'!$E$12)*('CPI USA'!$B$80/'CPI USA'!$B$74) -> 23.062108 | M85: Hydroelectric | N85: 57.12
A86: 456 | B86: 2015 | C86: GBP | D86: 0.415 | E86: 13.3 | F86: 18.691162 | G86: UK | H86: Solar PV, Fast progress | K86: =F86*('CPI USA'!$E$12)*('CPI USA'!$B$80/'CPI USA'!$B$74) -> 26.264261 | M86: PV-battery hybrid | N86: 36.27
A87: 456 | B87: 2015 | C87: GBP | D87: 0.452 | E87: 8.1 | F87: 11.383339 | G87: UK | H87: Solar PV, Maximum progress | K87: =F87*('CPI USA'!$E$12)*('CPI USA'!$B$80/'CPI USA'!$B$74) -> 15.995528 | M87: Wind, Onshore | N87: 31.07
A88: 456 | B88: 2015 | C88: GBP | D88: 0.454 | E88: 11.8 | F88: 16.583136 | G88: UK | H88: Solar PV, Maximum progress | K88: =F88*('CPI USA'!$E$12)*('CPI USA'!$B$80/'CPI USA'!$B$74) -> 23.302127 | M88: Solar PV | N88: 23.22
A89: 456 | B89: 2015 | C89: GBP | D89: 0.46 | E89: 13.6 | F89: 19.112767 | G89: UK | H89: Solar PV, Fast progress | K89: =F89*('CPI USA'!$E$12)*('CPI USA'!$B$80/'CPI USA'!$B$74) -> 26.856688
A90: 456 | B90: 2015 | C90: GBP | D90: 0.46 | E90: 14.4 | F90: 20.237048 | G90: UK | H90: Solar PV, Fast progress | K90: =F90*('CPI USA'!$E$12)*('CPI USA'!$B$80/'CPI USA'!$B$74) -> 28.436494
A91: 456 | B91: 2015 | C91: GBP | D91: 0.47 | E91: 17.4 | F91: 24.453099 | G91: UK | H91: Solar PV, Moderate progress | K91: =F91*('CPI USA'!$E$12)*('CPI USA'!$B$80/'CPI USA'!$B$74) -> 34.360763
A92: 403/455 | B92: 2015 | C92: GBP | D92: 0.471 | E92: 35.7 | F92: 50.171014 | G92: UK | H92: Solar PV, CCC 2015 | K92: =F92*('CPI USA'!$E$12)*('CPI USA'!$B$80/'CPI USA'!$B$74) -> 70.498807
A93: 456 | B93: 2015 | C93: GBP | D93: 0.505 | E93: 43.5 | F93: 61.132748 | G93: UK | H93: Solar PV, No progress | K93: =F93*('CPI USA'!$E$12)*('CPI USA'!$B$80/'CPI USA'!$B$74) -> 85.901908
A94: 403/455 | B94: 2015 | C94: GBP | D94: 0.513 | E94: 12.2 | F94: 17.145277 | G94: UK | H94: Solar PV, CCC 2015 | K94: =F94*('CPI USA'!$E$12)*('CPI USA'!$B$80/'CPI USA'!$B$74) -> 24.092029
A95: 403/455 | B95: 2015 | C95: GBP | D95: 0.514 | E95: 11.1 | F95: 15.599391 | G95: UK | H95: Solar PV, CCC 2015 | K95: =F95*('CPI USA'!$E$12)*('CPI USA'!$B$80/'CPI USA'!$B$74) -> 21.919797
A96: 403/455 | B96: 2015 | C96: GBP | D96: 0.518 | E96: 24.4 | F96: 34.290553 | G96: UK | H96: Solar PV, CCC 2015 | K96: =F96*('CPI USA'!$E$12)*('CPI USA'!$B$80/'CPI USA'!$B$74) -> 48.184058
A97: 403/455 | B97: 2015 | C97: GBP | D97: 0.519 | E97: 25.2 | F97: 35.414834 | G97: UK | H97: Solar PV, CCC 2015 | K97: =F97*('CPI USA'!$E$12)*('CPI USA'!$B$80/'CPI USA'!$B$74) -> 49.763864
A98: 456 | B98: 2015 | C98: GBP | D98: 0.528 | E98: 5.8 | F98: 8.1510331 | G98: UK | H98: Solar PV, Maximum progress | K98: =F98*('CPI USA'!$E$12)*('CPI USA'!$B$80/'CPI USA'!$B$74) -> 11.453588
A99: 456 | B99: 2015 | C99: GBP | D99: 0.53 | E99: 10.4 | F99: 14.615646 | G99: UK | H99: Solar PV, Maximum progress | K99: =F99*('CPI USA'!$E$12)*('CPI USA'!$B$80/'CPI USA'!$B$74) -> 20.537468
A100: 461 | B100: 2009 | C100: EUR | D100: 0.533 | E100: 26.3 | F100: 29.564668 | G100: Europe | H100: Solar 80, Wind 20 | K100: =F100*('CPI USA'!$E$12)*('CPI USA'!$B$80/'CPI USA'!$B$74) -> 41.543386
A101: 456 | B101: 2015 | C101: GBP | D101: 0.539 | E101: 14.6 | F101: 20.518118 | G101: UK | H101: Solar PV, Fast progress | K101: =F101*('CPI USA'!$E$12)*('CPI USA'!$B$80/'CPI USA'!$B$74) -> 28.831445
A102: 456 | B102: 2015 | C102: GBP | D102: 0.539 | E102: 17.1 | F102: 24.031494 | G102: UK | H102: Solar PV, Fast progress | K102: =F102*('CPI USA'!$E$12)*('CPI USA'!$B$80/'CPI USA'!$B$74) -> 33.768336
A103: 461 | B103: 2009 | C103: EUR | D103: 0.553 | E103: 17.5 | F103: 19.672307 | G103: Europe | H103: Solar 50, Wind 50 | K103: =F103*('CPI USA'!$E$12)*('CPI USA'!$B$80/'CPI USA'!$B$74) -> 27.642937
A104: 461 | B104: 2009 | C104: EUR | D104: 0.559 | E104: 15.9 | F104: 17.873696 | G104: Europe | H104: Solar 20, Wind 80 | K104: =F104*('CPI USA'!$E$12)*('CPI USA'!$B$80/'CPI USA'!$B$74) -> 25.115583
A105: 456 | B105: 2015 | C105: GBP | D105: 0.561 | E105: 22.5 | F105: 31.620387 | G105: UK | H105: Solar PV, Fast progress | K105: =F105*('CPI USA'!$E$12)*('CPI USA'!$B$80/'CPI USA'!$B$74) -> 44.432021
A106: 456 | B106: 2015 | C106: GBP | D106: 0.589 | E106: 10 | F106: 14.053505 | G106: UK | H106: Solar PV, Maximum progress | K106: =F106*('CPI USA'!$E$12)*('CPI USA'!$B$80/'CPI USA'!$B$74) -> 19.747565
A107: 456 | B107: 2015 | C107: GBP | D107: 0.59 | E107: 14.6 | F107: 20.518118 | G107: UK | H107: Solar PV, Maximum progress | K107: =F107*('CPI USA'!$E$12)*('CPI USA'!$B$80/'CPI USA'!$B$74) -> 28.831445
A108: 456 | B108: 2015 | C108: GBP | D108: 0.602 | E108: 29 | F108: 40.755166 | G108: UK | H108: Solar PV, Fast progress | K108: =F108*('CPI USA'!$E$12)*('CPI USA'!$B$80/'CPI USA'!$B$74) -> 57.267938
A109: 456 | B109: 2015 | C109: GBP | D109: 0.602 | E109: 27.3 | F109: 38.36607 | G109: UK | H109: Solar PV, Fast progress | K109: =F109*('CPI USA'!$E$12)*('CPI USA'!$B$80/'CPI USA'!$B$74) -> 53.910852
... A115: 461 | B115: 2009 | C115: EUR | D115: 0.831 | E115: 24.3 | F115: 27.316404 | G115: Europe | H115: Solar 20, Wind 80 | K115: =F115*('CPI USA'!$E$12)*('CPI USA'!$B$80/'CPI USA'!$B$74) -> 38.384193

Sheet Capacity Credit
A1: ID | B1: Penetration levels | C1: Capacity credit | D1: Type of Variable Energy
A2: 50 | B2: 0.04 | C2: 0.34 | D2: Wind
A3: 50 | B3: 0.08 | C3: 0.3 | D3: wind
A4: 50 | B4: 0.12 | C4: 0.26 | D4: wind
A5: 50 | B5: 0.16 | C5: 0.23 | D5: wind
A6: 50 | B6: 0.2 | C6: 0.2 | D6: wind
A7: 133 | B7: 0.016 | C7: 0.345 | D7: wind
A8: 133 | B8: 0.28 | C8: 0.149 | D8: wind
A9: 133 | B9: 0.28 | C9: 0.103 | D9: wind
A10: 133 | B10: 0.072 | C10: 0.341 | D10: wind
A11: 133 | B11: 0.142 | C11: 0.302 | D11: wind
A12: 133 | B12: 0.214 | C12: 0.26 | D12: wind
A13: 133 | B13: 0.286 | C13: 0.231 | D13: wind
... A382: 400 | B382: 0.18 | C382: 0.026 | D382: Solar PV

Sheet Curtailment
B3: Reference ID | C3: Penetration levels | D3: Energy spilling and curtailment | F3: Regional information
B4: 87 | C4: 0.12 | D4: 0.003 | F4: US
B5: 87 | C5: 0.15 | D5: 0.01 | F5: US
B6: 87 | C6: 0.195 | D6: 0.038 | F6: US
B7: 87 | C7: 0.23 | D7: 0.1 | F7: US
B8: 87 | C8: 0.255 | D8: 0.193 | F8: US
B9: 87 | C9: 0.269 | D9: 0.289 | F9: US
B10: 87 | C10: 0.281 | D10: 0.429 | F10: US
B11: 87 | C11: 0.233 | D11: 0.003 | F11: US
B12: 87 | C12: 0.293 | D12: 0.016 | F12: US
B13: 87 | C13: 0.358 | D13: 0.047 | F13: US
B14: 87 | C14: 0.428 | D14: 0.112 | F14: US
B15: 87 | C15: 0.472 | D15: 0.202 | F15: US
... B184: 1488 | C184: 0.111 | D184: 0.056 | F184: GB
B187: Note: ID 1488 not on References worksheet - see Joos, M. & Staffell, I. 2018. Short-term integration costs of variable renewable energy: Wind curtailment and balancing in Britain and Germany. Renewable and Sustainable Energy Reviews, 86, 45-65.
